
--- get_display ---
 22           0 LOAD_FAST                0 (text)
              2 RETURN_VALUE

--- get_clinical_conclusion ---
101           0 LOAD_FAST                0 (tst_hours)
              2 LOAD_CONST               1 (0)
              4 COMPARE_OP               4 (>)
              6 POP_JUMP_IF_FALSE       16 (to 32)
              8 LOAD_FAST                0 (tst_hours)
             10 LOAD_CONST               2 (4.0)
             12 COMPARE_OP               0 (<)
             14 POP_JUMP_IF_FALSE       16 (to 32)

102          16 LOAD_FAST                5 (lang)
             18 LOAD_CONST               3 ('he')
             20 COMPARE_OP               2 (==)
             22 POP_JUMP_IF_FALSE       14 (to 28)

103          24 LOAD_CONST               4 ('משך השינה היה קצר, דבר העלול להפחית את מהימנות התוצאות.\nהערה: נדרשת בדיקת רופא (Send to review by a physician).')
             26 RETURN_VALUE

105     >>   28 LOAD_CONST               5 ('The sleep duration was short, which may reduce the reliability of the results.\nNote: Send to review by a physician.')
             30 RETURN_VALUE

106     >>   32 LOAD_FAST                1 (pahi)
             34 LOAD_CONST               6 (5)
             36 COMPARE_OP               0 (<)
             38 POP_JUMP_IF_FALSE       64 (to 128)

107          40 LOAD_FAST                2 (t90_pct)
             42 LOAD_CONST               7 (1.0)
             44 COMPARE_OP               1 (<=)
             46 POP_JUMP_IF_FALSE       36 (to 72)
             48 LOAD_FAST                4 (min_sat)
             50 LOAD_CONST               8 (90)
             52 COMPARE_OP               5 (>=)
             54 POP_JUMP_IF_FALSE       36 (to 72)

108          56 LOAD_FAST                5 (lang)
             58 LOAD_CONST               3 ('he')
             60 COMPARE_OP               2 (==)
             62 POP_JUMP_IF_FALSE       34 (to 68)
             64 LOAD_CONST               9 ('בדיקת השינה תקינה.')
             66 RETURN_VALUE
        >>   68 LOAD_CONST              10 ('The sleep study is normal.')
             70 RETURN_VALUE

109     >>   72 LOAD_FAST                2 (t90_pct)
             74 LOAD_CONST              11 (5.0)
             76 COMPARE_OP               4 (>)
             78 POP_JUMP_IF_TRUE        48 (to 96)
             80 LOAD_FAST                3 (avg_sat)
             82 LOAD_CONST              12 (94)
             84 COMPARE_OP               0 (<)
             86 POP_JUMP_IF_TRUE        48 (to 96)
             88 LOAD_FAST                4 (min_sat)
             90 LOAD_CONST              13 (85)
             92 COMPARE_OP               0 (<)
             94 POP_JUMP_IF_FALSE       56 (to 112)

110     >>   96 LOAD_FAST                5 (lang)
             98 LOAD_CONST               3 ('he')
            100 COMPARE_OP               2 (==)
            102 POP_JUMP_IF_FALSE       54 (to 108)

111         104 LOAD_CONST              14 ('בדיקת השינה מצביעה על הפרעת נשימה בשינה בדרגה קלה, עם דה-סטורציה לילית שאינה פרופורציונלית.\nהמלצות: המשך הערכה/טיפול במסגרת מרפאת שינה.')
            106 RETURN_VALUE

113     >>  108 LOAD_CONST              15 ('The sleep study indicates mild sleep-disordered breathing, with disproportionate nocturnal desaturation.\nRecommendations: continue evaluation/treatment within a sleep clinic.')
            110 RETURN_VALUE

115     >>  112 LOAD_FAST                5 (lang)
            114 LOAD_CONST               3 ('he')
            116 COMPARE_OP               2 (==)
            118 POP_JUMP_IF_FALSE       62 (to 124)

116         120 LOAD_CONST              16 ('בדיקת השינה אינה מצביעה על הפרעת נשימה משמעותית בשינה לפי קריטריון AHI. עם זאת, נצפתה ירידה בריווי החמצן בדם בלילה.\nהמלצות: המשך הערכה/טיפול במסגרת מרפאת שינה.')
            122 RETURN_VALUE

118     >>  124 LOAD_CONST              17 ('The sleep study does not indicate significant sleep-disordered breathing according to AHI criteria. However, a drop in blood oxygen saturation was observed at night.\nRecommendations: continue evaluation/treatment within a sleep clinic.')
            126 RETURN_VALUE

120     >>  128 LOAD_FAST                1 (pahi)
            130 LOAD_CONST              18 (15)
            132 COMPARE_OP               0 (<)
            134 POP_JUMP_IF_FALSE       76 (to 152)

121         136 LOAD_FAST                5 (lang)
            138 LOAD_CONST               3 ('he')
            140 COMPARE_OP               2 (==)
            142 POP_JUMP_IF_FALSE       74 (to 148)

122         144 LOAD_CONST              19 ('בדיקת השינה מצביעה על הפרעת נשימה בשינה בדרגה קלה.\nהמלצות: המשך הערכה/טיפול במסגרת מרפאת שינה.')
            146 RETURN_VALUE

124     >>  148 LOAD_CONST              20 ('The sleep study indicates mild sleep-disordered breathing.\nRecommendations: continue evaluation/treatment within a sleep clinic.')
            150 RETURN_VALUE

125     >>  152 LOAD_FAST                1 (pahi)
            154 LOAD_CONST              21 (30)
            156 COMPARE_OP               1 (<=)
            158 POP_JUMP_IF_FALSE       88 (to 176)

126         160 LOAD_FAST                5 (lang)
            162 LOAD_CONST               3 ('he')
            164 COMPARE_OP               2 (==)
            166 POP_JUMP_IF_FALSE       86 (to 172)

127         168 LOAD_CONST              22 ('בדיקת השינה מצביעה על הפרעת נשימה בשינה בדרגה בינונית.\nהמלצות: המשך הערכה/טיפול במסגרת מרפאת שינה.')
            170 RETURN_VALUE

129     >>  172 LOAD_CONST              23 ('The sleep study indicates moderate sleep-disordered breathing.\nRecommendations: continue evaluation/treatment within a sleep clinic.')
            174 RETURN_VALUE

131     >>  176 LOAD_FAST                5 (lang)
            178 LOAD_CONST               3 ('he')
            180 COMPARE_OP               2 (==)
            182 POP_JUMP_IF_FALSE       94 (to 188)

132         184 LOAD_CONST              24 ('בדיקת השינה מצביעה על הפרעת נשימה בשינה בדרגה חמורה.\nהמלצות: המשך הערכה/טיפול במסגרת מרפאת שינה.')
            186 RETURN_VALUE

134     >>  188 LOAD_CONST              25 ('The sleep study indicates severe sleep-disordered breathing.\nRecommendations: continue evaluation/treatment within a sleep clinic.')
            190 RETURN_VALUE

--- _t ---
137           0 LOAD_FAST                1 (lang)
              2 LOAD_CONST               1 ('he')
              4 COMPARE_OP               3 (!=)
              6 POP_JUMP_IF_FALSE        6 (to 12)

138           8 LOAD_FAST                0 (text)
             10 RETURN_VALUE

140     >>   12 LOAD_GLOBAL              0 (TRANSLATIONS)
             14 LOAD_METHOD              1 (get)
             16 LOAD_FAST                0 (text)
             18 LOAD_FAST                0 (text)
             20 CALL_METHOD              2
             22 STORE_FAST               2 (translated)

142          24 LOAD_GLOBAL              2 (get_display)
             26 LOAD_FAST                2 (translated)
             28 CALL_FUNCTION            1
             30 RETURN_VALUE

--- _x ---
145           0 LOAD_FAST                1 (lang)
              2 LOAD_CONST               1 ('he')
              4 COMPARE_OP               2 (==)
              6 POP_JUMP_IF_FALSE        8 (to 16)
              8 LOAD_CONST               2 (1.0)
             10 LOAD_FAST                0 (val)
             12 BINARY_SUBTRACT
             14 RETURN_VALUE
        >>   16 LOAD_FAST                0 (val)
             18 RETURN_VALUE

--- _ha ---
148           0 LOAD_FAST                1 (lang)
              2 LOAD_CONST               1 ('he')
              4 COMPARE_OP               2 (==)
              6 POP_JUMP_IF_FALSE       18 (to 36)

149           8 LOAD_FAST                0 (align)
             10 LOAD_CONST               2 ('left')
             12 COMPARE_OP               2 (==)
             14 POP_JUMP_IF_FALSE       10 (to 20)
             16 LOAD_CONST               3 ('right')
             18 RETURN_VALUE
        >>   20 LOAD_FAST                0 (align)
             22 LOAD_CONST               3 ('right')
             24 COMPARE_OP               2 (==)
             26 POP_JUMP_IF_FALSE       16 (to 32)
             28 LOAD_CONST               2 ('left')
             30 RETURN_VALUE
        >>   32 LOAD_FAST                0 (align)
             34 RETURN_VALUE

150     >>   36 LOAD_FAST                0 (align)
             38 RETURN_VALUE

--- _fmt ---
155           0 LOAD_GLOBAL              0 (int)
              2 LOAD_FAST                0 (s)
              4 LOAD_CONST               1 (3600)
              6 BINARY_FLOOR_DIVIDE
              8 CALL_FUNCTION            1
             10 FORMAT_VALUE             0
             12 LOAD_CONST               2 ('h ')
             14 LOAD_GLOBAL              0 (int)
             16 LOAD_FAST                0 (s)
             18 LOAD_CONST               1 (3600)
             20 BINARY_MODULO
             22 LOAD_CONST               3 (60)
             24 BINARY_FLOOR_DIVIDE
             26 CALL_FUNCTION            1
             28 LOAD_CONST               4 ('02d')
             30 FORMAT_VALUE             4 (with format)
             32 LOAD_CONST               5 ('m')
             34 BUILD_STRING             4
             36 RETURN_VALUE

--- _qcol ---
158           0 LOAD_FAST                0 (v)
              2 LOAD_CONST               1 (80)
              4 COMPARE_OP               5 (>=)
              6 POP_JUMP_IF_FALSE        6 (to 12)
              8 LOAD_GLOBAL              0 (C_GOOD)
             10 RETURN_VALUE
        >>   12 LOAD_FAST                0 (v)
             14 LOAD_CONST               2 (60)
             16 COMPARE_OP               5 (>=)
             18 POP_JUMP_IF_FALSE       12 (to 24)
             20 LOAD_GLOBAL              1 (C_WARN)
             22 RETURN_VALUE
        >>   24 LOAD_GLOBAL              2 (C_BAD)
             26 RETURN_VALUE

--- _stats ---
161           0 LOAD_GLOBAL              0 (np)
              2 LOAD_ATTR                1 (asarray)
              4 LOAD_DEREF               0 (h)
              6 LOAD_GLOBAL              2 (int)
              8 LOAD_CONST               1 (('dtype',))
             10 CALL_FUNCTION_KW         2
             12 STORE_DEREF              0 (h)

162          14 LOAD_GLOBAL              3 (len)
             16 LOAD_DEREF               0 (h)
             18 CALL_FUNCTION            1
             20 STORE_FAST               1 (tib)

163          22 LOAD_CLOSURE             0 (h)
             24 BUILD_TUPLE              1
             26 LOAD_CONST               2 (<code object <listcomp> at 0x0000026C8AA31D10, file "patient_report.py", line 163>)
             28 LOAD_CONST               3 ('_stats.<locals>.<listcomp>')
             30 MAKE_FUNCTION            8 (closure)
             32 LOAD_CONST               4 ((0, 1, 2, 3, 4))
             34 GET_ITER
             36 CALL_FUNCTION            1
             38 UNPACK_SEQUENCE          5
             40 STORE_FAST               2 (wake)
             42 STORE_FAST               3 (n1)
             44 STORE_FAST               4 (n2)
             46 STORE_FAST               5 (n3)
             48 STORE_FAST               6 (rem)

164          50 LOAD_GLOBAL              2 (int)
             52 LOAD_FAST                3 (n1)
             54 LOAD_FAST                4 (n2)
             56 BINARY_ADD
             58 LOAD_FAST                5 (n3)
             60 BINARY_ADD
             62 LOAD_FAST                6 (rem)
             64 BINARY_ADD
             66 CALL_FUNCTION            1
             68 STORE_FAST               7 (tst)

165          70 LOAD_FAST                7 (tst)
             72 LOAD_GLOBAL              4 (max)
             74 LOAD_FAST                1 (tib)
             76 LOAD_CONST               5 (1)
             78 CALL_FUNCTION            2
             80 BINARY_TRUE_DIVIDE
             82 LOAD_CONST               6 (100)
             84 BINARY_MULTIPLY
             86 STORE_FAST               8 (se)

166          88 LOAD_GLOBAL              0 (np)
             90 LOAD_METHOD              5 (where)
             92 LOAD_DEREF               0 (h)
             94 LOAD_CONST               7 (0)
             96 COMPARE_OP               4 (>)
             98 CALL_METHOD              1
            100 LOAD_CONST               7 (0)
            102 BINARY_SUBSCR
            104 STORE_FAST               9 (nw)

167         106 LOAD_GLOBAL              3 (len)
            108 LOAD_FAST                9 (nw)
            110 CALL_FUNCTION            1
            112 POP_JUMP_IF_FALSE       63 (to 126)
            114 LOAD_GLOBAL              2 (int)
            116 LOAD_FAST                9 (nw)
            118 LOAD_CONST               7 (0)
            120 BINARY_SUBSCR
            122 CALL_FUNCTION            1
            124 JUMP_FORWARD             1 (to 128)
        >>  126 LOAD_FAST                1 (tib)
        >>  128 STORE_FAST              10 (sol)

168         130 LOAD_GLOBAL              2 (int)
            132 LOAD_DEREF               0 (h)
            134 LOAD_FAST               10 (sol)
            136 LOAD_CONST               0 (None)
            138 BUILD_SLICE              2
            140 BINARY_SUBSCR
            142 LOAD_CONST               7 (0)
            144 COMPARE_OP               2 (==)
            146 LOAD_METHOD              6 (sum)
            148 CALL_METHOD              0
            150 CALL_FUNCTION            1
            152 STORE_FAST              11 (waso)

169         154 LOAD_GLOBAL              4 (max)
            156 LOAD_FAST                7 (tst)
            158 LOAD_CONST               5 (1)
            160 CALL_FUNCTION            2
            162 STORE_FAST              12 (d)

170         164 LOAD_GLOBAL              7 (dict)
            166 LOAD_FAST                1 (tib)
            168 LOAD_FAST                7 (tst)
            170 LOAD_FAST                8 (se)
            172 LOAD_FAST               10 (sol)
            174 LOAD_FAST               11 (waso)

171         176 LOAD_FAST                3 (n1)
            178 LOAD_FAST               12 (d)
            180 BINARY_TRUE_DIVIDE
            182 LOAD_CONST               6 (100)
            184 BINARY_MULTIPLY
            186 LOAD_FAST                4 (n2)
            188 LOAD_FAST               12 (d)
            190 BINARY_TRUE_DIVIDE
            192 LOAD_CONST               6 (100)
            194 BINARY_MULTIPLY
            196 LOAD_FAST                5 (n3)
            198 LOAD_FAST               12 (d)
            200 BINARY_TRUE_DIVIDE
            202 LOAD_CONST               6 (100)
            204 BINARY_MULTIPLY
            206 LOAD_FAST                6 (rem)
            208 LOAD_FAST               12 (d)
            210 BINARY_TRUE_DIVIDE
            212 LOAD_CONST               6 (100)
            214 BINARY_MULTIPLY

172         216 LOAD_FAST                2 (wake)
            218 LOAD_GLOBAL              4 (max)
            220 LOAD_FAST                1 (tib)
            222 LOAD_CONST               5 (1)
            224 CALL_FUNCTION            2
            226 BINARY_TRUE_DIVIDE
            228 LOAD_CONST               6 (100)
            230 BINARY_MULTIPLY

170         232 LOAD_CONST               8 (('TIB', 'TST', 'SE', 'SOL', 'WASO', 'N1', 'N2', 'N3', 'REM', 'Wake'))
            234 CALL_FUNCTION_KW        10
            236 RETURN_VALUE

Disassembly of <code object <listcomp> at 0x0000026C8AA31D10, file "patient_report.py", line 163>:
163           0 BUILD_LIST               0
              2 LOAD_FAST                0 (.0)
        >>    4 FOR_ITER                 8 (to 22)
              6 STORE_FAST               1 (i)
              8 LOAD_DEREF               0 (h)
             10 LOAD_FAST                1 (i)
             12 COMPARE_OP               2 (==)
             14 LOAD_METHOD              0 (sum)
             16 CALL_METHOD              0
             18 LIST_APPEND              2
             20 JUMP_ABSOLUTE            2 (to 4)
        >>   22 RETURN_VALUE

--- _section_title ---
175           0 LOAD_GLOBAL              0 (_t)
              2 LOAD_FAST                1 (title)
              4 LOAD_FAST                4 (lang)
              6 CALL_FUNCTION            2
              8 STORE_FAST               5 (display_title)

177          10 LOAD_CONST               1 ('pAHI')
             12 LOAD_FAST                5 (display_title)
             14 CONTAINS_OP              0
             16 POP_JUMP_IF_FALSE       47 (to 94)

178          18 LOAD_FAST                4 (lang)
             20 LOAD_CONST               2 ('he')
             22 COMPARE_OP               2 (==)
             24 POP_JUMP_IF_FALSE       26 (to 52)

179          26 LOAD_FAST                5 (display_title)
             28 LOAD_METHOD              1 (replace)
             30 LOAD_CONST               3 ('(pAHI)')
             32 LOAD_CONST               4 ('')
             34 CALL_METHOD              2
             36 LOAD_METHOD              2 (strip)
             38 CALL_METHOD              0
             40 STORE_FAST               6 (clean_title)

180          42 LOAD_FAST                6 (clean_title)
             44 LOAD_CONST               3 ('(pAHI)')
             46 BUILD_LIST               2
             48 STORE_FAST               7 (lines)
             50 JUMP_FORWARD            24 (to 100)

183     >>   52 LOAD_FAST                5 (display_title)
             54 LOAD_METHOD              1 (replace)
             56 LOAD_CONST               5 ('Index (pAHI)')
             58 LOAD_CONST               4 ('')
             60 CALL_METHOD              2
             62 LOAD_METHOD              1 (replace)
             64 LOAD_CONST               6 ('Index')
             66 LOAD_CONST               4 ('')
             68 CALL_METHOD              2
             70 LOAD_METHOD              1 (replace)
             72 LOAD_CONST               3 ('(pAHI)')
             74 LOAD_CONST               4 ('')
             76 CALL_METHOD              2
             78 LOAD_METHOD              2 (strip)
             80 CALL_METHOD              0
             82 STORE_FAST               6 (clean_title)

184          84 LOAD_FAST                6 (clean_title)
             86 LOAD_CONST               5 ('Index (pAHI)')
             88 BUILD_LIST               2
             90 STORE_FAST               7 (lines)
             92 JUMP_FORWARD             3 (to 100)

186     >>   94 LOAD_FAST                5 (display_title)
             96 BUILD_LIST               1
             98 STORE_FAST               7 (lines)

188     >>  100 LOAD_FAST                4 (lang)
            102 LOAD_CONST               2 ('he')
            104 COMPARE_OP               2 (==)
            106 POP_JUMP_IF_FALSE       66 (to 132)

189         108 LOAD_GLOBAL              3 (get_display)
            110 LOAD_FAST                7 (lines)
            112 LOAD_CONST               7 (0)
            114 BINARY_SUBSCR
            116 CALL_FUNCTION            1
            118 FORMAT_VALUE             0
            120 LOAD_CONST               8 (' .')
            122 LOAD_FAST                2 (number)
            124 FORMAT_VALUE             0
            126 BUILD_STRING             3
            128 STORE_FAST               8 (line0)
            130 JUMP_FORWARD             9 (to 150)

191     >>  132 LOAD_FAST                2 (number)
            134 FORMAT_VALUE             0
            136 LOAD_CONST               9 ('. ')
            138 LOAD_FAST                7 (lines)
            140 LOAD_CONST               7 (0)
            142 BINARY_SUBSCR
            144 FORMAT_VALUE             0
            146 BUILD_STRING             3
            148 STORE_FAST               8 (line0)

194     >>  150 LOAD_CONST              10 (0.15)
            152 STORE_FAST               9 (x_start)

196         154 LOAD_FAST                0 (ax)
            156 LOAD_ATTR                4 (plot)
            158 LOAD_GLOBAL              5 (_x)
            160 LOAD_FAST                9 (x_start)
            162 LOAD_FAST                4 (lang)
            164 CALL_FUNCTION            2
            166 LOAD_FAST                3 (y_frac)
            168 LOAD_CONST              11 ('o')
            170 LOAD_GLOBAL              6 (ACCENT)
            172 LOAD_CONST              12 (7)

197         174 LOAD_FAST                0 (ax)
            176 LOAD_ATTR                7 (transAxes)
            178 LOAD_CONST              13 (False)
            180 LOAD_CONST              14 (6)

196         182 LOAD_CONST              15 (('color', 'markersize', 'transform', 'clip_on', 'zorder'))
            184 CALL_FUNCTION_KW         8
            186 POP_TOP

199         188 LOAD_FAST                9 (x_start)
            190 LOAD_CONST              16 (0.025)
            192 BINARY_ADD
            194 STORE_FAST              10 (base_x)

200         196 LOAD_FAST                0 (ax)
            198 LOAD_ATTR                8 (text)
            200 LOAD_GLOBAL              5 (_x)
            202 LOAD_FAST               10 (base_x)
            204 LOAD_FAST                4 (lang)
            206 CALL_FUNCTION            2
            208 LOAD_FAST                3 (y_frac)
            210 LOAD_FAST                8 (line0)

201         212 LOAD_CONST              17 (13)
            214 LOAD_CONST              18 ('bold')
            216 LOAD_GLOBAL              9 (TEXT_H)

202         218 LOAD_GLOBAL             10 (_ha)
            220 LOAD_CONST              19 ('left')
            222 LOAD_FAST                4 (lang)
            224 CALL_FUNCTION            2
            226 LOAD_CONST              20 ('center')
            228 LOAD_FAST                0 (ax)
            230 LOAD_ATTR                7 (transAxes)

200         232 LOAD_CONST              21 (('fontsize', 'fontweight', 'color', 'ha', 'va', 'transform'))
            234 CALL_FUNCTION_KW         9
            236 STORE_FAST              11 (t1)

204         238 LOAD_GLOBAL             11 (len)
            240 LOAD_FAST                7 (lines)
            242 CALL_FUNCTION            1
            244 LOAD_CONST              22 (1)
            246 COMPARE_OP               4 (>)
            248 POP_JUMP_IF_FALSE      184 (to 368)

205         250 LOAD_FAST                4 (lang)
            252 LOAD_CONST               2 ('he')
            254 COMPARE_OP               2 (==)
            256 POP_JUMP_IF_FALSE      135 (to 270)
            258 LOAD_GLOBAL              3 (get_display)
            260 LOAD_FAST                7 (lines)
            262 LOAD_CONST              22 (1)
            264 BINARY_SUBSCR
            266 CALL_FUNCTION            1
            268 JUMP_FORWARD             3 (to 276)
        >>  270 LOAD_FAST                7 (lines)
            272 LOAD_CONST              22 (1)
            274 BINARY_SUBSCR
        >>  276 STORE_FAST              12 (line1_text)

208         278 LOAD_FAST                0 (ax)
            280 LOAD_ATTR               12 (figure)
            282 LOAD_ATTR               13 (canvas)
            284 LOAD_METHOD             14 (draw)
            286 CALL_METHOD              0
            288 POP_TOP

209         290 LOAD_FAST               11 (t1)
            292 LOAD_METHOD             15 (get_window_extent)
            294 CALL_METHOD              0
            296 STORE_FAST              13 (bbox)

210         298 LOAD_FAST               13 (bbox)
            300 LOAD_METHOD             16 (transformed)
            302 LOAD_FAST                0 (ax)
            304 LOAD_ATTR                7 (transAxes)
            306 LOAD_METHOD             17 (inverted)
            308 CALL_METHOD              0
            310 CALL_METHOD              1
            312 STORE_FAST              14 (bbox_axes)

211         314 LOAD_FAST               14 (bbox_axes)
            316 LOAD_ATTR               18 (x0)
            318 LOAD_FAST               14 (bbox_axes)
            320 LOAD_ATTR               19 (x1)
            322 BINARY_ADD
            324 LOAD_CONST              23 (2)
            326 BINARY_TRUE_DIVIDE
            328 STORE_FAST              15 (x_center)

215         330 LOAD_FAST                0 (ax)
            332 LOAD_ATTR                8 (text)
            334 LOAD_FAST               15 (x_center)
            336 LOAD_FAST                3 (y_frac)
            338 LOAD_CONST              24 (0.13)
            340 BINARY_SUBTRACT
            342 LOAD_FAST               12 (line1_text)

216         344 LOAD_CONST              17 (13)
            346 LOAD_CONST              18 ('bold')
            348 LOAD_GLOBAL              9 (TEXT_H)

217         350 LOAD_CONST              20 ('center')
            352 LOAD_CONST              20 ('center')
            354 LOAD_FAST                0 (ax)
            356 LOAD_ATTR                7 (transAxes)

215         358 LOAD_CONST              21 (('fontsize', 'fontweight', 'color', 'ha', 'va', 'transform'))
            360 CALL_FUNCTION_KW         9
            362 POP_TOP
            364 LOAD_CONST               0 (None)
            366 RETURN_VALUE

204     >>  368 LOAD_CONST               0 (None)
            370 RETURN_VALUE

--- _panel ---
220           0 LOAD_FAST                0 (ax)
              2 LOAD_METHOD              0 (set_facecolor)
              4 LOAD_GLOBAL              1 (PANEL)
              6 CALL_METHOD              1
              8 POP_TOP

221          10 LOAD_FAST                0 (ax)
             12 LOAD_ATTR                2 (spines)
             14 LOAD_METHOD              3 (values)
             16 CALL_METHOD              0
             18 GET_ITER
        >>   20 FOR_ITER                12 (to 46)
             22 STORE_FAST               1 (sp)

222          24 LOAD_FAST                1 (sp)
             26 LOAD_METHOD              4 (set_color)
             28 LOAD_GLOBAL              5 (BORDER)
             30 CALL_METHOD              1
             32 POP_TOP
             34 LOAD_FAST                1 (sp)
             36 LOAD_METHOD              6 (set_linewidth)
             38 LOAD_CONST               1 (0.8)
             40 CALL_METHOD              1
             42 POP_TOP
             44 JUMP_ABSOLUTE           10 (to 20)

221     >>   46 LOAD_CONST               0 (None)
             48 RETURN_VALUE

--- _pill ---
225           0 LOAD_FAST                0 (ax)
              2 LOAD_METHOD              0 (add_patch)
              4 LOAD_GLOBAL              1 (FancyBboxPatch)
              6 LOAD_FAST                1 (x)
              8 LOAD_FAST                2 (y)
             10 BUILD_TUPLE              2
             12 LOAD_FAST                3 (w)
             14 LOAD_FAST                4 (h)

226          16 LOAD_CONST               1 ('round,pad=0,rounding_size=0.015')

227          18 LOAD_FAST                5 (color)
             20 LOAD_CONST               2 ('none')
             22 LOAD_FAST                6 (alpha)

228          24 LOAD_FAST                0 (ax)
             26 LOAD_ATTR                2 (transAxes)
             28 LOAD_CONST               3 (False)
             30 LOAD_CONST               4 (2)

225          32 LOAD_CONST               5 (('boxstyle', 'facecolor', 'edgecolor', 'alpha', 'transform', 'clip_on', 'zorder'))
             34 CALL_FUNCTION_KW        10
             36 CALL_METHOD              1
             38 POP_TOP
             40 LOAD_CONST               0 (None)
             42 RETURN_VALUE

--- _hypno ---
233           0 LOAD_GLOBAL              0 (np)
              2 LOAD_ATTR                1 (asarray)
              4 LOAD_FAST                1 (h)
              6 LOAD_GLOBAL              2 (int)
              8 LOAD_CONST               1 (('dtype',))
             10 CALL_FUNCTION_KW         2
             12 STORE_FAST               1 (h)

234          14 LOAD_CONST               2 (4)
             16 LOAD_CONST               3 (3)
             18 LOAD_CONST               4 (2)
             20 LOAD_CONST               5 (1)
             22 LOAD_CONST               6 (5)
             24 LOAD_CONST               7 (0)
             26 LOAD_CONST               8 ((0, 1, 2, 3, 4, -1))
             28 BUILD_CONST_KEY_MAP      6
             30 STORE_DEREF              0 (ym)

235          32 LOAD_GLOBAL              3 (STAGE_COLORS)
             34 LOAD_CONST               9 ('Wake')
             36 BINARY_SUBSCR
             38 LOAD_GLOBAL              3 (STAGE_COLORS)
             40 LOAD_CONST              10 ('N1')
             42 BINARY_SUBSCR

236          44 LOAD_GLOBAL              3 (STAGE_COLORS)
             46 LOAD_CONST              11 ('N2')
             48 BINARY_SUBSCR
             50 LOAD_GLOBAL              3 (STAGE_COLORS)
             52 LOAD_CONST              12 ('N3')
             54 BINARY_SUBSCR

237          56 LOAD_GLOBAL              3 (STAGE_COLORS)
             58 LOAD_CONST              13 ('REM')
             60 BINARY_SUBSCR
             62 LOAD_CONST              14 ('#CBD5E1')

235          64 LOAD_CONST               8 ((0, 1, 2, 3, 4, -1))
             66 BUILD_CONST_KEY_MAP      6
             68 STORE_FAST               3 (cm)

238          70 LOAD_GLOBAL              0 (np)
             72 LOAD_METHOD              4 (arange)
             74 LOAD_GLOBAL              5 (len)
             76 LOAD_FAST                1 (h)
             78 CALL_FUNCTION            1
             80 CALL_METHOD              1
             82 LOAD_CONST              15 (3600)
             84 BINARY_TRUE_DIVIDE
             86 STORE_FAST               4 (xs)

239          88 LOAD_CONST               7 (0)
             90 STORE_FAST               5 (i)

240          92 LOAD_FAST                5 (i)
             94 LOAD_GLOBAL              5 (len)
             96 LOAD_FAST                1 (h)
             98 CALL_FUNCTION            1
            100 COMPARE_OP               0 (<)
            102 POP_JUMP_IF_FALSE      129 (to 258)

241     >>  104 LOAD_FAST                1 (h)
            106 LOAD_FAST                5 (i)
            108 BINARY_SUBSCR
            110 STORE_FAST               6 (s)
            112 LOAD_FAST                5 (i)
            114 LOAD_CONST               5 (1)
            116 BINARY_ADD
            118 STORE_FAST               7 (j)

242         120 LOAD_FAST                7 (j)
            122 LOAD_GLOBAL              5 (len)
            124 LOAD_FAST                1 (h)
            126 CALL_FUNCTION            1
            128 COMPARE_OP               0 (<)
            130 POP_JUMP_IF_FALSE       88 (to 176)
            132 LOAD_FAST                1 (h)
            134 LOAD_FAST                7 (j)
            136 BINARY_SUBSCR
            138 LOAD_FAST                6 (s)
            140 COMPARE_OP               2 (==)
            142 POP_JUMP_IF_FALSE       88 (to 176)
        >>  144 LOAD_FAST                7 (j)
            146 LOAD_CONST               5 (1)
            148 INPLACE_ADD
            150 STORE_FAST               7 (j)
            152 LOAD_FAST                7 (j)
            154 LOAD_GLOBAL              5 (len)
            156 LOAD_FAST                1 (h)
            158 CALL_FUNCTION            1
            160 COMPARE_OP               0 (<)
            162 POP_JUMP_IF_FALSE       88 (to 176)
            164 LOAD_FAST                1 (h)
            166 LOAD_FAST                7 (j)
            168 BINARY_SUBSCR
            170 LOAD_FAST                6 (s)
            172 COMPARE_OP               2 (==)
            174 POP_JUMP_IF_TRUE        72 (to 144)

243     >>  176 LOAD_FAST                0 (ax)
            178 LOAD_ATTR                6 (fill_between)
            180 LOAD_FAST                4 (xs)
            182 LOAD_FAST                5 (i)
            184 LOAD_FAST                7 (j)
            186 BUILD_SLICE              2
            188 BINARY_SUBSCR
            190 LOAD_CONST               7 (0)
            192 LOAD_GLOBAL              0 (np)
            194 LOAD_METHOD              7 (full)
            196 LOAD_FAST                7 (j)
            198 LOAD_FAST                5 (i)
            200 BINARY_SUBTRACT
            202 LOAD_DEREF               0 (ym)
            204 LOAD_METHOD              8 (get)
            206 LOAD_GLOBAL              2 (int)
            208 LOAD_FAST                6 (s)
            210 CALL_FUNCTION            1
            212 LOAD_CONST               7 (0)
            214 CALL_METHOD              2
            216 CALL_METHOD              2

244         218 LOAD_FAST                3 (cm)
            220 LOAD_METHOD              8 (get)
            222 LOAD_GLOBAL              2 (int)
            224 LOAD_FAST                6 (s)
            226 CALL_FUNCTION            1
            228 LOAD_CONST              14 ('#CBD5E1')
            230 CALL_METHOD              2
            232 LOAD_CONST              16 (0.9)
            234 LOAD_CONST               7 (0)

243         236 LOAD_CONST              17 (('color', 'alpha', 'lw'))
            238 CALL_FUNCTION_KW         6
            240 POP_TOP

245         242 LOAD_FAST                7 (j)
            244 STORE_FAST               5 (i)

240         246 LOAD_FAST                5 (i)
            248 LOAD_GLOBAL              5 (len)
            250 LOAD_FAST                1 (h)
            252 CALL_FUNCTION            1
            254 COMPARE_OP               0 (<)
            256 POP_JUMP_IF_TRUE        52 (to 104)

247     >>  258 LOAD_GLOBAL              0 (np)
            260 LOAD_METHOD              9 (array)
            262 LOAD_CLOSURE             0 (ym)
            264 BUILD_TUPLE              1
            266 LOAD_CONST              18 (<code object <listcomp> at 0x0000026C8AA31A50, file "patient_report.py", line 247>)
            268 LOAD_CONST              19 ('_hypno.<locals>.<listcomp>')
            270 MAKE_FUNCTION            8 (closure)
            272 LOAD_FAST                1 (h)
            274 GET_ITER
            276 CALL_FUNCTION            1
            278 CALL_METHOD              1
            280 STORE_FAST               8 (y_vals)

248         282 LOAD_FAST                0 (ax)
            284 LOAD_ATTR               10 (step)
            286 LOAD_FAST                4 (xs)
            288 LOAD_FAST                8 (y_vals)
            290 LOAD_CONST              20 ('post')
            292 LOAD_GLOBAL             11 (TEXT_H)
            294 LOAD_CONST              21 (1.2)
            296 LOAD_CONST              22 (0.8)
            298 LOAD_CONST              23 (('where', 'color', 'linewidth', 'alpha'))
            300 CALL_FUNCTION_KW         6
            302 POP_TOP

249         304 LOAD_GLOBAL              5 (len)
            306 LOAD_FAST                4 (xs)
            308 CALL_FUNCTION            1
            310 POP_JUMP_IF_FALSE      160 (to 320)
            312 LOAD_FAST                4 (xs)
            314 LOAD_CONST              24 (-1)
            316 BINARY_SUBSCR
            318 JUMP_FORWARD             1 (to 322)
        >>  320 LOAD_CONST               5 (1)
        >>  322 STORE_FAST               9 (mh)

250         324 LOAD_FAST                0 (ax)
            326 LOAD_METHOD             12 (set_ylim)
            328 LOAD_CONST               7 (0)
            330 LOAD_CONST              25 (6)
            332 CALL_METHOD              2
            334 POP_TOP

251         336 LOAD_FAST                0 (ax)
            338 LOAD_METHOD             13 (set_yticks)
            340 BUILD_LIST               0
            342 LOAD_CONST              26 ((1, 2, 3, 4, 5))
            344 LIST_EXTEND              1
            346 CALL_METHOD              1
            348 POP_TOP

252         350 LOAD_GLOBAL             14 (_t)
            352 LOAD_CONST              12 ('N3')
            354 LOAD_FAST                2 (lang)
            356 CALL_FUNCTION            2
            358 LOAD_GLOBAL             14 (_t)
            360 LOAD_CONST              11 ('N2')
            362 LOAD_FAST                2 (lang)
            364 CALL_FUNCTION            2
            366 LOAD_GLOBAL             14 (_t)
            368 LOAD_CONST              10 ('N1')
            370 LOAD_FAST                2 (lang)
            372 CALL_FUNCTION            2
            374 LOAD_GLOBAL             14 (_t)
            376 LOAD_CONST              13 ('REM')
            378 LOAD_FAST                2 (lang)
            380 CALL_FUNCTION            2
            382 LOAD_GLOBAL             14 (_t)
            384 LOAD_CONST               9 ('Wake')
            386 LOAD_FAST                2 (lang)
            388 CALL_FUNCTION            2
            390 BUILD_LIST               5
            392 STORE_FAST              10 (labels)

253         394 LOAD_FAST                0 (ax)
            396 LOAD_ATTR               15 (set_yticklabels)
            398 LOAD_FAST               10 (labels)
            400 LOAD_CONST              27 (8)
            402 LOAD_CONST              28 ('bold')
            404 LOAD_CONST              29 (('fontsize', 'fontweight'))
            406 CALL_FUNCTION_KW         3
            408 POP_TOP

254         410 LOAD_GLOBAL              3 (STAGE_COLORS)
            412 LOAD_CONST              12 ('N3')
            414 BINARY_SUBSCR
            416 LOAD_GLOBAL              3 (STAGE_COLORS)
            418 LOAD_CONST              11 ('N2')
            420 BINARY_SUBSCR
            422 LOAD_GLOBAL              3 (STAGE_COLORS)
            424 LOAD_CONST              10 ('N1')
            426 BINARY_SUBSCR
            428 LOAD_GLOBAL              3 (STAGE_COLORS)
            430 LOAD_CONST              13 ('REM')
            432 BINARY_SUBSCR
            434 LOAD_GLOBAL              3 (STAGE_COLORS)
            436 LOAD_CONST               9 ('Wake')
            438 BINARY_SUBSCR
            440 BUILD_LIST               5
            442 STORE_FAST              11 (colors_for_ticks)

255         444 LOAD_GLOBAL             16 (zip)
            446 LOAD_FAST                0 (ax)
            448 LOAD_METHOD             17 (get_yticklabels)
            450 CALL_METHOD              0
            452 LOAD_FAST               11 (colors_for_ticks)
            454 CALL_FUNCTION            2
            456 GET_ITER
        >>  458 FOR_ITER                 9 (to 478)
            460 UNPACK_SEQUENCE          2
            462 STORE_FAST              12 (tick_label)
            464 STORE_FAST              13 (color)

256         466 LOAD_FAST               12 (tick_label)
            468 LOAD_METHOD             18 (set_color)
            470 LOAD_FAST               13 (color)
            472 CALL_METHOD              1
            474 POP_TOP
            476 JUMP_ABSOLUTE          229 (to 458)

257     >>  478 LOAD_FAST                0 (ax)
            480 LOAD_ATTR               19 (tick_params)
            482 LOAD_CONST              30 ('x')
            484 LOAD_CONST              31 (7)
            486 LOAD_GLOBAL             20 (TEXT_M)
            488 LOAD_CONST               4 (2)
            490 LOAD_CONST              32 (('axis', 'labelsize', 'colors', 'length'))
            492 CALL_FUNCTION_KW         4
            494 POP_TOP

258         496 LOAD_FAST                0 (ax)
            498 LOAD_METHOD             21 (set_facecolor)
            500 LOAD_GLOBAL             22 (PANEL)
            502 CALL_METHOD              1
            504 POP_TOP

259         506 LOAD_FAST                2 (lang)
            508 LOAD_CONST              33 ('he')
            510 COMPARE_OP               2 (==)
            512 EXTENDED_ARG             1
            514 POP_JUMP_IF_FALSE      300 (to 600)

260         516 LOAD_FAST                0 (ax)
            518 LOAD_METHOD             23 (set_xlim)
            520 LOAD_FAST                9 (mh)
            522 LOAD_CONST              34 (-1.2)
            524 CALL_METHOD              2
            526 POP_TOP

261         528 LOAD_FAST                0 (ax)
            530 LOAD_ATTR               24 (yaxis)
            532 LOAD_METHOD             25 (tick_right)
            534 CALL_METHOD              0
            536 POP_TOP

262         538 LOAD_FAST                0 (ax)
            540 LOAD_ATTR               24 (yaxis)
            542 LOAD_METHOD             26 (set_label_position)
            544 LOAD_CONST              35 ('right')
            546 CALL_METHOD              1
            548 POP_TOP

263         550 LOAD_FAST                0 (ax)
            552 LOAD_ATTR               27 (spines)
            554 LOAD_CONST              36 ('left')
            556 BINARY_SUBSCR
            558 LOAD_METHOD             28 (set_visible)
            560 LOAD_CONST              37 (False)
            562 CALL_METHOD              1
            564 POP_TOP

264         566 LOAD_FAST                0 (ax)
            568 LOAD_ATTR               27 (spines)
            570 LOAD_CONST              35 ('right')
            572 BINARY_SUBSCR
            574 LOAD_METHOD             18 (set_color)
            576 LOAD_GLOBAL             29 (BORDER)
            578 CALL_METHOD              1
            580 POP_TOP

265         582 LOAD_FAST                0 (ax)
            584 LOAD_ATTR               27 (spines)
            586 LOAD_CONST              35 ('right')
            588 BINARY_SUBSCR
            590 LOAD_METHOD             30 (set_position)
            592 LOAD_CONST              38 (('data', 0))
            594 CALL_METHOD              1
            596 POP_TOP
            598 JUMP_FORWARD            30 (to 660)

267     >>  600 LOAD_FAST                0 (ax)
            602 LOAD_METHOD             23 (set_xlim)
            604 LOAD_CONST              34 (-1.2)
            606 LOAD_FAST                9 (mh)
            608 CALL_METHOD              2
            610 POP_TOP

268         612 LOAD_FAST                0 (ax)
            614 LOAD_ATTR               27 (spines)
            616 LOAD_CONST              35 ('right')
            618 BINARY_SUBSCR
            620 LOAD_METHOD             28 (set_visible)
            622 LOAD_CONST              37 (False)
            624 CALL_METHOD              1
            626 POP_TOP

269         628 LOAD_FAST                0 (ax)
            630 LOAD_ATTR               27 (spines)
            632 LOAD_CONST              36 ('left')
            634 BINARY_SUBSCR
            636 LOAD_METHOD             18 (set_color)
            638 LOAD_GLOBAL             29 (BORDER)
            640 CALL_METHOD              1
            642 POP_TOP

270         644 LOAD_FAST                0 (ax)
            646 LOAD_ATTR               27 (spines)
            648 LOAD_CONST              36 ('left')
            650 BINARY_SUBSCR
            652 LOAD_METHOD             30 (set_position)
            654 LOAD_CONST              38 (('data', 0))
            656 CALL_METHOD              1
            658 POP_TOP

271     >>  660 LOAD_FAST                0 (ax)
            662 LOAD_ATTR               27 (spines)
            664 LOAD_CONST              39 ('top')
            666 BINARY_SUBSCR
            668 LOAD_METHOD             28 (set_visible)
            670 LOAD_CONST              37 (False)
            672 CALL_METHOD              1
            674 POP_TOP

272         676 LOAD_FAST                0 (ax)
            678 LOAD_ATTR               27 (spines)
            680 LOAD_CONST              40 ('bottom')
            682 BINARY_SUBSCR
            684 LOAD_METHOD             31 (set_bounds)
            686 LOAD_CONST               7 (0)
            688 LOAD_FAST                9 (mh)
            690 CALL_METHOD              2
            692 POP_TOP

273         694 LOAD_FAST                0 (ax)
            696 LOAD_ATTR               27 (spines)
            698 LOAD_CONST              40 ('bottom')
            700 BINARY_SUBSCR
            702 LOAD_METHOD             18 (set_color)
            704 LOAD_GLOBAL             29 (BORDER)
            706 CALL_METHOD              1
            708 POP_TOP

274         710 LOAD_FAST                0 (ax)
            712 LOAD_ATTR               32 (grid)
            714 LOAD_CONST              30 ('x')
            716 LOAD_GLOBAL             29 (BORDER)
            718 LOAD_CONST              41 (0.5)
            720 LOAD_CONST              42 (':')
            722 LOAD_CONST              43 (('axis', 'color', 'lw', 'linestyle'))
            724 CALL_FUNCTION_KW         4
            726 POP_TOP

275         728 LOAD_FAST                0 (ax)
            730 LOAD_ATTR               19 (tick_params)
            732 LOAD_GLOBAL             20 (TEXT_M)
            734 LOAD_CONST              44 (('colors',))
            736 CALL_FUNCTION_KW         1
            738 POP_TOP
            740 LOAD_CONST               0 (None)
            742 RETURN_VALUE

Disassembly of <code object <listcomp> at 0x0000026C8AA31A50, file "patient_report.py", line 247>:
247           0 BUILD_LIST               0
              2 LOAD_FAST                0 (.0)
        >>    4 FOR_ITER                10 (to 26)
              6 STORE_FAST               1 (s)
              8 LOAD_DEREF               0 (ym)
             10 LOAD_METHOD              0 (get)
             12 LOAD_GLOBAL              1 (int)
             14 LOAD_FAST                1 (s)
             16 CALL_FUNCTION            1
             18 LOAD_CONST               0 (0)
             20 CALL_METHOD              2
             22 LIST_APPEND              2
             24 JUMP_ABSOLUTE            2 (to 4)
        >>   26 RETURN_VALUE

--- _donut ---
282           0 BUILD_LIST               0
              2 LOAD_CONST               1 (('N1', 'N2', 'N3', 'REM', 'Wake'))
              4 LIST_EXTEND              1
              6 STORE_FAST               3 (lbls)

283           8 LOAD_FAST                1 (s)
             10 LOAD_CONST               2 ('N1')
             12 BINARY_SUBSCR
             14 LOAD_FAST                1 (s)
             16 LOAD_CONST               3 ('N2')
             18 BINARY_SUBSCR
             20 LOAD_FAST                1 (s)
             22 LOAD_CONST               4 ('N3')
             24 BINARY_SUBSCR
             26 LOAD_FAST                1 (s)
             28 LOAD_CONST               5 ('REM')
             30 BINARY_SUBSCR
             32 LOAD_FAST                1 (s)
             34 LOAD_CONST               6 ('Wake')
             36 BINARY_SUBSCR
             38 BUILD_LIST               5
             40 STORE_FAST               4 (vals)

284          42 LOAD_CONST               7 (<code object <listcomp> at 0x0000026C8AA312C0, file "patient_report.py", line 284>)
             44 LOAD_CONST               8 ('_donut.<locals>.<listcomp>')
             46 MAKE_FUNCTION            0
             48 LOAD_FAST                3 (lbls)
             50 GET_ITER
             52 CALL_FUNCTION            1
             54 STORE_FAST               5 (colors)

285          56 LOAD_FAST                0 (ax)
             58 LOAD_ATTR                0 (pie)

286          60 LOAD_FAST                4 (vals)
             62 LOAD_FAST                5 (colors)

287          64 LOAD_CONST               9 (<code object <lambda> at 0x0000026C8AA31370, file "patient_report.py", line 287>)
             66 LOAD_CONST              10 ('_donut.<locals>.<lambda>')
             68 MAKE_FUNCTION            0

288          70 LOAD_GLOBAL              1 (dict)
             72 LOAD_CONST              11 (0.5)
             74 LOAD_CONST              12 ('white')
             76 LOAD_CONST              13 (1.8)
             78 LOAD_CONST              14 (('width', 'edgecolor', 'linewidth'))
             80 CALL_FUNCTION_KW         3

289          82 LOAD_CONST              15 (90)
             84 LOAD_CONST              16 (0.75)

285          86 LOAD_CONST              17 (('colors', 'autopct', 'wedgeprops', 'startangle', 'pctdistance'))
             88 CALL_FUNCTION_KW         6
             90 UNPACK_SEQUENCE          3
             92 STORE_FAST               6 (_)
             94 STORE_FAST               6 (_)
             96 STORE_FAST               7 (auts)

291          98 LOAD_FAST                7 (auts)
            100 GET_ITER
        >>  102 FOR_ITER                17 (to 138)
            104 STORE_FAST               8 (at)

292         106 LOAD_FAST                8 (at)
            108 LOAD_METHOD              2 (set_color)
            110 LOAD_CONST              12 ('white')
            112 CALL_METHOD              1
            114 POP_TOP
            116 LOAD_FAST                8 (at)
            118 LOAD_METHOD              3 (set_fontsize)
            120 LOAD_CONST              18 (11)
            122 CALL_METHOD              1
            124 POP_TOP
            126 LOAD_FAST                8 (at)
            128 LOAD_METHOD              4 (set_fontweight)
            130 LOAD_CONST              19 ('bold')
            132 CALL_METHOD              1
            134 POP_TOP
            136 JUMP_ABSOLUTE           51 (to 102)

293     >>  138 LOAD_FAST                0 (ax)
            140 LOAD_METHOD              5 (set_facecolor)
            142 LOAD_GLOBAL              6 (PANEL)
            144 CALL_METHOD              1
            146 POP_TOP
            148 LOAD_CONST               0 (None)
            150 RETURN_VALUE

Disassembly of <code object <listcomp> at 0x0000026C8AA312C0, file "patient_report.py", line 284>:
284           0 BUILD_LIST               0
              2 LOAD_FAST                0 (.0)
        >>    4 FOR_ITER                 6 (to 18)
              6 STORE_FAST               1 (l)
              8 LOAD_GLOBAL              0 (STAGE_COLORS)
             10 LOAD_FAST                1 (l)
             12 BINARY_SUBSCR
             14 LIST_APPEND              2
             16 JUMP_ABSOLUTE            2 (to 4)
        >>   18 RETURN_VALUE

Disassembly of <code object <lambda> at 0x0000026C8AA31370, file "patient_report.py", line 287>:
287           0 LOAD_FAST                0 (p)
              2 LOAD_CONST               1 (5)
              4 COMPARE_OP               4 (>)
              6 POP_JUMP_IF_FALSE       10 (to 20)
              8 LOAD_FAST                0 (p)
             10 LOAD_CONST               2 ('.0f')
             12 FORMAT_VALUE             4 (with format)
             14 LOAD_CONST               3 ('%')
             16 BUILD_STRING             2
             18 RETURN_VALUE
        >>   20 LOAD_CONST               4 ('')
             22 RETURN_VALUE

--- _gauge ---
298           0 LOAD_FAST                0 (ax)
              2 LOAD_ATTR                0 (set_aspect)
              4 LOAD_CONST               1 ('equal')
              6 LOAD_CONST               2 ('box')
              8 LOAD_CONST               3 (('adjustable',))
             10 CALL_FUNCTION_KW         2
             12 POP_TOP

299          14 LOAD_FAST                0 (ax)
             16 LOAD_METHOD              1 (set_xlim)
             18 LOAD_CONST               4 (-1.15)
             20 LOAD_CONST               5 (1.15)
             22 CALL_METHOD              2
             24 POP_TOP

300          26 LOAD_CONST               6 (1.0)
             28 STORE_FAST               5 (y_scale)

301          30 LOAD_FAST                0 (ax)
             32 LOAD_METHOD              2 (set_ylim)
             34 LOAD_CONST               7 (-0.95)
             36 LOAD_CONST               5 (1.15)
             38 CALL_METHOD              2
             40 POP_TOP

302          42 LOAD_FAST                0 (ax)
             44 LOAD_METHOD              3 (axis)
             46 LOAD_CONST               8 ('off')
             48 CALL_METHOD              1
             50 POP_TOP

303          52 BUILD_LIST               0
             54 LOAD_CONST               9 (('#6EC2B5', '#97A8E5', '#B48EE5', '#E58EAA'))
             56 LIST_EXTEND              1
             58 STORE_FAST               6 (palette)

304          60 LOAD_GLOBAL              4 (LinearSegmentedColormap)
             62 LOAD_METHOD              5 (from_list)
             64 LOAD_CONST              10 ('purples')
             66 LOAD_FAST                6 (palette)
             68 CALL_METHOD              2
             70 STORE_FAST               7 (cmap)

305          72 LOAD_CONST              11 (180)
             74 STORE_FAST               8 (n)

306          76 LOAD_CONST              12 ((1.0, 0.65))
             78 UNPACK_SEQUENCE          2
             80 STORE_FAST               9 (outer_r)
             82 STORE_FAST              10 (inner_r)

307          84 LOAD_GLOBAL              6 (np)
             86 LOAD_METHOD              7 (linspace)
             88 LOAD_GLOBAL              6 (np)
             90 LOAD_ATTR                8 (pi)
             92 LOAD_CONST              13 (0)
             94 LOAD_FAST                8 (n)
             96 CALL_METHOD              3
             98 STORE_FAST              11 (th)

308         100 LOAD_GLOBAL              9 (range)
            102 LOAD_FAST                8 (n)
            104 LOAD_CONST              14 (1)
            106 BINARY_SUBTRACT
            108 CALL_FUNCTION            1
            110 GET_ITER
        >>  112 FOR_ITER                88 (to 290)
            114 STORE_FAST              12 (i)

309         116 LOAD_FAST               11 (th)
            118 LOAD_FAST               12 (i)
            120 BINARY_SUBSCR
            122 LOAD_FAST               11 (th)
            124 LOAD_FAST               12 (i)
            126 LOAD_CONST              14 (1)
            128 BINARY_ADD
            130 BINARY_SUBSCR
            132 ROT_TWO
            134 STORE_FAST              13 (t0)
            136 STORE_FAST              14 (t1)

310         138 LOAD_FAST               10 (inner_r)
            140 LOAD_GLOBAL              6 (np)
            142 LOAD_METHOD             10 (cos)
            144 LOAD_FAST               13 (t0)
            146 CALL_METHOD              1
            148 BINARY_MULTIPLY
            150 LOAD_FAST                9 (outer_r)
            152 LOAD_GLOBAL              6 (np)
            154 LOAD_METHOD             10 (cos)
            156 LOAD_FAST               13 (t0)
            158 CALL_METHOD              1
            160 BINARY_MULTIPLY
            162 LOAD_FAST                9 (outer_r)
            164 LOAD_GLOBAL              6 (np)
            166 LOAD_METHOD             10 (cos)
            168 LOAD_FAST               14 (t1)
            170 CALL_METHOD              1
            172 BINARY_MULTIPLY
            174 LOAD_FAST               10 (inner_r)
            176 LOAD_GLOBAL              6 (np)
            178 LOAD_METHOD             10 (cos)
            180 LOAD_FAST               14 (t1)
            182 CALL_METHOD              1
            184 BINARY_MULTIPLY
            186 BUILD_LIST               4
            188 STORE_FAST              15 (xs)

311         190 LOAD_FAST                5 (y_scale)
            192 LOAD_FAST               10 (inner_r)
            194 BINARY_MULTIPLY
            196 LOAD_GLOBAL              6 (np)
            198 LOAD_METHOD             11 (sin)
            200 LOAD_FAST               13 (t0)
            202 CALL_METHOD              1
            204 BINARY_MULTIPLY
            206 LOAD_FAST                5 (y_scale)
            208 LOAD_FAST                9 (outer_r)
            210 BINARY_MULTIPLY
            212 LOAD_GLOBAL              6 (np)
            214 LOAD_METHOD             11 (sin)
            216 LOAD_FAST               13 (t0)
            218 CALL_METHOD              1
            220 BINARY_MULTIPLY

312         222 LOAD_FAST                5 (y_scale)
            224 LOAD_FAST                9 (outer_r)
            226 BINARY_MULTIPLY
            228 LOAD_GLOBAL              6 (np)
            230 LOAD_METHOD             11 (sin)
            232 LOAD_FAST               14 (t1)
            234 CALL_METHOD              1
            236 BINARY_MULTIPLY
            238 LOAD_FAST                5 (y_scale)
            240 LOAD_FAST               10 (inner_r)
            242 BINARY_MULTIPLY
            244 LOAD_GLOBAL              6 (np)
            246 LOAD_METHOD             11 (sin)
            248 LOAD_FAST               14 (t1)
            250 CALL_METHOD              1
            252 BINARY_MULTIPLY

311         254 BUILD_LIST               4
            256 STORE_FAST              16 (ys)

313         258 LOAD_FAST                0 (ax)
            260 LOAD_ATTR               12 (fill)
            262 LOAD_FAST               15 (xs)
            264 LOAD_FAST               16 (ys)
            266 LOAD_FAST                7 (cmap)
            268 LOAD_FAST               12 (i)
            270 LOAD_FAST                8 (n)
            272 BINARY_TRUE_DIVIDE
            274 CALL_FUNCTION            1
            276 LOAD_CONST              15 ('none')
            278 LOAD_CONST              16 (2)
            280 LOAD_CONST              17 (0.9)
            282 LOAD_CONST              18 (('color', 'edgecolor', 'zorder', 'alpha'))
            284 CALL_FUNCTION_KW         6
            286 POP_TOP
            288 JUMP_ABSOLUTE           56 (to 112)

315     >>  290 LOAD_FAST                0 (ax)
            292 LOAD_ATTR               13 (plot)
            294 LOAD_CONST              19 (-1.1)
            296 LOAD_CONST              20 (1.1)
            298 BUILD_LIST               2
            300 LOAD_CONST              13 (0)
            302 LOAD_CONST              13 (0)
            304 BUILD_LIST               2
            306 LOAD_GLOBAL             14 (BORDER)
            308 LOAD_CONST              21 (1.5)
            310 LOAD_CONST              14 (1)
            312 LOAD_CONST              22 (('color', 'lw', 'zorder'))
            314 CALL_FUNCTION_KW         5
            316 POP_TOP

316         318 LOAD_FAST                0 (ax)
            320 LOAD_ATTR               15 (text)
            322 LOAD_CONST              23 (-1.0)
            324 LOAD_CONST              24 (-0.05)
            326 LOAD_FAST                3 (vmin)
            328 FORMAT_VALUE             0
            330 LOAD_CONST              25 ('\n')
            332 LOAD_GLOBAL             16 (_t)
            334 LOAD_CONST              26 ('Normal')
            336 LOAD_FAST                2 (lang)
            338 CALL_FUNCTION            2
            340 FORMAT_VALUE             0
            342 BUILD_STRING             3
            344 LOAD_CONST              27 ('center')
            346 LOAD_CONST              28 ('top')
            348 LOAD_CONST              29 (10.5)
            350 LOAD_CONST              30 ('bold')
            352 LOAD_FAST                6 (palette)
            354 LOAD_CONST              13 (0)
            356 BINARY_SUBSCR
            358 LOAD_CONST              31 (3)
            360 LOAD_CONST              32 (('ha', 'va', 'fontsize', 'fontweight', 'color', 'zorder'))
            362 CALL_FUNCTION_KW         9
            364 POP_TOP

317         366 LOAD_FAST                0 (ax)
            368 LOAD_ATTR               15 (text)
            370 LOAD_CONST               6 (1.0)
            372 LOAD_CONST              24 (-0.05)
            374 LOAD_FAST                4 (vmax)
            376 FORMAT_VALUE             0
            378 LOAD_CONST              25 ('\n')
            380 LOAD_GLOBAL             16 (_t)
            382 LOAD_CONST              33 ('Severe')
            384 LOAD_FAST                2 (lang)
            386 CALL_FUNCTION            2
            388 FORMAT_VALUE             0
            390 BUILD_STRING             3
            392 LOAD_CONST              27 ('center')
            394 LOAD_CONST              28 ('top')
            396 LOAD_CONST              29 (10.5)
            398 LOAD_CONST              30 ('bold')
            400 LOAD_FAST                6 (palette)
            402 LOAD_CONST              31 (3)
            404 BINARY_SUBSCR
            406 LOAD_CONST              31 (3)
            408 LOAD_CONST              32 (('ha', 'va', 'fontsize', 'fontweight', 'color', 'zorder'))
            410 CALL_FUNCTION_KW         9
            412 POP_TOP

318         414 LOAD_GLOBAL              6 (np)
            416 LOAD_METHOD              7 (linspace)
            418 LOAD_FAST                3 (vmin)
            420 LOAD_FAST                4 (vmax)
            422 LOAD_CONST              34 (7)
            424 CALL_METHOD              3
            426 GET_ITER
        >>  428 FOR_ITER                62 (to 554)
            430 STORE_FAST              17 (tv)

319         432 LOAD_FAST               17 (tv)
            434 LOAD_FAST                3 (vmin)
            436 BINARY_SUBTRACT
            438 LOAD_GLOBAL             17 (max)
            440 LOAD_FAST                4 (vmax)
            442 LOAD_FAST                3 (vmin)
            444 BINARY_SUBTRACT
            446 LOAD_CONST              14 (1)
            448 CALL_FUNCTION            2
            450 BINARY_TRUE_DIVIDE
            452 STORE_FAST              18 (frac)

320         454 LOAD_GLOBAL              6 (np)
            456 LOAD_ATTR                8 (pi)
            458 LOAD_CONST              14 (1)
            460 LOAD_FAST               18 (frac)
            462 BINARY_SUBTRACT
            464 BINARY_MULTIPLY
            466 STORE_FAST              19 (ang_rad)

321         468 LOAD_FAST                0 (ax)
            470 LOAD_ATTR               13 (plot)
            472 LOAD_FAST               10 (inner_r)
            474 LOAD_GLOBAL              6 (np)
            476 LOAD_METHOD             10 (cos)
            478 LOAD_FAST               19 (ang_rad)
            480 CALL_METHOD              1
            482 BINARY_MULTIPLY
            484 LOAD_FAST               10 (inner_r)
            486 LOAD_CONST              35 (0.05)
            488 BINARY_ADD
            490 LOAD_GLOBAL              6 (np)
            492 LOAD_METHOD             10 (cos)
            494 LOAD_FAST               19 (ang_rad)
            496 CALL_METHOD              1
            498 BINARY_MULTIPLY
            500 BUILD_LIST               2

322         502 LOAD_FAST                5 (y_scale)
            504 LOAD_FAST               10 (inner_r)
            506 BINARY_MULTIPLY
            508 LOAD_GLOBAL              6 (np)
            510 LOAD_METHOD             11 (sin)
            512 LOAD_FAST               19 (ang_rad)
            514 CALL_METHOD              1
            516 BINARY_MULTIPLY
            518 LOAD_FAST                5 (y_scale)
            520 LOAD_FAST               10 (inner_r)
            522 LOAD_CONST              35 (0.05)
            524 BINARY_ADD
            526 BINARY_MULTIPLY
            528 LOAD_GLOBAL              6 (np)
            530 LOAD_METHOD             11 (sin)
            532 LOAD_FAST               19 (ang_rad)
            534 CALL_METHOD              1
            536 BINARY_MULTIPLY
            538 BUILD_LIST               2

323         540 LOAD_CONST              36 ('white')
            542 LOAD_CONST              21 (1.5)
            544 LOAD_CONST              37 (4)

321         546 LOAD_CONST              22 (('color', 'lw', 'zorder'))
            548 CALL_FUNCTION_KW         5
            550 POP_TOP
            552 JUMP_ABSOLUTE          214 (to 428)

324     >>  554 LOAD_GLOBAL              6 (np)
            556 LOAD_METHOD             18 (clip)
            558 LOAD_FAST                1 (val)
            560 LOAD_FAST                3 (vmin)
            562 BINARY_SUBTRACT
            564 LOAD_GLOBAL             17 (max)
            566 LOAD_FAST                4 (vmax)
            568 LOAD_FAST                3 (vmin)
            570 BINARY_SUBTRACT
            572 LOAD_CONST              14 (1)
            574 CALL_FUNCTION            2
            576 BINARY_TRUE_DIVIDE
            578 LOAD_CONST              13 (0)
            580 LOAD_CONST              14 (1)
            582 CALL_METHOD              3
            584 STORE_FAST              20 (frac_v)

325         586 LOAD_GLOBAL              6 (np)
            588 LOAD_ATTR                8 (pi)
            590 LOAD_CONST              14 (1)
            592 LOAD_FAST               20 (frac_v)
            594 BINARY_SUBTRACT
            596 BINARY_MULTIPLY
            598 STORE_FAST              19 (ang_rad)

326         600 LOAD_FAST               10 (inner_r)
            602 LOAD_CONST              38 (0.06)
            604 BINARY_SUBTRACT
            606 STORE_FAST              21 (tip_r)

327         608 LOAD_FAST               21 (tip_r)
            610 LOAD_GLOBAL              6 (np)
            612 LOAD_METHOD             10 (cos)
            614 LOAD_FAST               19 (ang_rad)
            616 CALL_METHOD              1
            618 BINARY_MULTIPLY
            620 LOAD_FAST                5 (y_scale)
            622 LOAD_FAST               21 (tip_r)
            624 BINARY_MULTIPLY
            626 LOAD_GLOBAL              6 (np)
            628 LOAD_METHOD             11 (sin)
            630 LOAD_FAST               19 (ang_rad)
            632 CALL_METHOD              1
            634 BINARY_MULTIPLY
            636 ROT_TWO
            638 STORE_FAST              22 (nx)
            640 STORE_FAST              23 (ny)

328         642 LOAD_FAST                0 (ax)
            644 LOAD_ATTR               19 (annotate)
            646 LOAD_CONST              39 ('')
            648 LOAD_FAST               22 (nx)
            650 LOAD_FAST               23 (ny)
            652 BUILD_TUPLE              2
            654 LOAD_CONST              40 ((0, 0))

329         656 LOAD_GLOBAL             20 (dict)
            658 LOAD_CONST              41 ('-|>')
            660 LOAD_GLOBAL             21 (TEXT_H)
            662 LOAD_CONST              42 (2.5)
            664 LOAD_CONST              43 (16)
            666 LOAD_CONST              44 (('arrowstyle', 'color', 'lw', 'mutation_scale'))
            668 CALL_FUNCTION_KW         4

330         670 LOAD_CONST              45 (6)

328         672 LOAD_CONST              46 (('xy', 'xytext', 'arrowprops', 'zorder'))
            674 CALL_FUNCTION_KW         5
            676 POP_TOP

331         678 LOAD_FAST                0 (ax)
            680 LOAD_ATTR               13 (plot)
            682 LOAD_CONST              13 (0)
            684 LOAD_CONST              13 (0)
            686 LOAD_CONST              47 ('o')
            688 LOAD_GLOBAL             21 (TEXT_H)
            690 LOAD_CONST              48 (8)
            692 LOAD_CONST              34 (7)
            694 LOAD_CONST              49 (('color', 'markersize', 'zorder'))
            696 CALL_FUNCTION_KW         6
            698 POP_TOP

333         700 LOAD_FAST                0 (ax)
            702 LOAD_ATTR               15 (text)
            704 LOAD_CONST              13 (0)
            706 LOAD_CONST              50 (-0.1)
            708 LOAD_FAST                1 (val)
            710 LOAD_CONST              51 ('.1f')
            712 FORMAT_VALUE             4 (with format)
            714 LOAD_CONST              27 ('center')
            716 LOAD_CONST              28 ('top')
            718 LOAD_CONST              52 (20)
            720 LOAD_CONST              30 ('bold')
            722 LOAD_GLOBAL             21 (TEXT_H)
            724 LOAD_CONST              48 (8)
            726 LOAD_CONST              32 (('ha', 'va', 'fontsize', 'fontweight', 'color', 'zorder'))
            728 CALL_FUNCTION_KW         9
            730 POP_TOP

334         732 LOAD_FAST                0 (ax)
            734 LOAD_ATTR               15 (text)
            736 LOAD_CONST              13 (0)
            738 LOAD_CONST              53 (-0.45)
            740 LOAD_GLOBAL             16 (_t)
            742 LOAD_CONST              54 ('events / hour')
            744 LOAD_FAST                2 (lang)
            746 CALL_FUNCTION            2
            748 LOAD_CONST              27 ('center')
            750 LOAD_CONST              27 ('center')
            752 LOAD_CONST              55 (11)
            754 LOAD_CONST              30 ('bold')
            756 LOAD_GLOBAL             22 (TEXT_L)
            758 LOAD_CONST              48 (8)
            760 LOAD_CONST              32 (('ha', 'va', 'fontsize', 'fontweight', 'color', 'zorder'))
            762 CALL_FUNCTION_KW         9
            764 POP_TOP

335         766 LOAD_FAST                1 (val)
            768 LOAD_CONST              56 (5)
            770 COMPARE_OP               0 (<)
            772 EXTENDED_ARG             1
            774 POP_JUMP_IF_FALSE      390 (to 780)
            776 LOAD_CONST              26 ('Normal')
            778 JUMP_FORWARD            15 (to 810)
        >>  780 LOAD_FAST                1 (val)
            782 LOAD_CONST              57 (15)
            784 COMPARE_OP               0 (<)
            786 EXTENDED_ARG             1
            788 POP_JUMP_IF_FALSE      397 (to 794)
            790 LOAD_CONST              58 ('Mild')
            792 JUMP_FORWARD             8 (to 810)
        >>  794 LOAD_FAST                1 (val)
            796 LOAD_CONST              59 (30)
            798 COMPARE_OP               0 (<)
            800 EXTENDED_ARG             1
            802 POP_JUMP_IF_FALSE      404 (to 808)
            804 LOAD_CONST              60 ('Moderate')
            806 JUMP_FORWARD             1 (to 810)
        >>  808 LOAD_CONST              33 ('Severe')
        >>  810 STORE_FAST              24 (sev)

336         812 LOAD_FAST                6 (palette)
            814 LOAD_CONST              13 (0)
            816 BINARY_SUBSCR
            818 LOAD_FAST                6 (palette)
            820 LOAD_CONST              14 (1)
            822 BINARY_SUBSCR
            824 LOAD_FAST                6 (palette)
            826 LOAD_CONST              16 (2)
            828 BINARY_SUBSCR
            830 LOAD_FAST                6 (palette)
            832 LOAD_CONST              31 (3)
            834 BINARY_SUBSCR
            836 LOAD_CONST              61 (('Normal', 'Mild', 'Moderate', 'Severe'))
            838 BUILD_CONST_KEY_MAP      4
            840 LOAD_METHOD             23 (get)
            842 LOAD_FAST               24 (sev)
            844 LOAD_GLOBAL             24 (TEXT_M)
            846 CALL_METHOD              2
            848 STORE_FAST              25 (sev_col)

337         850 LOAD_FAST                0 (ax)
            852 LOAD_ATTR               15 (text)
            854 LOAD_CONST              13 (0)
            856 LOAD_CONST              62 (-0.65)
            858 LOAD_GLOBAL             16 (_t)
            860 LOAD_FAST               24 (sev)
            862 LOAD_FAST                2 (lang)
            864 CALL_FUNCTION            2
            866 LOAD_CONST              27 ('center')
            868 LOAD_CONST              27 ('center')
            870 LOAD_CONST              63 (13)
            872 LOAD_CONST              30 ('bold')
            874 LOAD_FAST               25 (sev_col)
            876 LOAD_CONST              48 (8)
            878 LOAD_CONST              32 (('ha', 'va', 'fontsize', 'fontweight', 'color', 'zorder'))
            880 CALL_FUNCTION_KW         9
            882 POP_TOP
            884 LOAD_CONST               0 (None)
            886 RETURN_VALUE

--- _bullets ---
342           0 BUILD_LIST               0
              2 STORE_FAST               4 (b)

343           4 LOAD_FAST                0 (s)
              6 LOAD_CONST               1 ('SE')
              8 BINARY_SUBSCR
             10 STORE_FAST               5 (se)

344          12 LOAD_FAST                3 (lang)
             14 LOAD_CONST               2 ('he')
             16 COMPARE_OP               2 (==)
             18 POP_JUMP_IF_FALSE      241 (to 482)

345          20 LOAD_FAST                5 (se)
             22 LOAD_CONST               3 (85)
             24 COMPARE_OP               5 (>=)
             26 POP_JUMP_IF_FALSE       25 (to 50)
             28 LOAD_FAST                4 (b)
             30 LOAD_METHOD              0 (append)
             32 LOAD_CONST               4 ('יעילות שינה טובה (')
             34 LOAD_FAST                5 (se)
             36 LOAD_CONST               5 ('.0f')
             38 FORMAT_VALUE             4 (with format)
             40 LOAD_CONST               6 ('%) — בטווח התקין.')
             42 BUILD_STRING             3
             44 CALL_METHOD              1
             46 POP_TOP
             48 JUMP_FORWARD            25 (to 100)

346     >>   50 LOAD_FAST                5 (se)
             52 LOAD_CONST               7 (70)
             54 COMPARE_OP               5 (>=)
             56 POP_JUMP_IF_FALSE       40 (to 80)
             58 LOAD_FAST                4 (b)
             60 LOAD_METHOD              0 (append)
             62 LOAD_CONST               8 ('יעילות שינה מופחתת במידה מתונה (')
             64 LOAD_FAST                5 (se)
             66 LOAD_CONST               5 ('.0f')
             68 FORMAT_VALUE             4 (with format)
             70 LOAD_CONST               9 ('%).')
             72 BUILD_STRING             3
             74 CALL_METHOD              1
             76 POP_TOP
             78 JUMP_FORWARD            10 (to 100)

347     >>   80 LOAD_FAST                4 (b)
             82 LOAD_METHOD              0 (append)
             84 LOAD_CONST              10 ('יעילות שינה נמוכה (')
             86 LOAD_FAST                5 (se)
             88 LOAD_CONST               5 ('.0f')
             90 FORMAT_VALUE             4 (with format)
             92 LOAD_CONST              11 ('%) — ערנות משמעותית במהלך הלילה.')
             94 BUILD_STRING             3
             96 CALL_METHOD              1
             98 POP_TOP

349     >>  100 LOAD_FAST                0 (s)
            102 LOAD_CONST              12 ('N3')
            104 BINARY_SUBSCR
            106 LOAD_FAST                0 (s)
            108 LOAD_CONST              13 ('REM')
            110 BINARY_SUBSCR
            112 ROT_TWO
            114 STORE_FAST               6 (n3)
            116 STORE_FAST               7 (rem)

350         118 LOAD_FAST                6 (n3)
            120 LOAD_CONST              14 (15)
            122 COMPARE_OP               5 (>=)
            124 POP_JUMP_IF_FALSE       73 (to 146)
            126 LOAD_FAST                7 (rem)
            128 LOAD_CONST              15 (18)
            130 COMPARE_OP               5 (>=)
            132 POP_JUMP_IF_FALSE       73 (to 146)

351         134 LOAD_FAST                4 (b)
            136 LOAD_METHOD              0 (append)
            138 LOAD_CONST              16 ('ארכיטקטורת שינה שמורה היטב עם שנת חלום (REM) ושינה עמוקה (N3) מספקת.')
            140 CALL_METHOD              1
            142 POP_TOP
            144 JUMP_FORWARD            29 (to 204)

352     >>  146 LOAD_FAST                6 (n3)
            148 LOAD_CONST              17 (10)
            150 COMPARE_OP               0 (<)
            152 POP_JUMP_IF_FALSE       88 (to 176)

353         154 LOAD_FAST                4 (b)
            156 LOAD_METHOD              0 (append)
            158 LOAD_CONST              18 ('שינה עמוקה (N3) מופחתת (')
            160 LOAD_FAST                6 (n3)
            162 LOAD_CONST               5 ('.0f')
            164 FORMAT_VALUE             4 (with format)
            166 LOAD_CONST              19 ('%) — ייתכן שהשינה הייתה קלה מהרגיל.')
            168 BUILD_STRING             3
            170 CALL_METHOD              1
            172 POP_TOP
            174 JUMP_FORWARD            14 (to 204)

354     >>  176 LOAD_FAST                7 (rem)
            178 LOAD_CONST              14 (15)
            180 COMPARE_OP               0 (<)
            182 POP_JUMP_IF_FALSE      102 (to 204)

355         184 LOAD_FAST                4 (b)
            186 LOAD_METHOD              0 (append)
            188 LOAD_CONST              20 ('שנת חלום (REM) נמוכה (')
            190 LOAD_FAST                7 (rem)
            192 LOAD_CONST               5 ('.0f')
            194 FORMAT_VALUE             4 (with format)
            196 LOAD_CONST              21 ('%) — עשוי להשפיע על התאוששות.')
            198 BUILD_STRING             3
            200 CALL_METHOD              1
            202 POP_TOP

357     >>  204 LOAD_FAST                1 (rdi)
            206 LOAD_CONST               0 (None)
            208 IS_OP                    1
            210 POP_JUMP_IF_FALSE      146 (to 292)

358         212 LOAD_FAST                1 (rdi)
            214 LOAD_CONST              22 (5)
            216 COMPARE_OP               0 (<)
            218 POP_JUMP_IF_FALSE      121 (to 242)
            220 LOAD_FAST                4 (b)
            222 LOAD_METHOD              0 (append)
            224 LOAD_CONST              23 ('לא זוהו הפרעות נשימה משמעותיות (pAHI ')
            226 LOAD_FAST                1 (rdi)
            228 LOAD_CONST              24 ('.1f')
            230 FORMAT_VALUE             4 (with format)
            232 LOAD_CONST              25 ('/hr).')
            234 BUILD_STRING             3
            236 CALL_METHOD              1
            238 POP_TOP
            240 JUMP_FORWARD            25 (to 292)

359     >>  242 LOAD_FAST                1 (rdi)
            244 LOAD_CONST              14 (15)
            246 COMPARE_OP               0 (<)
            248 POP_JUMP_IF_FALSE      136 (to 272)
            250 LOAD_FAST                4 (b)
            252 LOAD_METHOD              0 (append)
            254 LOAD_CONST              26 ('נצפו הפרעות נשימה קלות (pAHI ')
            256 LOAD_FAST                1 (rdi)
            258 LOAD_CONST              24 ('.1f')
            260 FORMAT_VALUE             4 (with format)
            262 LOAD_CONST              27 ('/hr) — מומלץ מעקב.')
            264 BUILD_STRING             3
            266 CALL_METHOD              1
            268 POP_TOP
            270 JUMP_FORWARD            10 (to 292)

360     >>  272 LOAD_FAST                4 (b)
            274 LOAD_METHOD              0 (append)
            276 LOAD_CONST              28 ('הפרעות נשימה משמעותיות (pAHI ')
            278 LOAD_FAST                1 (rdi)
            280 LOAD_CONST              24 ('.1f')
            282 FORMAT_VALUE             4 (with format)
            284 LOAD_CONST              29 ('/hr) — מומלץ ייעוץ רופא.')
            286 BUILD_STRING             3
            288 CALL_METHOD              1
            290 POP_TOP

362     >>  292 LOAD_FAST                2 (spo2)
            294 POP_JUMP_IF_FALSE      189 (to 378)

363         296 LOAD_FAST                2 (spo2)
            298 LOAD_METHOD              1 (get)
            300 LOAD_CONST              30 ('avg')
            302 LOAD_CONST              31 (0)
            304 CALL_METHOD              2
            306 STORE_FAST               8 (avg)
            308 LOAD_FAST                2 (spo2)
            310 LOAD_METHOD              1 (get)
            312 LOAD_CONST              32 ('t_under90')
            314 LOAD_CONST              31 (0)
            316 CALL_METHOD              2
            318 STORE_FAST               9 (t90)

364         320 LOAD_FAST                8 (avg)
            322 LOAD_CONST              33 (95)
            324 COMPARE_OP               5 (>=)
            326 POP_JUMP_IF_FALSE      175 (to 350)
            328 LOAD_FAST                4 (b)
            330 LOAD_METHOD              0 (append)
            332 LOAD_CONST              34 ('ריווי חמצן בדם תקין (ממוצע SpO2 ')
            334 LOAD_FAST                8 (avg)
            336 LOAD_CONST              24 ('.1f')
            338 FORMAT_VALUE             4 (with format)
            340 LOAD_CONST               9 ('%).')
            342 BUILD_STRING             3
            344 CALL_METHOD              1
            346 POP_TOP
            348 JUMP_FORWARD            14 (to 378)

365     >>  350 LOAD_FAST                4 (b)
            352 LOAD_METHOD              0 (append)
            354 LOAD_CONST              35 ('ממוצע SpO2 ')
            356 LOAD_FAST                8 (avg)
            358 LOAD_CONST              24 ('.1f')
            360 FORMAT_VALUE             4 (with format)
            362 LOAD_CONST              36 ('% עם ')
            364 LOAD_FAST                9 (t90)
            366 LOAD_CONST               5 ('.0f')
            368 FORMAT_VALUE             4 (with format)
            370 LOAD_CONST              37 (' דקות מתחת ל-90% — מומלץ בירור רפואי.')
            372 BUILD_STRING             5
            374 CALL_METHOD              1
            376 POP_TOP

367     >>  378 LOAD_FAST                0 (s)
            380 LOAD_CONST              38 ('WASO')
            382 BINARY_SUBSCR
            384 LOAD_CONST              39 (60)
            386 BINARY_TRUE_DIVIDE
            388 STORE_FAST              10 (wm)

368         390 LOAD_FAST               10 (wm)
            392 LOAD_CONST              40 (20)
            394 COMPARE_OP               0 (<)
            396 POP_JUMP_IF_FALSE      205 (to 410)
            398 LOAD_FAST                4 (b)
            400 LOAD_METHOD              0 (append)
            402 LOAD_CONST              41 ('יקיצות מינימליות במהלך הלילה — רצף שינה טוב.')
            404 CALL_METHOD              1
            406 POP_TOP
            408 JUMP_FORWARD            25 (to 460)

369     >>  410 LOAD_FAST               10 (wm)
            412 LOAD_CONST              42 (45)
            414 COMPARE_OP               0 (<)
            416 POP_JUMP_IF_FALSE      220 (to 440)
            418 LOAD_FAST                4 (b)
            420 LOAD_METHOD              0 (append)
            422 LOAD_CONST              43 ('ערנות לילית מתונה (')
            424 LOAD_FAST               10 (wm)
            426 LOAD_CONST               5 ('.0f')
            428 FORMAT_VALUE             4 (with format)
            430 LOAD_CONST              44 (' דקות לאחר תחילת שינה).')
            432 BUILD_STRING             3
            434 CALL_METHOD              1
            436 POP_TOP
            438 JUMP_FORWARD            10 (to 460)

370     >>  440 LOAD_FAST                4 (b)
            442 LOAD_METHOD              0 (append)
            444 LOAD_CONST              45 ('יקיצות מרובות (')
            446 LOAD_FAST               10 (wm)
            448 LOAD_CONST               5 ('.0f')
            450 FORMAT_VALUE             4 (with format)
            452 LOAD_CONST              46 (' דקות WASO) — זוהה קיטוע שינה.')
            454 BUILD_STRING             3
            456 CALL_METHOD              1
            458 POP_TOP

371     >>  460 LOAD_CONST              47 (<code object <listcomp> at 0x0000026C8AA316E0, file "patient_report.py", line 371>)
            462 LOAD_CONST              48 ('_bullets.<locals>.<listcomp>')
            464 MAKE_FUNCTION            0
            466 LOAD_FAST                4 (b)
            468 LOAD_CONST               0 (None)
            470 LOAD_CONST              22 (5)
            472 BUILD_SLICE              2
            474 BINARY_SUBSCR
            476 GET_ITER
            478 CALL_FUNCTION            1
            480 RETURN_VALUE

373     >>  482 LOAD_FAST                5 (se)
            484 LOAD_CONST               3 (85)
            486 COMPARE_OP               5 (>=)
            488 EXTENDED_ARG             1
            490 POP_JUMP_IF_FALSE      257 (to 514)
            492 LOAD_FAST                4 (b)
            494 LOAD_METHOD              0 (append)
            496 LOAD_CONST              49 ('Sleep efficiency is good (')
            498 LOAD_FAST                5 (se)
            500 LOAD_CONST               5 ('.0f')
            502 FORMAT_VALUE             4 (with format)
            504 LOAD_CONST              50 ('%) — within the normal range.')
            506 BUILD_STRING             3
            508 CALL_METHOD              1
            510 POP_TOP
            512 JUMP_FORWARD            26 (to 566)

374     >>  514 LOAD_FAST                5 (se)
            516 LOAD_CONST               7 (70)
            518 COMPARE_OP               5 (>=)
            520 EXTENDED_ARG             1
            522 POP_JUMP_IF_FALSE      273 (to 546)
            524 LOAD_FAST                4 (b)
            526 LOAD_METHOD              0 (append)
            528 LOAD_CONST              51 ('Sleep efficiency is moderately reduced (')
            530 LOAD_FAST                5 (se)
            532 LOAD_CONST               5 ('.0f')
            534 FORMAT_VALUE             4 (with format)
            536 LOAD_CONST               9 ('%).')
            538 BUILD_STRING             3
            540 CALL_METHOD              1
            542 POP_TOP
            544 JUMP_FORWARD            10 (to 566)

375     >>  546 LOAD_FAST                4 (b)
            548 LOAD_METHOD              0 (append)
            550 LOAD_CONST              52 ('Sleep efficiency is low (')
            552 LOAD_FAST                5 (se)
            554 LOAD_CONST               5 ('.0f')
            556 FORMAT_VALUE             4 (with format)
            558 LOAD_CONST              53 ('%) — significant nighttime wakefulness.')
            560 BUILD_STRING             3
            562 CALL_METHOD              1
            564 POP_TOP

376     >>  566 LOAD_FAST                0 (s)
            568 LOAD_CONST              12 ('N3')
            570 BINARY_SUBSCR
            572 LOAD_FAST                0 (s)
            574 LOAD_CONST              13 ('REM')
            576 BINARY_SUBSCR
            578 ROT_TWO
            580 STORE_FAST               6 (n3)
            582 STORE_FAST               7 (rem)

377         584 LOAD_FAST                6 (n3)
            586 LOAD_CONST              14 (15)
            588 COMPARE_OP               5 (>=)
            590 EXTENDED_ARG             1
            592 POP_JUMP_IF_FALSE      308 (to 616)
            594 LOAD_FAST                7 (rem)
            596 LOAD_CONST              15 (18)
            598 COMPARE_OP               5 (>=)
            600 EXTENDED_ARG             1
            602 POP_JUMP_IF_FALSE      308 (to 616)

378         604 LOAD_FAST                4 (b)
            606 LOAD_METHOD              0 (append)
            608 LOAD_CONST              54 ('Sleep architecture is well-preserved with adequate deep (N3) and REM sleep.')
            610 CALL_METHOD              1
            612 POP_TOP
            614 JUMP_FORWARD            31 (to 678)

379     >>  616 LOAD_FAST                6 (n3)
            618 LOAD_CONST              17 (10)
            620 COMPARE_OP               0 (<)
            622 EXTENDED_ARG             1
            624 POP_JUMP_IF_FALSE      324 (to 648)

380         626 LOAD_FAST                4 (b)
            628 LOAD_METHOD              0 (append)
            630 LOAD_CONST              55 ('Deep sleep (N3) is reduced (')
            632 LOAD_FAST                6 (n3)
            634 LOAD_CONST               5 ('.0f')
            636 FORMAT_VALUE             4 (with format)
            638 LOAD_CONST              56 ('%) — sleep may be lighter than normal.')
            640 BUILD_STRING             3
            642 CALL_METHOD              1
            644 POP_TOP
            646 JUMP_FORWARD            15 (to 678)

381     >>  648 LOAD_FAST                7 (rem)
            650 LOAD_CONST              14 (15)
            652 COMPARE_OP               0 (<)
            654 EXTENDED_ARG             1
            656 POP_JUMP_IF_FALSE      339 (to 678)

382         658 LOAD_FAST                4 (b)
            660 LOAD_METHOD              0 (append)
            662 LOAD_CONST              57 ('REM sleep is low (')
            664 LOAD_FAST                7 (rem)
            666 LOAD_CONST               5 ('.0f')
            668 FORMAT_VALUE             4 (with format)
            670 LOAD_CONST              58 ('%) — may affect memory consolidation and recovery.')
            672 BUILD_STRING             3
            674 CALL_METHOD              1
            676 POP_TOP

383     >>  678 LOAD_FAST                1 (rdi)
            680 LOAD_CONST               0 (None)
            682 IS_OP                    1
            684 EXTENDED_ARG             1
            686 POP_JUMP_IF_FALSE      386 (to 772)

384         688 LOAD_FAST                1 (rdi)
            690 LOAD_CONST              22 (5)
            692 COMPARE_OP               0 (<)
            694 EXTENDED_ARG             1
            696 POP_JUMP_IF_FALSE      360 (to 720)
            698 LOAD_FAST                4 (b)
            700 LOAD_METHOD              0 (append)
            702 LOAD_CONST              59 ('No significant respiratory disturbances detected (pAHI ')
            704 LOAD_FAST                1 (rdi)
            706 LOAD_CONST              24 ('.1f')
            708 FORMAT_VALUE             4 (with format)
            710 LOAD_CONST              25 ('/hr).')
            712 BUILD_STRING             3
            714 CALL_METHOD              1
            716 POP_TOP
            718 JUMP_FORWARD            26 (to 772)

385     >>  720 LOAD_FAST                1 (rdi)
            722 LOAD_CONST              14 (15)
            724 COMPARE_OP               0 (<)
            726 EXTENDED_ARG             1
            728 POP_JUMP_IF_FALSE      376 (to 752)
            730 LOAD_FAST                4 (b)
            732 LOAD_METHOD              0 (append)
            734 LOAD_CONST              60 ('Mild respiratory disturbances noted (pAHI ')
            736 LOAD_FAST                1 (rdi)
            738 LOAD_CONST              24 ('.1f')
            740 FORMAT_VALUE             4 (with format)
            742 LOAD_CONST              61 ('/hr) — monitoring advised.')
            744 BUILD_STRING             3
            746 CALL_METHOD              1
            748 POP_TOP
            750 JUMP_FORWARD            10 (to 772)

386     >>  752 LOAD_FAST                4 (b)
            754 LOAD_METHOD              0 (append)
            756 LOAD_CONST              62 ('Significant respiratory disturbances (pAHI ')
            758 LOAD_FAST                1 (rdi)
            760 LOAD_CONST              24 ('.1f')
            762 FORMAT_VALUE             4 (with format)
            764 LOAD_CONST              63 ('/hr) — follow-up recommended.')
            766 BUILD_STRING             3
            768 CALL_METHOD              1
            770 POP_TOP

387     >>  772 LOAD_FAST                2 (spo2)
            774 EXTENDED_ARG             1
            776 POP_JUMP_IF_FALSE      431 (to 862)

388         778 LOAD_FAST                2 (spo2)
            780 LOAD_METHOD              1 (get)
            782 LOAD_CONST              30 ('avg')
            784 LOAD_CONST              31 (0)
            786 CALL_METHOD              2
            788 STORE_FAST               8 (avg)
            790 LOAD_FAST                2 (spo2)
            792 LOAD_METHOD              1 (get)
            794 LOAD_CONST              32 ('t_under90')
            796 LOAD_CONST              31 (0)
            798 CALL_METHOD              2
            800 STORE_FAST               9 (t90)

389         802 LOAD_FAST                8 (avg)
            804 LOAD_CONST              33 (95)
            806 COMPARE_OP               5 (>=)
            808 EXTENDED_ARG             1
            810 POP_JUMP_IF_FALSE      417 (to 834)
            812 LOAD_FAST                4 (b)
            814 LOAD_METHOD              0 (append)
            816 LOAD_CONST              64 ('Blood oxygen saturation is normal (mean SpO2 ')
            818 LOAD_FAST                8 (avg)
            820 LOAD_CONST              24 ('.1f')
            822 FORMAT_VALUE             4 (with format)
            824 LOAD_CONST               9 ('%).')
            826 BUILD_STRING             3
            828 CALL_METHOD              1
            830 POP_TOP
            832 JUMP_FORWARD            14 (to 862)

390     >>  834 LOAD_FAST                4 (b)
            836 LOAD_METHOD              0 (append)
            838 LOAD_CONST              65 ('Mean SpO2 ')
            840 LOAD_FAST                8 (avg)
            842 LOAD_CONST              24 ('.1f')
            844 FORMAT_VALUE             4 (with format)
            846 LOAD_CONST              66 ('% with ')
            848 LOAD_FAST                9 (t90)
            850 LOAD_CONST               5 ('.0f')
            852 FORMAT_VALUE             4 (with format)
            854 LOAD_CONST              67 (' min below 90% — oxygenation review advised.')
            856 BUILD_STRING             5
            858 CALL_METHOD              1
            860 POP_TOP

391     >>  862 LOAD_FAST                0 (s)
            864 LOAD_CONST              38 ('WASO')
            866 BINARY_SUBSCR
            868 LOAD_CONST              39 (60)
            870 BINARY_TRUE_DIVIDE
            872 STORE_FAST              10 (wm)

392         874 LOAD_FAST               10 (wm)
            876 LOAD_CONST              40 (20)
            878 COMPARE_OP               0 (<)
            880 EXTENDED_ARG             1
            882 POP_JUMP_IF_FALSE      448 (to 896)
            884 LOAD_FAST                4 (b)
            886 LOAD_METHOD              0 (append)
            888 LOAD_CONST              68 ('Minimal nighttime awakenings — good sleep continuity.')
            890 CALL_METHOD              1
            892 POP_TOP
            894 JUMP_FORWARD            26 (to 948)

393     >>  896 LOAD_FAST               10 (wm)
            898 LOAD_CONST              42 (45)
            900 COMPARE_OP               0 (<)
            902 EXTENDED_ARG             1
            904 POP_JUMP_IF_FALSE      464 (to 928)
            906 LOAD_FAST                4 (b)
            908 LOAD_METHOD              0 (append)
            910 LOAD_CONST              69 ('Moderate nighttime wakefulness (')
            912 LOAD_FAST               10 (wm)
            914 LOAD_CONST               5 ('.0f')
            916 FORMAT_VALUE             4 (with format)
            918 LOAD_CONST              70 (' min after sleep onset).')
            920 BUILD_STRING             3
            922 CALL_METHOD              1
            924 POP_TOP
            926 JUMP_FORWARD            10 (to 948)

394     >>  928 LOAD_FAST                4 (b)
            930 LOAD_METHOD              0 (append)
            932 LOAD_CONST              71 ('Frequent awakenings (')
            934 LOAD_FAST               10 (wm)
            936 LOAD_CONST               5 ('.0f')
            938 FORMAT_VALUE             4 (with format)
            940 LOAD_CONST              72 (' min WASO) — sleep fragmentation detected.')
            942 BUILD_STRING             3
            944 CALL_METHOD              1
            946 POP_TOP

395     >>  948 LOAD_FAST                4 (b)
            950 LOAD_CONST               0 (None)
            952 LOAD_CONST              22 (5)
            954 BUILD_SLICE              2
            956 BINARY_SUBSCR
            958 RETURN_VALUE

Disassembly of <code object <listcomp> at 0x0000026C8AA316E0, file "patient_report.py", line 371>:
371           0 BUILD_LIST               0
              2 LOAD_FAST                0 (.0)
        >>    4 FOR_ITER                 6 (to 18)
              6 STORE_FAST               1 (line)
              8 LOAD_GLOBAL              0 (get_display)
             10 LOAD_FAST                1 (line)
             12 CALL_FUNCTION            1
             14 LIST_APPEND              2
             16 JUMP_ABSOLUTE            2 (to 4)
        >>   18 RETURN_VALUE

--- _generate_single_report ---
422           0 LOAD_FAST                9 (rdi)
              2 LOAD_CONST               0 (None)
              4 IS_OP                    1
              6 POP_JUMP_IF_FALSE        6 (to 12)
              8 LOAD_FAST                9 (rdi)
             10 JUMP_FORWARD             1 (to 14)
        >>   12 LOAD_FAST               10 (ahi)
        >>   14 STORE_FAST              20 (rdi_v)

423          16 LOAD_GLOBAL              0 (_stats)
             18 LOAD_FAST                0 (hypno_1hz_int)
             20 CALL_FUNCTION            1
             22 STORE_FAST              21 (st)

426          24 LOAD_GLOBAL              1 (plt)
             26 LOAD_ATTR                2 (figure)
             28 LOAD_CONST               1 ((8.27, 11.69))
             30 LOAD_GLOBAL              3 (BG)
             32 LOAD_CONST               2 (('figsize', 'facecolor'))
             34 CALL_FUNCTION_KW         2
             36 STORE_FAST              22 (fig)

429          38 SETUP_FINALLY           93 (to 226)

430          40 LOAD_CONST               3 (0)
             42 LOAD_CONST               0 (None)
             44 IMPORT_NAME              4 (os)
             46 STORE_DEREF              1 (os)
             48 LOAD_CONST               3 (0)
             50 LOAD_CONST               0 (None)
             52 IMPORT_NAME              5 (sys)
             54 STORE_DEREF              3 (sys)

431          56 LOAD_CONST               3 (0)
             58 LOAD_CONST               4 (('Image',))
             60 IMPORT_NAME              6 (PIL)
             62 IMPORT_FROM              7 (Image)
             64 STORE_FAST              23 (Image)
             66 POP_TOP

432          68 LOAD_CLOSURE             1 (os)
             70 LOAD_CLOSURE             3 (sys)
             72 BUILD_TUPLE              2
             74 LOAD_CONST               5 (<code object _resource_path at 0x0000026C8AA32340, file "patient_report.py", line 432>)
             76 LOAD_CONST               6 ('_generate_single_report.<locals>._resource_path')
             78 MAKE_FUNCTION            8 (closure)
             80 STORE_FAST              24 (_resource_path)

437          82 LOAD_FAST               24 (_resource_path)
             84 LOAD_CONST               7 ('logo_up.png')
             86 CALL_FUNCTION            1
             88 STORE_FAST              25 (logo_up_path)

438          90 LOAD_DEREF               1 (os)
             92 LOAD_ATTR                8 (path)
             94 LOAD_METHOD              9 (exists)
             96 LOAD_FAST               25 (logo_up_path)
             98 CALL_METHOD              1
            100 POP_JUMP_IF_FALSE       76 (to 152)

439         102 LOAD_FAST               23 (Image)
            104 LOAD_METHOD             10 (open)
            106 LOAD_FAST               25 (logo_up_path)
            108 CALL_METHOD              1
            110 STORE_FAST              26 (logo_up_img)

440         112 LOAD_FAST               22 (fig)
            114 LOAD_ATTR               11 (add_axes)
            116 BUILD_LIST               0
            118 LOAD_CONST               8 ((0.38, 0.945, 0.24, 0.072))
            120 LIST_EXTEND              1
            122 LOAD_CONST               9 ('N')
            124 LOAD_CONST              10 (10)
            126 LOAD_CONST              11 (('anchor', 'zorder'))
            128 CALL_FUNCTION_KW         3
            130 STORE_FAST              27 (ax_logo_up)

441         132 LOAD_FAST               27 (ax_logo_up)
            134 LOAD_METHOD             12 (imshow)
            136 LOAD_FAST               26 (logo_up_img)
            138 CALL_METHOD              1
            140 POP_TOP

442         142 LOAD_FAST               27 (ax_logo_up)
            144 LOAD_METHOD             13 (axis)
            146 LOAD_CONST              12 ('off')
            148 CALL_METHOD              1
            150 POP_TOP

444     >>  152 LOAD_FAST               24 (_resource_path)
            154 LOAD_CONST              13 ('logo_down.png')
            156 CALL_FUNCTION            1
            158 STORE_FAST              28 (logo_down_path)

445         160 LOAD_DEREF               1 (os)
            162 LOAD_ATTR                8 (path)
            164 LOAD_METHOD              9 (exists)
            166 LOAD_FAST               28 (logo_down_path)
            168 CALL_METHOD              1
            170 POP_JUMP_IF_FALSE      111 (to 222)

446         172 LOAD_FAST               23 (Image)
            174 LOAD_METHOD             10 (open)
            176 LOAD_FAST               28 (logo_down_path)
            178 CALL_METHOD              1
            180 STORE_FAST              29 (logo_down_img)

447         182 LOAD_FAST               22 (fig)
            184 LOAD_ATTR               11 (add_axes)
            186 BUILD_LIST               0
            188 LOAD_CONST              14 ((0.05, 0.0, 0.9, 0.096))
            190 LIST_EXTEND              1
            192 LOAD_CONST              15 ('S')
            194 LOAD_CONST              10 (10)
            196 LOAD_CONST              11 (('anchor', 'zorder'))
            198 CALL_FUNCTION_KW         3
            200 STORE_FAST              30 (ax_logo_down)

448         202 LOAD_FAST               30 (ax_logo_down)
            204 LOAD_METHOD             12 (imshow)
            206 LOAD_FAST               29 (logo_down_img)
            208 CALL_METHOD              1
            210 POP_TOP

449         212 LOAD_FAST               30 (ax_logo_down)
            214 LOAD_METHOD             13 (axis)
            216 LOAD_CONST              12 ('off')
            218 CALL_METHOD              1
            220 POP_TOP
        >>  222 POP_BLOCK
            224 JUMP_FORWARD            25 (to 276)

450     >>  226 DUP_TOP
            228 LOAD_GLOBAL             14 (Exception)
            230 JUMP_IF_NOT_EXC_MATCH   137 (to 274)
            232 POP_TOP
            234 STORE_FAST              31 (e)
            236 POP_TOP
            238 SETUP_FINALLY           13 (to 266)

451         240 LOAD_GLOBAL             15 (print)
            242 LOAD_CONST              16 ('Logo error: ')
            244 LOAD_FAST               31 (e)
            246 FORMAT_VALUE             0
            248 BUILD_STRING             2
            250 CALL_FUNCTION            1
            252 POP_TOP
            254 POP_BLOCK
            256 POP_EXCEPT
            258 LOAD_CONST               0 (None)
            260 STORE_FAST              31 (e)
            262 DELETE_FAST             31 (e)
            264 JUMP_FORWARD             5 (to 276)
        >>  266 LOAD_CONST               0 (None)
            268 STORE_FAST              31 (e)
            270 DELETE_FAST             31 (e)
            272 RERAISE                  1

450     >>  274 RERAISE                  0

453     >>  276 LOAD_FAST               22 (fig)
            278 LOAD_ATTR               16 (patch)
            280 LOAD_METHOD             17 (set_facecolor)
            282 LOAD_GLOBAL              3 (BG)
            284 CALL_METHOD              1
            286 POP_TOP

456         288 LOAD_FAST               22 (fig)
            290 LOAD_METHOD             11 (add_axes)
            292 BUILD_LIST               0
            294 LOAD_CONST              17 ((0.0, 0.915, 1.0, 0.04))
            296 LIST_EXTEND              1
            298 CALL_METHOD              1
            300 STORE_FAST              32 (ax_title)

457         302 LOAD_FAST               32 (ax_title)
            304 LOAD_METHOD             13 (axis)
            306 LOAD_CONST              12 ('off')
            308 CALL_METHOD              1
            310 POP_TOP

458         312 LOAD_GLOBAL             18 (_t)
            314 LOAD_CONST              18 ('Overnight Sleep Study Report')
            316 LOAD_DEREF               0 (lang)
            318 CALL_FUNCTION            2
            320 STORE_FAST              33 (t_text)

459         322 LOAD_FAST               32 (ax_title)
            324 LOAD_ATTR               19 (text)
            326 LOAD_CONST              19 (0.5)
            328 LOAD_CONST              19 (0.5)
            330 LOAD_FAST               33 (t_text)

460         332 LOAD_FAST               32 (ax_title)
            334 LOAD_ATTR               20 (transAxes)

461         336 LOAD_CONST              20 (17)
            338 LOAD_CONST              21 ('bold')
            340 LOAD_GLOBAL             21 (TEXT_H)
            342 LOAD_CONST              22 ('center')
            344 LOAD_CONST              22 ('center')

459         346 LOAD_CONST              23 (('transform', 'fontsize', 'fontweight', 'color', 'va', 'ha'))
            348 CALL_FUNCTION_KW         9
            350 POP_TOP

463         352 LOAD_FAST                2 (subject_name)
            354 POP_JUMP_IF_FALSE      181 (to 362)

464         356 LOAD_FAST                2 (subject_name)
            358 STORE_FAST              34 (sid)
            360 JUMP_FORWARD             9 (to 380)

466     >>  362 LOAD_GLOBAL             22 (str)
            364 LOAD_FAST                1 (subject_id)
            366 CALL_FUNCTION            1
            368 LOAD_METHOD             23 (split)
            370 LOAD_CONST              24 ('_')
            372 CALL_METHOD              1
            374 LOAD_CONST               3 (0)
            376 BINARY_SUBSCR
            378 STORE_FAST              34 (sid)

468     >>  380 LOAD_DEREF               0 (lang)
            382 LOAD_CONST              25 ('he')
            384 COMPARE_OP               2 (==)
            386 POP_JUMP_IF_FALSE      196 (to 392)
            388 LOAD_CONST              26 (0.98)
            390 JUMP_FORWARD             1 (to 394)
        >>  392 LOAD_CONST              27 (0.02)
        >>  394 STORE_FAST              35 (name_x)

469         396 LOAD_DEREF               0 (lang)
            398 LOAD_CONST              25 ('he')
            400 COMPARE_OP               2 (==)
            402 POP_JUMP_IF_FALSE      204 (to 408)
            404 LOAD_CONST              28 ('right')
            406 JUMP_FORWARD             1 (to 410)
        >>  408 LOAD_CONST              29 ('left')
        >>  410 STORE_FAST              36 (name_ha)

470         412 LOAD_FAST                2 (subject_name)
            414 POP_JUMP_IF_FALSE      222 (to 444)
            416 LOAD_DEREF               0 (lang)
            418 LOAD_CONST              25 ('he')
            420 COMPARE_OP               2 (==)
            422 POP_JUMP_IF_FALSE      222 (to 444)
            424 LOAD_FAST               34 (sid)
            426 FORMAT_VALUE             0
            428 LOAD_CONST              30 (' ')
            430 LOAD_GLOBAL             18 (_t)
            432 LOAD_CONST              31 ('Name:')
            434 LOAD_DEREF               0 (lang)
            436 CALL_FUNCTION            2
            438 FORMAT_VALUE             0
            440 BUILD_STRING             3
            442 JUMP_FORWARD            37 (to 518)

471     >>  444 LOAD_FAST                2 (subject_name)
            446 POP_JUMP_IF_TRUE       238 (to 476)
            448 LOAD_DEREF               0 (lang)
            450 LOAD_CONST              25 ('he')
            452 COMPARE_OP               2 (==)
            454 POP_JUMP_IF_FALSE      238 (to 476)
            456 LOAD_FAST               34 (sid)
            458 FORMAT_VALUE             0
            460 LOAD_CONST              30 (' ')
            462 LOAD_GLOBAL             18 (_t)
            464 LOAD_CONST              32 ('ID:')
            466 LOAD_DEREF               0 (lang)
            468 CALL_FUNCTION            2
            470 FORMAT_VALUE             0
            472 BUILD_STRING             3
            474 JUMP_FORWARD            21 (to 518)

472     >>  476 LOAD_FAST                2 (subject_name)
            478 POP_JUMP_IF_FALSE      250 (to 500)
            480 LOAD_GLOBAL             18 (_t)
            482 LOAD_CONST              31 ('Name:')
            484 LOAD_DEREF               0 (lang)
            486 CALL_FUNCTION            2
            488 FORMAT_VALUE             0
            490 LOAD_CONST              30 (' ')
            492 LOAD_FAST               34 (sid)
            494 FORMAT_VALUE             0
            496 BUILD_STRING             3
            498 JUMP_FORWARD             9 (to 518)

473     >>  500 LOAD_GLOBAL             18 (_t)
            502 LOAD_CONST              32 ('ID:')
            504 LOAD_DEREF               0 (lang)
            506 CALL_FUNCTION            2
            508 FORMAT_VALUE             0
            510 LOAD_CONST              30 (' ')
            512 LOAD_FAST               34 (sid)
            514 FORMAT_VALUE             0
            516 BUILD_STRING             3

470     >>  518 STORE_FAST              37 (name_text)

475         520 LOAD_FAST               32 (ax_title)
            522 LOAD_ATTR               19 (text)
            524 LOAD_FAST               35 (name_x)
            526 LOAD_CONST              19 (0.5)
            528 LOAD_FAST               37 (name_text)

476         530 LOAD_FAST               32 (ax_title)
            532 LOAD_ATTR               20 (transAxes)

477         534 LOAD_CONST              33 (14)
            536 LOAD_CONST              21 ('bold')
            538 LOAD_GLOBAL             21 (TEXT_H)
            540 LOAD_CONST              22 ('center')
            542 LOAD_FAST               36 (name_ha)

475         544 LOAD_CONST              23 (('transform', 'fontsize', 'fontweight', 'color', 'va', 'ha'))
            546 CALL_FUNCTION_KW         9
            548 POP_TOP

479         550 LOAD_FAST               32 (ax_title)
            552 LOAD_ATTR               24 (plot)
            554 LOAD_CONST               3 (0)
            556 LOAD_CONST              34 (1)
            558 BUILD_LIST               2
            560 LOAD_CONST              35 (0.0)
            562 LOAD_CONST              35 (0.0)
            564 BUILD_LIST               2
            566 LOAD_GLOBAL             25 (ACCENT)
            568 LOAD_CONST              36 (2.5)

480         570 LOAD_FAST               32 (ax_title)
            572 LOAD_ATTR               20 (transAxes)

479         574 LOAD_CONST              37 (('color', 'lw', 'transform'))
            576 CALL_FUNCTION_KW         5
            578 POP_TOP

483         580 LOAD_FAST               22 (fig)
            582 LOAD_METHOD             11 (add_axes)
            584 BUILD_LIST               0
            586 LOAD_CONST              38 ((0.0, 0.885, 1.0, 0.025))
            588 LIST_EXTEND              1
            590 CALL_METHOD              1
            592 STORE_FAST              38 (ax_dem)

484         594 LOAD_FAST               38 (ax_dem)
            596 LOAD_METHOD             13 (axis)
            598 LOAD_CONST              12 ('off')
            600 CALL_METHOD              1
            602 POP_TOP

485         604 BUILD_LIST               0
            606 STORE_FAST              39 (parts)

486         608 LOAD_DEREF               0 (lang)
            610 LOAD_CONST              25 ('he')
            612 COMPARE_OP               2 (==)
            614 EXTENDED_ARG             1
            616 POP_JUMP_IF_FALSE      361 (to 722)

487         618 LOAD_FAST                4 (study_date)
            620 EXTENDED_ARG             1
            622 POP_JUMP_IF_FALSE      317 (to 634)
            624 LOAD_FAST               39 (parts)
            626 LOAD_METHOD             26 (append)
            628 LOAD_FAST                4 (study_date)
            630 CALL_METHOD              1
            632 POP_TOP

488     >>  634 LOAD_FAST                5 (subject_age)
            636 EXTENDED_ARG             1
            638 POP_JUMP_IF_FALSE      333 (to 666)
            640 LOAD_FAST               39 (parts)
            642 LOAD_METHOD             26 (append)
            644 LOAD_FAST                5 (subject_age)
            646 FORMAT_VALUE             0
            648 LOAD_CONST              30 (' ')
            650 LOAD_GLOBAL             18 (_t)
            652 LOAD_CONST              39 ('Age:')
            654 LOAD_DEREF               0 (lang)
            656 CALL_FUNCTION            2
            658 FORMAT_VALUE             0
            660 BUILD_STRING             3
            662 CALL_METHOD              1
            664 POP_TOP

489     >>  666 LOAD_FAST                6 (sex)
            668 EXTENDED_ARG             1
            670 POP_JUMP_IF_FALSE      360 (to 720)

490         672 LOAD_GLOBAL             22 (str)
            674 LOAD_FAST                6 (sex)
            676 CALL_FUNCTION            1
            678 LOAD_METHOD             27 (upper)
            680 CALL_METHOD              0
            682 LOAD_CONST              40 (('M', 'MALE'))
            684 CONTAINS_OP              0
            686 EXTENDED_ARG             1
            688 POP_JUMP_IF_FALSE      350 (to 700)
            690 LOAD_GLOBAL             18 (_t)
            692 LOAD_CONST              41 ('Male')
            694 LOAD_DEREF               0 (lang)
            696 CALL_FUNCTION            2
            698 JUMP_FORWARD             4 (to 708)
        >>  700 LOAD_GLOBAL             18 (_t)
            702 LOAD_CONST              42 ('Female')
            704 LOAD_DEREF               0 (lang)
            706 CALL_FUNCTION            2
        >>  708 STORE_FAST              40 (s_txt)

491         710 LOAD_FAST               39 (parts)
            712 LOAD_METHOD             26 (append)
            714 LOAD_FAST               40 (s_txt)
            716 CALL_METHOD              1
            718 POP_TOP
        >>  720 JUMP_FORWARD            51 (to 824)

493     >>  722 LOAD_FAST                4 (study_date)
            724 EXTENDED_ARG             1
            726 POP_JUMP_IF_FALSE      369 (to 738)
            728 LOAD_FAST               39 (parts)
            730 LOAD_METHOD             26 (append)
            732 LOAD_FAST                4 (study_date)
            734 CALL_METHOD              1
            736 POP_TOP

494     >>  738 LOAD_FAST                5 (subject_age)
            740 EXTENDED_ARG             1
            742 POP_JUMP_IF_FALSE      385 (to 770)
            744 LOAD_FAST               39 (parts)
            746 LOAD_METHOD             26 (append)
            748 LOAD_GLOBAL             18 (_t)
            750 LOAD_CONST              39 ('Age:')
            752 LOAD_DEREF               0 (lang)
            754 CALL_FUNCTION            2
            756 FORMAT_VALUE             0
            758 LOAD_CONST              30 (' ')
            760 LOAD_FAST                5 (subject_age)
            762 FORMAT_VALUE             0
            764 BUILD_STRING             3
            766 CALL_METHOD              1
            768 POP_TOP

495     >>  770 LOAD_FAST                6 (sex)
            772 EXTENDED_ARG             1
            774 POP_JUMP_IF_FALSE      412 (to 824)

496         776 LOAD_GLOBAL             22 (str)
            778 LOAD_FAST                6 (sex)
            780 CALL_FUNCTION            1
            782 LOAD_METHOD             27 (upper)
            784 CALL_METHOD              0
            786 LOAD_CONST              40 (('M', 'MALE'))
            788 CONTAINS_OP              0
            790 EXTENDED_ARG             1
            792 POP_JUMP_IF_FALSE      402 (to 804)
            794 LOAD_GLOBAL             18 (_t)
            796 LOAD_CONST              41 ('Male')
            798 LOAD_DEREF               0 (lang)
            800 CALL_FUNCTION            2
            802 JUMP_FORWARD             4 (to 812)
        >>  804 LOAD_GLOBAL             18 (_t)
            806 LOAD_CONST              42 ('Female')
            808 LOAD_DEREF               0 (lang)
            810 CALL_FUNCTION            2
        >>  812 STORE_FAST              40 (s_txt)

497         814 LOAD_FAST               39 (parts)
            816 LOAD_METHOD             26 (append)
            818 LOAD_FAST               40 (s_txt)
            820 CALL_METHOD              1
            822 POP_TOP

499     >>  824 LOAD_DEREF               0 (lang)
            826 LOAD_CONST              25 ('he')
            828 COMPARE_OP               2 (==)
            830 EXTENDED_ARG             1
            832 POP_JUMP_IF_FALSE      424 (to 848)

500         834 LOAD_FAST               39 (parts)
            836 LOAD_CONST               0 (None)
            838 LOAD_CONST               0 (None)
            840 LOAD_CONST              43 (-1)
            842 BUILD_SLICE              3
            844 BINARY_SUBSCR
            846 STORE_FAST              39 (parts)

502     >>  848 LOAD_FAST               38 (ax_dem)
            850 LOAD_ATTR               19 (text)
            852 LOAD_CONST              19 (0.5)
            854 LOAD_CONST              19 (0.5)
            856 LOAD_CONST              44 (' • ')
            858 LOAD_METHOD             28 (join)
            860 LOAD_FAST               39 (parts)
            862 CALL_METHOD              1

503         864 LOAD_FAST               38 (ax_dem)
            866 LOAD_ATTR               20 (transAxes)
            868 LOAD_CONST              45 (13)

504         870 LOAD_GLOBAL             29 (TEXT_M)
            872 LOAD_CONST              22 ('center')
            874 LOAD_CONST              22 ('center')

502         876 LOAD_CONST              46 (('transform', 'fontsize', 'color', 'va', 'ha'))
            878 CALL_FUNCTION_KW         8
            880 POP_TOP

509         882 LOAD_DEREF               0 (lang)
            884 LOAD_CONST              25 ('he')
            886 COMPARE_OP               2 (==)
            888 EXTENDED_ARG             1
            890 POP_JUMP_IF_FALSE      450 (to 900)
            892 LOAD_CONST              47 (1.0)
            894 LOAD_CONST              48 (1.45)
            896 BUILD_LIST               2
            898 JUMP_FORWARD             3 (to 906)
        >>  900 LOAD_CONST              48 (1.45)
            902 LOAD_CONST              47 (1.0)
            904 BUILD_LIST               2
        >>  906 STORE_FAST              41 (w_ratios)

510         908 LOAD_GLOBAL             30 (GridSpec)
            910 LOAD_CONST              49 (5)
            912 LOAD_CONST              50 (2)
            914 LOAD_FAST               22 (fig)

511         916 LOAD_CONST              51 (0.865)
            918 LOAD_CONST              52 (0.23)

512         920 LOAD_CONST              53 (0.04)
            922 LOAD_CONST              54 (0.97)

513         924 LOAD_CONST              55 (0.55)
            926 LOAD_CONST              56 (0.28)

514         928 BUILD_LIST               0
            930 LOAD_CONST              57 ((0.85, 1.35, 1.35, 1.15, 1.1))
            932 LIST_EXTEND              1

515         934 LOAD_FAST               41 (w_ratios)

510         936 LOAD_CONST              58 (('figure', 'top', 'bottom', 'left', 'right', 'hspace', 'wspace', 'height_ratios', 'width_ratios'))
            938 CALL_FUNCTION_KW        11
            940 STORE_FAST              42 (gs)

517         942 LOAD_DEREF               0 (lang)
            944 LOAD_CONST              25 ('he')
            946 COMPARE_OP               2 (==)
            948 EXTENDED_ARG             1
            950 POP_JUMP_IF_FALSE      478 (to 956)
            952 LOAD_CONST              34 (1)
            954 JUMP_FORWARD             1 (to 958)
        >>  956 LOAD_CONST               3 (0)
        >>  958 STORE_FAST              43 (c_left)

518         960 LOAD_DEREF               0 (lang)
            962 LOAD_CONST              25 ('he')
            964 COMPARE_OP               2 (==)
            966 EXTENDED_ARG             1
            968 POP_JUMP_IF_FALSE      487 (to 974)
            970 LOAD_CONST               3 (0)
            972 JUMP_FORWARD             1 (to 976)
        >>  974 LOAD_CONST              34 (1)
        >>  976 STORE_FAST              44 (c_right)

521         978 LOAD_FAST               22 (fig)
            980 LOAD_METHOD             31 (add_subplot)
            982 LOAD_FAST               42 (gs)
            984 LOAD_CONST               3 (0)
            986 LOAD_CONST              50 (2)
            988 BUILD_SLICE              2
            990 LOAD_FAST               43 (c_left)
            992 BUILD_TUPLE              2
            994 BINARY_SUBSCR
            996 CALL_METHOD              1
            998 STORE_FAST              45 (ax1)

522        1000 LOAD_GLOBAL             32 (_panel)
           1002 LOAD_FAST               45 (ax1)
           1004 CALL_FUNCTION            1
           1006 POP_TOP
           1008 LOAD_FAST               45 (ax1)
           1010 LOAD_METHOD             13 (axis)
           1012 LOAD_CONST              12 ('off')
           1014 CALL_METHOD              1
           1016 POP_TOP

523        1018 LOAD_GLOBAL             33 (_section_title)
           1020 LOAD_FAST               45 (ax1)
           1022 LOAD_CONST              59 ('Sleep Architecture')
           1024 LOAD_CONST              34 (1)
           1026 LOAD_CONST              60 (1.05)
           1028 LOAD_DEREF               0 (lang)
           1030 LOAD_CONST              61 (('y_frac', 'lang'))
           1032 CALL_FUNCTION_KW         5
           1034 POP_TOP

525        1036 LOAD_DEREF               0 (lang)
           1038 LOAD_CONST              25 ('he')
           1040 COMPARE_OP               2 (==)
           1042 EXTENDED_ARG             2
           1044 POP_JUMP_IF_FALSE      525 (to 1050)
           1046 LOAD_CONST              62 (-0.06)
           1048 JUMP_FORWARD             1 (to 1052)
        >> 1050 LOAD_CONST              27 (0.02)
        >> 1052 STORE_FAST              46 (ax1_x)

526        1054 LOAD_FAST               45 (ax1)
           1056 LOAD_METHOD             34 (inset_axes)
           1058 LOAD_FAST               46 (ax1_x)
           1060 LOAD_CONST              63 (0.25)
           1062 LOAD_CONST              64 (0.71)
           1064 LOAD_CONST              65 (0.65)
           1066 BUILD_LIST               4
           1068 CALL_METHOD              1
           1070 STORE_FAST              47 (axi)

527        1072 LOAD_GLOBAL             35 (_hypno)
           1074 LOAD_FAST               47 (axi)
           1076 LOAD_FAST                0 (hypno_1hz_int)
           1078 LOAD_DEREF               0 (lang)
           1080 LOAD_CONST              66 (('lang',))
           1082 CALL_FUNCTION_KW         3
           1084 POP_TOP

529        1086 LOAD_FAST               45 (ax1)
           1088 LOAD_ATTR               24 (plot)
           1090 LOAD_CONST              67 (0.05)
           1092 LOAD_CONST              68 (0.95)
           1094 BUILD_LIST               2
           1096 LOAD_CONST              69 (0.2)
           1098 LOAD_CONST              69 (0.2)
           1100 BUILD_LIST               2
           1102 LOAD_GLOBAL             36 (BORDER)
           1104 LOAD_CONST              70 (0.6)
           1106 LOAD_FAST               45 (ax1)
           1108 LOAD_ATTR               20 (transAxes)
           1110 LOAD_CONST              37 (('color', 'lw', 'transform'))
           1112 CALL_FUNCTION_KW         5
           1114 POP_TOP

531        1116 LOAD_CONST              71 (0.85)
           1118 STORE_FAST              48 (sum_y)

532        1120 LOAD_GLOBAL             37 (_fmt)
           1122 LOAD_FAST               21 (st)
           1124 LOAD_CONST              72 ('SOL')
           1126 BINARY_SUBSCR
           1128 CALL_FUNCTION            1
           1130 LOAD_CONST              73 ('Sleep Onset')
           1132 BUILD_TUPLE              2
           1134 LOAD_GLOBAL             37 (_fmt)
           1136 LOAD_FAST               21 (st)
           1138 LOAD_CONST              74 ('TST')
           1140 BINARY_SUBSCR
           1142 CALL_FUNCTION            1
           1144 LOAD_CONST              75 ('Total Sleep')
           1146 BUILD_TUPLE              2
           1148 LOAD_GLOBAL             37 (_fmt)
           1150 LOAD_FAST               21 (st)
           1152 LOAD_CONST              76 ('WASO')
           1154 BINARY_SUBSCR
           1156 CALL_FUNCTION            1
           1158 LOAD_CONST              77 ('WASO:')
           1160 BUILD_TUPLE              2
           1162 BUILD_LIST               3
           1164 STORE_FAST              49 (kpis)

533        1166 LOAD_DEREF               0 (lang)
           1168 LOAD_CONST              25 ('he')
           1170 COMPARE_OP               2 (==)
           1172 EXTENDED_ARG             2
           1174 POP_JUMP_IF_FALSE      595 (to 1190)
           1176 LOAD_FAST               49 (kpis)
           1178 LOAD_CONST               0 (None)
           1180 LOAD_CONST               0 (None)
           1182 LOAD_CONST              43 (-1)
           1184 BUILD_SLICE              3
           1186 BINARY_SUBSCR
           1188 STORE_FAST              49 (kpis)

535     >> 1190 LOAD_GLOBAL             38 (enumerate)
           1192 LOAD_FAST               49 (kpis)
           1194 CALL_FUNCTION            1
           1196 GET_ITER
        >> 1198 FOR_ITER                67 (to 1334)
           1200 UNPACK_SEQUENCE          2
           1202 STORE_FAST              50 (i)
           1204 UNPACK_SEQUENCE          2
           1206 STORE_FAST              51 (v)
           1208 STORE_FAST              52 (k)

536        1210 LOAD_FAST               48 (sum_y)
           1212 LOAD_FAST               50 (i)
           1214 LOAD_CONST              78 (0.3)
           1216 BINARY_MULTIPLY
           1218 BINARY_SUBTRACT
           1220 STORE_FAST              53 (y_center)

537        1222 LOAD_DEREF               0 (lang)
           1224 LOAD_CONST              25 ('he')
           1226 COMPARE_OP               2 (==)
           1228 EXTENDED_ARG             2
           1230 POP_JUMP_IF_FALSE      618 (to 1236)
           1232 LOAD_CONST              79 (0.86)
           1234 JUMP_FORWARD             1 (to 1238)
        >> 1236 LOAD_CONST              80 (0.92)
        >> 1238 STORE_FAST              54 (actual_cx)

538        1240 LOAD_FAST               45 (ax1)
           1242 LOAD_ATTR               19 (text)
           1244 LOAD_FAST               54 (actual_cx)
           1246 LOAD_FAST               53 (y_center)
           1248 LOAD_FAST               51 (v)
           1250 LOAD_FAST               45 (ax1)
           1252 LOAD_ATTR               20 (transAxes)

539        1254 LOAD_CONST              33 (14)
           1256 LOAD_CONST              21 ('bold')
           1258 LOAD_GLOBAL             21 (TEXT_H)
           1260 LOAD_CONST              22 ('center')
           1262 LOAD_CONST              10 (10)

538        1264 LOAD_CONST              81 (('transform', 'fontsize', 'fontweight', 'color', 'ha', 'zorder'))
           1266 CALL_FUNCTION_KW         9
           1268 POP_TOP

540        1270 LOAD_DEREF               0 (lang)
           1272 LOAD_CONST              25 ('he')
           1274 COMPARE_OP               2 (==)
           1276 EXTENDED_ARG             2
           1278 POP_JUMP_IF_FALSE      642 (to 1284)
           1280 LOAD_CONST              82 (7.5)
           1282 JUMP_FORWARD             1 (to 1286)
        >> 1284 LOAD_CONST              83 (9)
        >> 1286 STORE_FAST              55 (lbl_fs)

541        1288 LOAD_FAST               45 (ax1)
           1290 LOAD_ATTR               19 (text)
           1292 LOAD_FAST               54 (actual_cx)
           1294 LOAD_FAST               53 (y_center)
           1296 LOAD_CONST              84 (0.03)
           1298 BINARY_SUBTRACT
           1300 LOAD_GLOBAL             18 (_t)
           1302 LOAD_FAST               52 (k)
           1304 LOAD_DEREF               0 (lang)
           1306 CALL_FUNCTION            2
           1308 LOAD_FAST               45 (ax1)
           1310 LOAD_ATTR               20 (transAxes)

542        1312 LOAD_FAST               55 (lbl_fs)
           1314 LOAD_CONST              21 ('bold')
           1316 LOAD_GLOBAL             39 (TEXT_L)
           1318 LOAD_CONST              22 ('center')
           1320 LOAD_CONST              85 ('top')
           1322 LOAD_CONST              10 (10)

541        1324 LOAD_CONST              86 (('transform', 'fontsize', 'fontweight', 'color', 'ha', 'va', 'zorder'))
           1326 CALL_FUNCTION_KW        10
           1328 POP_TOP
           1330 EXTENDED_ARG             2
           1332 JUMP_ABSOLUTE          599 (to 1198)

545     >> 1334 LOAD_FAST               22 (fig)
           1336 LOAD_METHOD             31 (add_subplot)
           1338 LOAD_FAST               42 (gs)
           1340 LOAD_CONST               3 (0)
           1342 LOAD_CONST              50 (2)
           1344 BUILD_SLICE              2
           1346 LOAD_FAST               44 (c_right)
           1348 BUILD_TUPLE              2
           1350 BINARY_SUBSCR
           1352 CALL_METHOD              1
           1354 STORE_FAST              56 (ax2)

546        1356 LOAD_GLOBAL             32 (_panel)
           1358 LOAD_FAST               56 (ax2)
           1360 CALL_FUNCTION            1
           1362 POP_TOP
           1364 LOAD_FAST               56 (ax2)
           1366 LOAD_METHOD             13 (axis)
           1368 LOAD_CONST              12 ('off')
           1370 CALL_METHOD              1
           1372 POP_TOP

547        1374 LOAD_GLOBAL             33 (_section_title)
           1376 LOAD_FAST               56 (ax2)
           1378 LOAD_CONST              87 ('Stage Distribution')
           1380 LOAD_CONST              50 (2)
           1382 LOAD_CONST              60 (1.05)
           1384 LOAD_DEREF               0 (lang)
           1386 LOAD_CONST              61 (('y_frac', 'lang'))
           1388 CALL_FUNCTION_KW         5
           1390 POP_TOP

549        1392 LOAD_FAST               56 (ax2)
           1394 LOAD_METHOD             34 (inset_axes)
           1396 BUILD_LIST               0
           1398 LOAD_CONST              88 ((0.04, 0.2, 0.92, 0.76))
           1400 LIST_EXTEND              1
           1402 CALL_METHOD              1
           1404 STORE_FAST              57 (ax2p)

550        1406 LOAD_GLOBAL             40 (_donut)
           1408 LOAD_FAST               57 (ax2p)
           1410 LOAD_FAST               21 (st)
           1412 LOAD_DEREF               0 (lang)
           1414 LOAD_CONST              66 (('lang',))
           1416 CALL_FUNCTION_KW         3
           1418 POP_TOP

552        1420 LOAD_GLOBAL             41 (_qcol)
           1422 LOAD_FAST               21 (st)
           1424 LOAD_CONST              89 ('SE')
           1426 BINARY_SUBSCR
           1428 CALL_FUNCTION            1
           1430 STORE_FAST              58 (se_col)

553        1432 LOAD_FAST               57 (ax2p)
           1434 LOAD_ATTR               19 (text)
           1436 LOAD_CONST              19 (0.5)
           1438 LOAD_CONST              90 (0.52)
           1440 LOAD_FAST               21 (st)
           1442 LOAD_CONST              89 ('SE')
           1444 BINARY_SUBSCR
           1446 LOAD_CONST              91 ('.0f')
           1448 FORMAT_VALUE             4 (with format)
           1450 LOAD_CONST              92 ('%')
           1452 BUILD_STRING             2

554        1454 LOAD_CONST              22 ('center')
           1456 LOAD_CONST              22 ('center')
           1458 LOAD_CONST              93 (20)

555        1460 LOAD_CONST              21 ('bold')
           1462 LOAD_FAST               58 (se_col)
           1464 LOAD_FAST               57 (ax2p)
           1466 LOAD_ATTR               20 (transAxes)

553        1468 LOAD_CONST              94 (('ha', 'va', 'fontsize', 'fontweight', 'color', 'transform'))
           1470 CALL_FUNCTION_KW         9
           1472 POP_TOP

556        1474 LOAD_FAST               57 (ax2p)
           1476 LOAD_ATTR               19 (text)
           1478 LOAD_CONST              19 (0.5)
           1480 LOAD_CONST              95 (0.38)
           1482 LOAD_GLOBAL             18 (_t)
           1484 LOAD_CONST              96 ('Efficiency')
           1486 LOAD_DEREF               0 (lang)
           1488 CALL_FUNCTION            2

557        1490 LOAD_CONST              22 ('center')
           1492 LOAD_CONST              22 ('center')
           1494 LOAD_CONST              82 (7.5)
           1496 LOAD_CONST              21 ('bold')

558        1498 LOAD_GLOBAL             39 (TEXT_L)
           1500 LOAD_FAST               57 (ax2p)
           1502 LOAD_ATTR               20 (transAxes)

556        1504 LOAD_CONST              94 (('ha', 'va', 'fontsize', 'fontweight', 'color', 'transform'))
           1506 CALL_FUNCTION_KW         9
           1508 POP_TOP

560        1510 BUILD_LIST               0
           1512 LOAD_CONST              97 (('N1', 'N2', 'N3', 'REM', 'Wake'))
           1514 LIST_EXTEND              1
           1516 STORE_FAST              59 (lbls)

561        1518 LOAD_DEREF               0 (lang)
           1520 LOAD_CONST              25 ('he')
           1522 COMPARE_OP               2 (==)
           1524 EXTENDED_ARG             3
           1526 POP_JUMP_IF_FALSE      771 (to 1542)
           1528 LOAD_FAST               59 (lbls)
           1530 LOAD_CONST               0 (None)
           1532 LOAD_CONST               0 (None)
           1534 LOAD_CONST              43 (-1)
           1536 BUILD_SLICE              3
           1538 BINARY_SUBSCR
           1540 STORE_FAST              59 (lbls)

563     >> 1542 LOAD_CONST              98 ((0.14, 0.04))
           1544 UNPACK_SEQUENCE          2
           1546 STORE_FAST              60 (chip_w)
           1548 STORE_FAST              61 (gap)

564        1550 LOAD_GLOBAL             42 (len)
           1552 LOAD_FAST               59 (lbls)
           1554 CALL_FUNCTION            1
           1556 LOAD_FAST               60 (chip_w)
           1558 BINARY_MULTIPLY
           1560 LOAD_GLOBAL             42 (len)
           1562 LOAD_FAST               59 (lbls)
           1564 CALL_FUNCTION            1
           1566 LOAD_CONST              34 (1)
           1568 BINARY_SUBTRACT
           1570 LOAD_FAST               61 (gap)
           1572 BINARY_MULTIPLY
           1574 BINARY_ADD
           1576 STORE_FAST              62 (total_w)

565        1578 LOAD_CONST              47 (1.0)
           1580 LOAD_FAST               62 (total_w)
           1582 BINARY_SUBTRACT
           1584 LOAD_CONST              50 (2)
           1586 BINARY_TRUE_DIVIDE
           1588 STORE_FAST              63 (x0)

566        1590 LOAD_GLOBAL             38 (enumerate)
           1592 LOAD_FAST               59 (lbls)
           1594 CALL_FUNCTION            1
           1596 GET_ITER
        >> 1598 FOR_ITER                69 (to 1738)
           1600 UNPACK_SEQUENCE          2
           1602 STORE_FAST              50 (i)
           1604 STORE_FAST              64 (lbl)

567        1606 LOAD_FAST               63 (x0)
           1608 LOAD_FAST               50 (i)
           1610 LOAD_FAST               60 (chip_w)
           1612 LOAD_FAST               61 (gap)
           1614 BINARY_ADD
           1616 BINARY_MULTIPLY
           1618 BINARY_ADD
           1620 STORE_FAST              65 (cx)

568        1622 LOAD_GLOBAL             43 (_x)
           1624 LOAD_FAST               65 (cx)
           1626 LOAD_DEREF               0 (lang)
           1628 CALL_FUNCTION            2
           1630 STORE_FAST              66 (box_x)

569        1632 LOAD_DEREF               0 (lang)
           1634 LOAD_CONST              25 ('he')
           1636 COMPARE_OP               2 (==)
           1638 EXTENDED_ARG             3
           1640 POP_JUMP_IF_FALSE      825 (to 1650)
           1642 LOAD_FAST               66 (box_x)
           1644 LOAD_FAST               60 (chip_w)
           1646 INPLACE_SUBTRACT
           1648 STORE_FAST              66 (box_x)

571     >> 1650 LOAD_FAST               56 (ax2)
           1652 LOAD_METHOD             44 (add_patch)
           1654 LOAD_GLOBAL             45 (FancyBboxPatch)
           1656 LOAD_FAST               66 (box_x)
           1658 LOAD_CONST              99 (0.12)
           1660 BUILD_TUPLE              2
           1662 LOAD_FAST               60 (chip_w)
           1664 LOAD_CONST             100 (0.055)

572        1666 LOAD_CONST             101 ('round,pad=0,rounding_size=0.01')

573        1668 LOAD_GLOBAL             46 (STAGE_COLORS)
           1670 LOAD_FAST               64 (lbl)
           1672 BINARY_SUBSCR
           1674 LOAD_CONST             102 ('none')

574        1676 LOAD_CONST             103 (0.75)
           1678 LOAD_FAST               56 (ax2)
           1680 LOAD_ATTR               20 (transAxes)

571        1682 LOAD_CONST             104 (('boxstyle', 'facecolor', 'edgecolor', 'alpha', 'transform'))
           1684 CALL_FUNCTION_KW         8
           1686 CALL_METHOD              1
           1688 POP_TOP

576        1690 LOAD_FAST               56 (ax2)
           1692 LOAD_ATTR               19 (text)
           1694 LOAD_FAST               66 (box_x)
           1696 LOAD_FAST               60 (chip_w)
           1698 LOAD_CONST              50 (2)
           1700 BINARY_TRUE_DIVIDE
           1702 BINARY_ADD
           1704 LOAD_CONST             105 (0.148)
           1706 LOAD_GLOBAL             18 (_t)
           1708 LOAD_FAST               64 (lbl)
           1710 LOAD_DEREF               0 (lang)
           1712 CALL_FUNCTION            2

577        1714 LOAD_FAST               56 (ax2)
           1716 LOAD_ATTR               20 (transAxes)
           1718 LOAD_CONST             106 (9.5)

578        1720 LOAD_CONST             107 ('white')
           1722 LOAD_CONST              22 ('center')
           1724 LOAD_CONST              22 ('center')
           1726 LOAD_CONST              21 ('bold')

576        1728 LOAD_CONST             108 (('transform', 'fontsize', 'color', 'ha', 'va', 'fontweight'))
           1730 CALL_FUNCTION_KW         9
           1732 POP_TOP
           1734 EXTENDED_ARG             3
           1736 JUMP_ABSOLUTE          799 (to 1598)

581     >> 1738 LOAD_FAST               22 (fig)
           1740 LOAD_METHOD             31 (add_subplot)
           1742 LOAD_FAST               42 (gs)
           1744 LOAD_CONST              50 (2)
           1746 LOAD_FAST               43 (c_left)
           1748 BUILD_TUPLE              2
           1750 BINARY_SUBSCR
           1752 CALL_METHOD              1
           1754 STORE_FAST              67 (ax3)

582        1756 LOAD_GLOBAL             32 (_panel)
           1758 LOAD_FAST               67 (ax3)
           1760 CALL_FUNCTION            1
           1762 POP_TOP
           1764 LOAD_FAST               67 (ax3)
           1766 LOAD_METHOD             13 (axis)
           1768 LOAD_CONST              12 ('off')
           1770 CALL_METHOD              1
           1772 POP_TOP

583        1774 LOAD_GLOBAL             33 (_section_title)
           1776 LOAD_FAST               67 (ax3)
           1778 LOAD_CONST             109 ('Respiratory Disturbance Index (pAHI)')
           1780 LOAD_CONST             110 (3)
           1782 LOAD_CONST             111 (1.55)
           1784 LOAD_DEREF               0 (lang)
           1786 LOAD_CONST              61 (('y_frac', 'lang'))
           1788 CALL_FUNCTION_KW         5
           1790 POP_TOP

585        1792 LOAD_FAST               20 (rdi_v)
           1794 LOAD_CONST               0 (None)
           1796 IS_OP                    1
           1798 EXTENDED_ARG             3
           1800 POP_JUMP_IF_FALSE      916 (to 1832)

586        1802 LOAD_FAST               67 (ax3)
           1804 LOAD_METHOD             34 (inset_axes)
           1806 BUILD_LIST               0
           1808 LOAD_CONST             112 ((-0.15, -0.45, 1.3, 1.8))
           1810 LIST_EXTEND              1
           1812 CALL_METHOD              1
           1814 STORE_FAST              68 (ax3g)

587        1816 LOAD_GLOBAL             47 (_gauge)
           1818 LOAD_FAST               68 (ax3g)
           1820 LOAD_FAST               20 (rdi_v)
           1822 LOAD_DEREF               0 (lang)
           1824 LOAD_CONST              66 (('lang',))
           1826 CALL_FUNCTION_KW         3
           1828 POP_TOP
           1830 JUMP_FORWARD            18 (to 1868)

589     >> 1832 LOAD_FAST               67 (ax3)
           1834 LOAD_ATTR               19 (text)
           1836 LOAD_CONST              19 (0.5)
           1838 LOAD_CONST             113 (0.48)
           1840 LOAD_GLOBAL             18 (_t)
           1842 LOAD_CONST             114 ('Not measured')
           1844 LOAD_DEREF               0 (lang)
           1846 CALL_FUNCTION            2

590        1848 LOAD_FAST               67 (ax3)
           1850 LOAD_ATTR               20 (transAxes)
           1852 LOAD_CONST              22 ('center')

591        1854 LOAD_CONST             115 (11)
           1856 LOAD_GLOBAL             39 (TEXT_L)
           1858 LOAD_CONST             116 ('italic')
           1860 LOAD_CONST              22 ('center')

589        1862 LOAD_CONST             117 (('transform', 'ha', 'fontsize', 'color', 'style', 'va'))
           1864 CALL_FUNCTION_KW         9
           1866 POP_TOP

594     >> 1868 LOAD_FAST               22 (fig)
           1870 LOAD_METHOD             31 (add_subplot)
           1872 LOAD_FAST               42 (gs)
           1874 LOAD_CONST              50 (2)
           1876 LOAD_FAST               44 (c_right)
           1878 BUILD_TUPLE              2
           1880 BINARY_SUBSCR
           1882 CALL_METHOD              1
           1884 STORE_FAST              69 (ax4)

595        1886 LOAD_GLOBAL             32 (_panel)
           1888 LOAD_FAST               69 (ax4)
           1890 CALL_FUNCTION            1
           1892 POP_TOP
           1894 LOAD_FAST               69 (ax4)
           1896 LOAD_METHOD             13 (axis)
           1898 LOAD_CONST              12 ('off')
           1900 CALL_METHOD              1
           1902 POP_TOP

596        1904 LOAD_GLOBAL             33 (_section_title)
           1906 LOAD_FAST               69 (ax4)
           1908 LOAD_CONST             118 ('Additional Metrics')
           1910 LOAD_CONST             119 (4)
           1912 LOAD_CONST             111 (1.55)
           1914 LOAD_DEREF               0 (lang)
           1916 LOAD_CONST              61 (('y_frac', 'lang'))
           1918 CALL_FUNCTION_KW         5
           1920 POP_TOP

598        1922 BUILD_LIST               0
           1924 STORE_FAST              70 (rows)

599        1926 LOAD_FAST                7 (spo2_stats)
           1928 EXTENDED_ARG             4
           1930 POP_JUMP_IF_FALSE     1044 (to 2088)

600        1932 LOAD_FAST                7 (spo2_stats)
           1934 LOAD_METHOD             48 (get)
           1936 LOAD_CONST             120 ('avg')
           1938 LOAD_CONST               3 (0)
           1940 CALL_METHOD              2
           1942 STORE_FAST              71 (avg_val)

601        1944 LOAD_FAST                7 (spo2_stats)
           1946 LOAD_METHOD             48 (get)
           1948 LOAD_CONST             121 ('min')
           1950 LOAD_CONST               3 (0)
           1952 CALL_METHOD              2
           1954 STORE_FAST              72 (min_val)

602        1956 LOAD_FAST                7 (spo2_stats)
           1958 LOAD_METHOD             48 (get)
           1960 LOAD_CONST             122 ('t_under90')
           1962 LOAD_CONST               3 (0)
           1964 CALL_METHOD              2
           1966 STORE_FAST              73 (t90_val)

604        1968 LOAD_DEREF               0 (lang)
           1970 LOAD_CONST              25 ('he')
           1972 COMPARE_OP               2 (==)
           1974 EXTENDED_ARG             3
           1976 POP_JUMP_IF_FALSE     1019 (to 2038)

605        1978 LOAD_FAST               70 (rows)

606        1980 LOAD_CONST             123 ('SpO2 Average')
           1982 LOAD_FAST               71 (avg_val)
           1984 LOAD_CONST             124 ('.1f')
           1986 FORMAT_VALUE             4 (with format)
           1988 LOAD_CONST             125 (' %')
           1990 BUILD_STRING             2
           1992 BUILD_TUPLE              2

607        1994 LOAD_CONST             126 ('SpO2 Minimum')
           1996 LOAD_FAST               72 (min_val)
           1998 LOAD_CONST             124 ('.1f')
           2000 FORMAT_VALUE             4 (with format)
           2002 LOAD_CONST             125 (' %')
           2004 BUILD_STRING             2
           2006 BUILD_TUPLE              2

608        2008 LOAD_CONST             127 ('Time < 90%')
           2010 LOAD_GLOBAL             49 (get_display)
           2012 LOAD_CONST             128 ('דקות')
           2014 CALL_FUNCTION            1
           2016 FORMAT_VALUE             0
           2018 LOAD_CONST              30 (' ')
           2020 LOAD_FAST               73 (t90_val)
           2022 LOAD_CONST             124 ('.1f')
           2024 FORMAT_VALUE             4 (with format)
           2026 BUILD_STRING             3
           2028 BUILD_TUPLE              2

605        2030 BUILD_LIST               3
           2032 INPLACE_ADD
           2034 STORE_FAST              70 (rows)
           2036 JUMP_FORWARD            25 (to 2088)

611     >> 2038 LOAD_FAST               70 (rows)

612        2040 LOAD_CONST             123 ('SpO2 Average')
           2042 LOAD_FAST               71 (avg_val)
           2044 LOAD_CONST             124 ('.1f')
           2046 FORMAT_VALUE             4 (with format)
           2048 LOAD_CONST             125 (' %')
           2050 BUILD_STRING             2
           2052 BUILD_TUPLE              2

613        2054 LOAD_CONST             126 ('SpO2 Minimum')
           2056 LOAD_FAST               72 (min_val)
           2058 LOAD_CONST             124 ('.1f')
           2060 FORMAT_VALUE             4 (with format)
           2062 LOAD_CONST             125 (' %')
           2064 BUILD_STRING             2
           2066 BUILD_TUPLE              2

614        2068 LOAD_CONST             127 ('Time < 90%')
           2070 LOAD_FAST               73 (t90_val)
           2072 LOAD_CONST             124 ('.1f')
           2074 FORMAT_VALUE             4 (with format)
           2076 LOAD_CONST             129 (' min')
           2078 BUILD_STRING             2
           2080 BUILD_TUPLE              2

611        2082 BUILD_LIST               3
           2084 INPLACE_ADD
           2086 STORE_FAST              70 (rows)

616     >> 2088 LOAD_FAST                8 (plm_metrics)
           2090 EXTENDED_ARG             4
           2092 POP_JUMP_IF_FALSE     1074 (to 2148)

617        2094 LOAD_FAST                8 (plm_metrics)
           2096 LOAD_METHOD             48 (get)
           2098 LOAD_CONST             130 ('PLMI')
           2100 CALL_METHOD              1
           2102 EXTENDED_ARG             4
           2104 JUMP_IF_TRUE_OR_POP   1057 (to 2114)
           2106 LOAD_FAST                8 (plm_metrics)
           2108 LOAD_METHOD             48 (get)
           2110 LOAD_CONST             131 ('plmi')
           2112 CALL_METHOD              1
        >> 2114 STORE_FAST              74 (plmi)

618        2116 LOAD_FAST               74 (plmi)
           2118 LOAD_CONST               0 (None)
           2120 IS_OP                    1
           2122 EXTENDED_ARG             4
           2124 POP_JUMP_IF_FALSE     1074 (to 2148)

619        2126 LOAD_FAST               70 (rows)
           2128 LOAD_METHOD             26 (append)
           2130 LOAD_CONST             132 ('Limb Movements (PLMI)')
           2132 LOAD_FAST               74 (plmi)
           2134 LOAD_CONST             124 ('.1f')
           2136 FORMAT_VALUE             4 (with format)
           2138 LOAD_CONST             133 (' / hr')
           2140 BUILD_STRING             2
           2142 BUILD_TUPLE              2
           2144 CALL_METHOD              1
           2146 POP_TOP

621     >> 2148 LOAD_FAST               70 (rows)
           2150 EXTENDED_ARG             4
           2152 POP_JUMP_IF_TRUE      1096 (to 2192)

622        2154 LOAD_FAST               69 (ax4)
           2156 LOAD_ATTR               19 (text)
           2158 LOAD_CONST              19 (0.5)
           2160 LOAD_CONST              19 (0.5)
           2162 LOAD_GLOBAL             18 (_t)
           2164 LOAD_CONST             134 ('No additional data')
           2166 LOAD_DEREF               0 (lang)
           2168 CALL_FUNCTION            2

623        2170 LOAD_FAST               69 (ax4)
           2172 LOAD_ATTR               20 (transAxes)
           2174 LOAD_CONST              22 ('center')

624        2176 LOAD_CONST              10 (10)
           2178 LOAD_GLOBAL             39 (TEXT_L)
           2180 LOAD_CONST             116 ('italic')
           2182 LOAD_CONST              22 ('center')

622        2184 LOAD_CONST             117 (('transform', 'ha', 'fontsize', 'color', 'style', 'va'))
           2186 CALL_FUNCTION_KW         9
           2188 POP_TOP
           2190 JUMP_FORWARD           142 (to 2476)

626     >> 2192 LOAD_CONST              56 (0.28)
           2194 STORE_FAST              75 (step)

627        2196 LOAD_GLOBAL             38 (enumerate)
           2198 LOAD_FAST               70 (rows)
           2200 CALL_FUNCTION            1
           2202 GET_ITER
        >> 2204 FOR_ITER               135 (to 2476)
           2206 UNPACK_SEQUENCE          2
           2208 STORE_FAST              50 (i)
           2210 UNPACK_SEQUENCE          2
           2212 STORE_FAST              52 (k)
           2214 STORE_FAST              51 (v)

628        2216 LOAD_CONST              47 (1.0)
           2218 LOAD_FAST               50 (i)
           2220 LOAD_FAST               75 (step)
           2222 BINARY_MULTIPLY
           2224 BINARY_SUBTRACT
           2226 STORE_FAST              76 (y)

629        2228 LOAD_FAST               50 (i)
           2230 LOAD_CONST               3 (0)
           2232 COMPARE_OP               4 (>)
           2234 EXTENDED_ARG             4
           2236 POP_JUMP_IF_FALSE     1142 (to 2284)

630        2238 LOAD_FAST               69 (ax4)
           2240 LOAD_ATTR               24 (plot)
           2242 LOAD_CONST              53 (0.04)
           2244 LOAD_CONST             135 (0.96)
           2246 BUILD_LIST               2
           2248 LOAD_FAST               76 (y)
           2250 LOAD_FAST               75 (step)
           2252 LOAD_CONST              19 (0.5)
           2254 BINARY_MULTIPLY
           2256 BINARY_ADD
           2258 LOAD_FAST               76 (y)
           2260 LOAD_FAST               75 (step)
           2262 LOAD_CONST              19 (0.5)
           2264 BINARY_MULTIPLY
           2266 BINARY_ADD
           2268 BUILD_LIST               2

631        2270 LOAD_GLOBAL             36 (BORDER)
           2272 LOAD_CONST              19 (0.5)
           2274 LOAD_FAST               69 (ax4)
           2276 LOAD_ATTR               20 (transAxes)

630        2278 LOAD_CONST              37 (('color', 'lw', 'transform'))
           2280 CALL_FUNCTION_KW         5
           2282 POP_TOP

633     >> 2284 LOAD_GLOBAL             43 (_x)
           2286 LOAD_CONST              27 (0.02)
           2288 LOAD_DEREF               0 (lang)
           2290 CALL_FUNCTION            2
           2292 STORE_FAST              77 (k_x)

634        2294 LOAD_GLOBAL             43 (_x)
           2296 LOAD_CONST              26 (0.98)
           2298 LOAD_DEREF               0 (lang)
           2300 CALL_FUNCTION            2
           2302 STORE_FAST              78 (v_x)

635        2304 LOAD_GLOBAL             18 (_t)
           2306 LOAD_FAST               52 (k)
           2308 LOAD_DEREF               0 (lang)
           2310 CALL_FUNCTION            2
           2312 STORE_FAST              79 (lbl_text)

636        2314 LOAD_GLOBAL             42 (len)
           2316 LOAD_FAST               79 (lbl_text)
           2318 CALL_FUNCTION            1
           2320 LOAD_CONST             136 (16)
           2322 COMPARE_OP               4 (>)
           2324 EXTENDED_ARG             4
           2326 POP_JUMP_IF_FALSE     1166 (to 2332)
           2328 LOAD_CONST             137 (10.5)
           2330 JUMP_FORWARD             1 (to 2334)
        >> 2332 LOAD_CONST             138 (12)
        >> 2334 STORE_FAST              80 (fs_k)

638        2336 LOAD_FAST               69 (ax4)
           2338 LOAD_ATTR               19 (text)
           2340 LOAD_FAST               77 (k_x)
           2342 LOAD_FAST               76 (y)
           2344 LOAD_FAST               79 (lbl_text)
           2346 LOAD_FAST               69 (ax4)
           2348 LOAD_ATTR               20 (transAxes)

639        2350 LOAD_FAST               80 (fs_k)
           2352 LOAD_GLOBAL             29 (TEXT_M)
           2354 LOAD_CONST              22 ('center')
           2356 LOAD_GLOBAL             50 (_ha)
           2358 LOAD_CONST              29 ('left')
           2360 LOAD_DEREF               0 (lang)
           2362 CALL_FUNCTION            2

638        2364 LOAD_CONST              46 (('transform', 'fontsize', 'color', 'va', 'ha'))
           2366 CALL_FUNCTION_KW         8
           2368 POP_TOP

641        2370 LOAD_FAST               51 (v)
           2372 STORE_FAST              81 (val_txt)

642        2374 LOAD_DEREF               0 (lang)
           2376 LOAD_CONST              25 ('he')
           2378 COMPARE_OP               2 (==)
           2380 EXTENDED_ARG             4
           2382 POP_JUMP_IF_FALSE     1207 (to 2414)
           2384 LOAD_CONST             139 ('hr')
           2386 LOAD_FAST               51 (v)
           2388 CONTAINS_OP              0
           2390 EXTENDED_ARG             4
           2392 POP_JUMP_IF_FALSE     1207 (to 2414)

643        2394 LOAD_FAST               81 (val_txt)
           2396 LOAD_METHOD             51 (replace)
           2398 LOAD_CONST             139 ('hr')
           2400 LOAD_CONST             140 ('שעה')
           2402 CALL_METHOD              2
           2404 STORE_FAST              81 (val_txt)

644        2406 LOAD_GLOBAL             49 (get_display)
           2408 LOAD_FAST               81 (val_txt)
           2410 CALL_FUNCTION            1
           2412 STORE_FAST              81 (val_txt)

646     >> 2414 LOAD_GLOBAL             42 (len)
           2416 LOAD_FAST               81 (val_txt)
           2418 CALL_FUNCTION            1
           2420 LOAD_CONST             141 (8)
           2422 COMPARE_OP               4 (>)
           2424 EXTENDED_ARG             4
           2426 POP_JUMP_IF_FALSE     1216 (to 2432)
           2428 LOAD_CONST             138 (12)
           2430 JUMP_FORWARD             1 (to 2434)
        >> 2432 LOAD_CONST             142 (13.5)
        >> 2434 STORE_FAST              82 (fs_v)

647        2436 LOAD_FAST               69 (ax4)
           2438 LOAD_ATTR               19 (text)
           2440 LOAD_FAST               78 (v_x)
           2442 LOAD_FAST               76 (y)
           2444 LOAD_FAST               81 (val_txt)
           2446 LOAD_FAST               69 (ax4)
           2448 LOAD_ATTR               20 (transAxes)

648        2450 LOAD_FAST               82 (fs_v)
           2452 LOAD_GLOBAL             21 (TEXT_H)
           2454 LOAD_GLOBAL             50 (_ha)
           2456 LOAD_CONST              28 ('right')
           2458 LOAD_DEREF               0 (lang)
           2460 CALL_FUNCTION            2
           2462 LOAD_CONST              22 ('center')

649        2464 LOAD_CONST              21 ('bold')

647        2466 LOAD_CONST             108 (('transform', 'fontsize', 'color', 'ha', 'va', 'fontweight'))
           2468 CALL_FUNCTION_KW         9
           2470 POP_TOP
           2472 EXTENDED_ARG             4
           2474 JUMP_ABSOLUTE         1102 (to 2204)

652     >> 2476 LOAD_FAST               22 (fig)
           2478 LOAD_METHOD             31 (add_subplot)
           2480 LOAD_FAST               42 (gs)
           2482 LOAD_CONST             110 (3)
           2484 LOAD_FAST               43 (c_left)
           2486 BUILD_TUPLE              2
           2488 BINARY_SUBSCR
           2490 CALL_METHOD              1
           2492 STORE_FAST              83 (ax5)

653        2494 LOAD_GLOBAL             32 (_panel)
           2496 LOAD_FAST               83 (ax5)
           2498 CALL_FUNCTION            1
           2500 POP_TOP
           2502 LOAD_FAST               83 (ax5)
           2504 LOAD_METHOD             13 (axis)
           2506 LOAD_CONST              12 ('off')
           2508 CALL_METHOD              1
           2510 POP_TOP

654        2512 LOAD_GLOBAL             33 (_section_title)
           2514 LOAD_FAST               83 (ax5)
           2516 LOAD_CONST             143 ('Cardiovascular Metrics')
           2518 LOAD_CONST              49 (5)
           2520 LOAD_CONST             144 (1.15)
           2522 LOAD_DEREF               0 (lang)
           2524 LOAD_CONST              61 (('y_frac', 'lang'))
           2526 CALL_FUNCTION_KW         5
           2528 POP_TOP

656        2530 LOAD_FAST               19 (cv_stats)
           2532 LOAD_CONST               0 (None)
           2534 IS_OP                    0
           2536 EXTENDED_ARG             4
           2538 POP_JUMP_IF_FALSE     1277 (to 2554)

657        2540 LOAD_CONST             145 (62.0)
           2542 LOAD_CONST             146 (48.0)
           2544 LOAD_CONST             147 (110.0)
           2546 LOAD_CONST             148 ('N/A')
           2548 LOAD_CONST             149 (('avg_hr', 'min_hr', 'max_hr', 'rmssd'))
           2550 BUILD_CONST_KEY_MAP      4
           2552 STORE_FAST              19 (cv_stats)

659     >> 2554 LOAD_CONST             150 (<code object _fmt_cv at 0x0000026C8AA32760, file "patient_report.py", line 659>)
           2556 LOAD_CONST             151 ('_generate_single_report.<locals>._fmt_cv')
           2558 MAKE_FUNCTION            0
           2560 STORE_FAST              84 (_fmt_cv)

664        2562 LOAD_GLOBAL             18 (_t)
           2564 LOAD_CONST             152 ('bpm')
           2566 LOAD_DEREF               0 (lang)
           2568 CALL_FUNCTION            2
           2570 STORE_FAST              85 (bpm_str)

665        2572 LOAD_DEREF               0 (lang)
           2574 LOAD_CONST              25 ('he')
           2576 COMPARE_OP               2 (==)
           2578 EXTENDED_ARG             5
           2580 POP_JUMP_IF_FALSE     1302 (to 2604)
           2582 LOAD_FAST               85 (bpm_str)
           2584 FORMAT_VALUE             0
           2586 LOAD_CONST              30 (' ')
           2588 LOAD_FAST               84 (_fmt_cv)
           2590 LOAD_FAST               19 (cv_stats)
           2592 LOAD_CONST             153 ('avg_hr')
           2594 BINARY_SUBSCR
           2596 CALL_FUNCTION            1
           2598 FORMAT_VALUE             0
           2600 BUILD_STRING             3
           2602 JUMP_FORWARD            10 (to 2624)
        >> 2604 LOAD_FAST               84 (_fmt_cv)
           2606 LOAD_FAST               19 (cv_stats)
           2608 LOAD_CONST             153 ('avg_hr')
           2610 BINARY_SUBSCR
           2612 CALL_FUNCTION            1
           2614 FORMAT_VALUE             0
           2616 LOAD_CONST              30 (' ')
           2618 LOAD_FAST               85 (bpm_str)
           2620 FORMAT_VALUE             0
           2622 BUILD_STRING             3
        >> 2624 STORE_FAST              86 (hr_avg)

666        2626 LOAD_DEREF               0 (lang)
           2628 LOAD_CONST              25 ('he')
           2630 COMPARE_OP               2 (==)
           2632 EXTENDED_ARG             5
           2634 POP_JUMP_IF_FALSE     1336 (to 2672)
           2636 LOAD_FAST               85 (bpm_str)
           2638 FORMAT_VALUE             0
           2640 LOAD_CONST              30 (' ')
           2642 LOAD_FAST               84 (_fmt_cv)
           2644 LOAD_FAST               19 (cv_stats)
           2646 LOAD_CONST             154 ('min_hr')
           2648 BINARY_SUBSCR
           2650 CALL_FUNCTION            1
           2652 FORMAT_VALUE             0
           2654 LOAD_CONST             155 (' / ')
           2656 LOAD_FAST               84 (_fmt_cv)
           2658 LOAD_FAST               19 (cv_stats)
           2660 LOAD_CONST             156 ('max_hr')
           2662 BINARY_SUBSCR
           2664 CALL_FUNCTION            1
           2666 FORMAT_VALUE             0
           2668 BUILD_STRING             5
           2670 JUMP_FORWARD            17 (to 2706)
        >> 2672 LOAD_FAST               84 (_fmt_cv)
           2674 LOAD_FAST               19 (cv_stats)
           2676 LOAD_CONST             154 ('min_hr')
           2678 BINARY_SUBSCR
           2680 CALL_FUNCTION            1
           2682 FORMAT_VALUE             0
           2684 LOAD_CONST             155 (' / ')
           2686 LOAD_FAST               84 (_fmt_cv)
           2688 LOAD_FAST               19 (cv_stats)
           2690 LOAD_CONST             156 ('max_hr')
           2692 BINARY_SUBSCR
           2694 CALL_FUNCTION            1
           2696 FORMAT_VALUE             0
           2698 LOAD_CONST              30 (' ')
           2700 LOAD_FAST               85 (bpm_str)
           2702 FORMAT_VALUE             0
           2704 BUILD_STRING             5
        >> 2706 STORE_FAST              87 (hr_minmax)

669        2708 LOAD_CONST             157 ('Average Heart Rate')
           2710 LOAD_FAST               86 (hr_avg)
           2712 BUILD_TUPLE              2

670        2714 LOAD_CONST             158 ('Min / Max HR')
           2716 LOAD_FAST               87 (hr_minmax)
           2718 BUILD_TUPLE              2

668        2720 BUILD_LIST               2
           2722 STORE_FAST              88 (cv_rows)

673        2724 LOAD_FAST               84 (_fmt_cv)
           2726 LOAD_FAST               19 (cv_stats)
           2728 LOAD_CONST             159 ('rmssd')
           2730 BINARY_SUBSCR
           2732 CALL_FUNCTION            1
           2734 LOAD_CONST             148 ('N/A')
           2736 COMPARE_OP               3 (!=)
           2738 EXTENDED_ARG             5
           2740 POP_JUMP_IF_FALSE     1411 (to 2822)

674        2742 LOAD_DEREF               0 (lang)
           2744 LOAD_CONST              25 ('he')
           2746 COMPARE_OP               2 (==)
           2748 EXTENDED_ARG             5
           2750 POP_JUMP_IF_FALSE     1390 (to 2780)
           2752 LOAD_GLOBAL             18 (_t)
           2754 LOAD_CONST             160 ('ms')
           2756 LOAD_DEREF               0 (lang)
           2758 CALL_FUNCTION            2
           2760 FORMAT_VALUE             0
           2762 LOAD_CONST              30 (' ')
           2764 LOAD_FAST               84 (_fmt_cv)
           2766 LOAD_FAST               19 (cv_stats)
           2768 LOAD_CONST             159 ('rmssd')
           2770 BINARY_SUBSCR
           2772 CALL_FUNCTION            1
           2774 FORMAT_VALUE             0
           2776 BUILD_STRING             3
           2778 JUMP_FORWARD            13 (to 2806)
        >> 2780 LOAD_FAST               84 (_fmt_cv)
           2782 LOAD_FAST               19 (cv_stats)
           2784 LOAD_CONST             159 ('rmssd')
           2786 BINARY_SUBSCR
           2788 CALL_FUNCTION            1
           2790 FORMAT_VALUE             0
           2792 LOAD_CONST              30 (' ')
           2794 LOAD_GLOBAL             18 (_t)
           2796 LOAD_CONST             160 ('ms')
           2798 LOAD_DEREF               0 (lang)
           2800 CALL_FUNCTION            2
           2802 FORMAT_VALUE             0
           2804 BUILD_STRING             3
        >> 2806 STORE_FAST              89 (rmssd_val)

675        2808 LOAD_FAST               88 (cv_rows)
           2810 LOAD_METHOD             26 (append)
           2812 LOAD_CONST             161 ('Heart Rate Variability')
           2814 LOAD_FAST               89 (rmssd_val)
           2816 BUILD_TUPLE              2
           2818 CALL_METHOD              1
           2820 POP_TOP

677     >> 2822 LOAD_CONST             162 (0.22)
           2824 STORE_FAST              75 (step)

678        2826 LOAD_GLOBAL             38 (enumerate)
           2828 LOAD_FAST               88 (cv_rows)
           2830 CALL_FUNCTION            1
           2832 GET_ITER
        >> 2834 FOR_ITER                71 (to 2978)
           2836 UNPACK_SEQUENCE          2
           2838 STORE_FAST              50 (i)
           2840 UNPACK_SEQUENCE          2
           2842 STORE_FAST              52 (k)
           2844 STORE_FAST              51 (v)

679        2846 LOAD_CONST             163 (0.7)
           2848 LOAD_FAST               50 (i)
           2850 LOAD_FAST               75 (step)
           2852 BINARY_MULTIPLY
           2854 BINARY_SUBTRACT
           2856 STORE_FAST              76 (y)

680        2858 LOAD_GLOBAL             43 (_x)
           2860 LOAD_CONST              27 (0.02)
           2862 LOAD_DEREF               0 (lang)
           2864 CALL_FUNCTION            2
           2866 STORE_FAST              77 (k_x)

681        2868 LOAD_DEREF               0 (lang)
           2870 LOAD_CONST              25 ('he')
           2872 COMPARE_OP               2 (==)
           2874 EXTENDED_ARG             5
           2876 POP_JUMP_IF_FALSE     1444 (to 2888)
           2878 LOAD_GLOBAL             43 (_x)
           2880 LOAD_CONST             144 (1.15)
           2882 LOAD_DEREF               0 (lang)
           2884 CALL_FUNCTION            2
           2886 JUMP_FORWARD             4 (to 2896)
        >> 2888 LOAD_GLOBAL             43 (_x)
           2890 LOAD_CONST              68 (0.95)
           2892 LOAD_DEREF               0 (lang)
           2894 CALL_FUNCTION            2
        >> 2896 STORE_FAST              78 (v_x)

683        2898 LOAD_FAST               83 (ax5)
           2900 LOAD_ATTR               19 (text)
           2902 LOAD_FAST               77 (k_x)
           2904 LOAD_FAST               76 (y)
           2906 LOAD_GLOBAL             18 (_t)
           2908 LOAD_FAST               52 (k)
           2910 LOAD_DEREF               0 (lang)
           2912 CALL_FUNCTION            2
           2914 LOAD_FAST               83 (ax5)
           2916 LOAD_ATTR               20 (transAxes)

684        2918 LOAD_CONST             138 (12)
           2920 LOAD_GLOBAL             29 (TEXT_M)
           2922 LOAD_CONST              22 ('center')
           2924 LOAD_GLOBAL             50 (_ha)
           2926 LOAD_CONST              29 ('left')
           2928 LOAD_DEREF               0 (lang)
           2930 CALL_FUNCTION            2

683        2932 LOAD_CONST              46 (('transform', 'fontsize', 'color', 'va', 'ha'))
           2934 CALL_FUNCTION_KW         8
           2936 POP_TOP

686        2938 LOAD_FAST               83 (ax5)
           2940 LOAD_ATTR               19 (text)
           2942 LOAD_FAST               78 (v_x)
           2944 LOAD_FAST               76 (y)
           2946 LOAD_FAST               51 (v)
           2948 LOAD_FAST               83 (ax5)
           2950 LOAD_ATTR               20 (transAxes)

687        2952 LOAD_CONST             142 (13.5)
           2954 LOAD_GLOBAL             21 (TEXT_H)
           2956 LOAD_GLOBAL             50 (_ha)
           2958 LOAD_CONST              28 ('right')
           2960 LOAD_DEREF               0 (lang)
           2962 CALL_FUNCTION            2
           2964 LOAD_CONST              22 ('center')

688        2966 LOAD_CONST              21 ('bold')

686        2968 LOAD_CONST             108 (('transform', 'fontsize', 'color', 'ha', 'va', 'fontweight'))
           2970 CALL_FUNCTION_KW         9
           2972 POP_TOP
           2974 EXTENDED_ARG             5
           2976 JUMP_ABSOLUTE         1417 (to 2834)

691     >> 2978 LOAD_FAST               22 (fig)
           2980 LOAD_METHOD             31 (add_subplot)
           2982 LOAD_FAST               42 (gs)
           2984 LOAD_CONST             110 (3)
           2986 LOAD_FAST               44 (c_right)
           2988 BUILD_TUPLE              2
           2990 BINARY_SUBSCR
           2992 CALL_METHOD              1
           2994 STORE_FAST              90 (ax5b)

692        2996 LOAD_GLOBAL             32 (_panel)
           2998 LOAD_FAST               90 (ax5b)
           3000 CALL_FUNCTION            1
           3002 POP_TOP
           3004 LOAD_FAST               90 (ax5b)
           3006 LOAD_METHOD             13 (axis)
           3008 LOAD_CONST              12 ('off')
           3010 CALL_METHOD              1
           3012 POP_TOP

693        3014 LOAD_GLOBAL             33 (_section_title)
           3016 LOAD_FAST               90 (ax5b)
           3018 LOAD_CONST             164 ('Body Position Statistics')
           3020 LOAD_CONST             165 (6)
           3022 LOAD_CONST             144 (1.15)
           3024 LOAD_DEREF               0 (lang)
           3026 LOAD_CONST              61 (('y_frac', 'lang'))
           3028 CALL_FUNCTION_KW         5
           3030 POP_TOP

695        3032 LOAD_DEREF               2 (pos_stats)
           3034 LOAD_CONST               0 (None)
           3036 IS_OP                    0
           3038 EXTENDED_ARG             5
           3040 POP_JUMP_IF_FALSE     1528 (to 3056)

696        3042 LOAD_CONST             166 (45)
           3044 LOAD_CONST             167 (25)
           3046 LOAD_CONST              93 (20)
           3048 LOAD_CONST              10 (10)
           3050 LOAD_CONST             168 (('Supine', 'Left', 'Right', 'Prone'))
           3052 BUILD_CONST_KEY_MAP      4
           3054 STORE_DEREF              2 (pos_stats)

698     >> 3056 LOAD_GLOBAL             52 (list)
           3058 LOAD_DEREF               2 (pos_stats)
           3060 LOAD_METHOD             53 (keys)
           3062 CALL_METHOD              0
           3064 CALL_FUNCTION            1
           3066 STORE_FAST              91 (pos_labels)

699        3068 LOAD_CLOSURE             2 (pos_stats)
           3070 BUILD_TUPLE              1
           3072 LOAD_CONST             169 (<code object <listcomp> at 0x0000026C8AA32810, file "patient_report.py", line 699>)
           3074 LOAD_CONST             170 ('_generate_single_report.<locals>.<listcomp>')
           3076 MAKE_FUNCTION            8 (closure)
           3078 LOAD_FAST               91 (pos_labels)
           3080 GET_ITER
           3082 CALL_FUNCTION            1
           3084 STORE_FAST              92 (pos_fracs)

700        3086 BUILD_LIST               0
           3088 LOAD_CONST             171 (('#A3C4F3', '#E58EAA', '#F9C784', '#D4C4E9'))
           3090 LIST_EXTEND              1
           3092 STORE_FAST              93 (pos_colors)

702        3094 LOAD_FAST               90 (ax5b)
           3096 LOAD_METHOD             34 (inset_axes)
           3098 BUILD_LIST               0
           3100 LOAD_CONST             172 ((0.0, -0.75, 1.0, 1.7))
           3102 LIST_EXTEND              1
           3104 CALL_METHOD              1
           3106 STORE_FAST              94 (ax5_pie)

703        3108 LOAD_CLOSURE             0 (lang)
           3110 BUILD_TUPLE              1
           3112 LOAD_CONST             173 (<code object <listcomp> at 0x0000026C8AA328C0, file "patient_report.py", line 703>)
           3114 LOAD_CONST             170 ('_generate_single_report.<locals>.<listcomp>')
           3116 MAKE_FUNCTION            8 (closure)
           3118 LOAD_FAST               91 (pos_labels)
           3120 GET_ITER
           3122 CALL_FUNCTION            1
           3124 STORE_FAST              95 (disp_labels)

704        3126 BUILD_LIST               0
           3128 STORE_FAST              96 (filtered_fracs)

705        3130 BUILD_LIST               0
           3132 STORE_FAST              97 (filtered_labels)

706        3134 BUILD_LIST               0
           3136 STORE_FAST              98 (filtered_colors)

707        3138 LOAD_GLOBAL             54 (zip)
           3140 LOAD_FAST               92 (pos_fracs)
           3142 LOAD_FAST               95 (disp_labels)
           3144 LOAD_FAST               93 (pos_colors)
           3146 CALL_FUNCTION            3
           3148 GET_ITER
        >> 3150 FOR_ITER                26 (to 3204)
           3152 UNPACK_SEQUENCE          3
           3154 STORE_FAST              99 (f)
           3156 STORE_FAST             100 (l)
           3158 STORE_FAST             101 (c)

708        3160 LOAD_FAST               99 (f)
           3162 LOAD_CONST               3 (0)
           3164 COMPARE_OP               4 (>)
           3166 EXTENDED_ARG             6
           3168 POP_JUMP_IF_FALSE     1600 (to 3200)

709        3170 LOAD_FAST               96 (filtered_fracs)
           3172 LOAD_METHOD             26 (append)
           3174 LOAD_FAST               99 (f)
           3176 CALL_METHOD              1
           3178 POP_TOP

710        3180 LOAD_FAST               97 (filtered_labels)
           3182 LOAD_METHOD             26 (append)
           3184 LOAD_FAST              100 (l)
           3186 CALL_METHOD              1
           3188 POP_TOP

711        3190 LOAD_FAST               98 (filtered_colors)
           3192 LOAD_METHOD             26 (append)
           3194 LOAD_FAST              101 (c)
           3196 CALL_METHOD              1
           3198 POP_TOP
        >> 3200 EXTENDED_ARG             6
           3202 JUMP_ABSOLUTE         1575 (to 3150)

713     >> 3204 LOAD_FAST               96 (filtered_fracs)
           3206 EXTENDED_ARG             6
           3208 POP_JUMP_IF_FALSE     1662 (to 3324)

714        3210 LOAD_FAST               94 (ax5_pie)
           3212 LOAD_ATTR               55 (pie)
           3214 LOAD_FAST               96 (filtered_fracs)
           3216 LOAD_FAST               97 (filtered_labels)
           3218 LOAD_FAST               98 (filtered_colors)
           3220 LOAD_CONST             174 (90)

715        3222 LOAD_CONST             175 ('%1.0f%%')
           3224 LOAD_CONST             103 (0.75)
           3226 LOAD_CONST             144 (1.15)

716        3228 LOAD_CONST              19 (0.5)
           3230 LOAD_CONST             107 ('white')
           3232 LOAD_CONST             176 (1.8)
           3234 LOAD_CONST             177 (('width', 'edgecolor', 'linewidth'))
           3236 BUILD_CONST_KEY_MAP      3

714        3238 LOAD_CONST             178 (('labels', 'colors', 'startangle', 'autopct', 'pctdistance', 'labeldistance', 'wedgeprops'))
           3240 CALL_FUNCTION_KW         8
           3242 UNPACK_SEQUENCE          3
           3244 STORE_FAST             102 (_)
           3246 STORE_FAST             103 (texts)
           3248 STORE_FAST             104 (auts)

717        3250 LOAD_FAST              103 (texts)
           3252 GET_ITER
        >> 3254 FOR_ITER                13 (to 3282)
           3256 STORE_FAST             105 (t)

718        3258 LOAD_FAST              105 (t)
           3260 LOAD_METHOD             56 (set_fontsize)
           3262 LOAD_CONST              10 (10)
           3264 CALL_METHOD              1
           3266 POP_TOP

719        3268 LOAD_FAST              105 (t)
           3270 LOAD_METHOD             57 (set_color)
           3272 LOAD_GLOBAL             21 (TEXT_H)
           3274 CALL_METHOD              1
           3276 POP_TOP
           3278 EXTENDED_ARG             6
           3280 JUMP_ABSOLUTE         1627 (to 3254)

720     >> 3282 LOAD_FAST              104 (auts)
           3284 GET_ITER
        >> 3286 FOR_ITER                18 (to 3324)
           3288 STORE_FAST             106 (at)

721        3290 LOAD_FAST              106 (at)
           3292 LOAD_METHOD             57 (set_color)
           3294 LOAD_CONST             107 ('white')
           3296 CALL_METHOD              1
           3298 POP_TOP

722        3300 LOAD_FAST              106 (at)
           3302 LOAD_METHOD             56 (set_fontsize)
           3304 LOAD_CONST              83 (9)
           3306 CALL_METHOD              1
           3308 POP_TOP

723        3310 LOAD_FAST              106 (at)
           3312 LOAD_METHOD             58 (set_fontweight)
           3314 LOAD_CONST              21 ('bold')
           3316 CALL_METHOD              1
           3318 POP_TOP
           3320 EXTENDED_ARG             6
           3322 JUMP_ABSOLUTE         1643 (to 3286)

725     >> 3324 LOAD_FAST               11 (resp_stats)
           3326 EXTENDED_ARG             6
           3328 POP_JUMP_IF_FALSE     1774 (to 3548)
           3330 LOAD_CONST             179 ('pAHI 3%')
           3332 LOAD_FAST               11 (resp_stats)
           3334 CONTAINS_OP              0
           3336 EXTENDED_ARG             6
           3338 POP_JUMP_IF_FALSE     1774 (to 3548)
           3340 LOAD_FAST               11 (resp_stats)
           3342 LOAD_CONST             179 ('pAHI 3%')
           3344 BINARY_SUBSCR
           3346 LOAD_METHOD             48 (get)
           3348 LOAD_CONST             180 ('supine')
           3350 CALL_METHOD              1
           3352 LOAD_CONST               0 (None)
           3354 IS_OP                    1
           3356 EXTENDED_ARG             6
           3358 POP_JUMP_IF_TRUE      1690 (to 3380)
           3360 LOAD_FAST               11 (resp_stats)
           3362 LOAD_CONST             179 ('pAHI 3%')
           3364 BINARY_SUBSCR
           3366 LOAD_METHOD             48 (get)
           3368 LOAD_CONST             181 ('nsupine')
           3370 CALL_METHOD              1
           3372 LOAD_CONST               0 (None)
           3374 IS_OP                    1
           3376 EXTENDED_ARG             6
           3378 POP_JUMP_IF_FALSE     1774 (to 3548)

726     >> 3380 LOAD_FAST               11 (resp_stats)
           3382 LOAD_CONST             179 ('pAHI 3%')
           3384 BINARY_SUBSCR
           3386 LOAD_METHOD             48 (get)
           3388 LOAD_CONST             180 ('supine')
           3390 CALL_METHOD              1
           3392 STORE_FAST             107 (sup_ahi)

727        3394 LOAD_FAST               11 (resp_stats)
           3396 LOAD_CONST             179 ('pAHI 3%')
           3398 BINARY_SUBSCR
           3400 LOAD_METHOD             48 (get)
           3402 LOAD_CONST             181 ('nsupine')
           3404 CALL_METHOD              1
           3406 STORE_FAST             108 (nsup_ahi)

729        3408 LOAD_FAST              107 (sup_ahi)
           3410 LOAD_CONST               0 (None)
           3412 IS_OP                    1
           3414 EXTENDED_ARG             6
           3416 POP_JUMP_IF_FALSE     1713 (to 3426)
           3418 LOAD_FAST              107 (sup_ahi)
           3420 LOAD_CONST             124 ('.1f')
           3422 FORMAT_VALUE             4 (with format)
           3424 JUMP_FORWARD             1 (to 3428)
        >> 3426 LOAD_CONST             148 ('N/A')
        >> 3428 STORE_FAST             109 (sup_str)

730        3430 LOAD_FAST              108 (nsup_ahi)
           3432 LOAD_CONST               0 (None)
           3434 IS_OP                    1
           3436 EXTENDED_ARG             6
           3438 POP_JUMP_IF_FALSE     1724 (to 3448)
           3440 LOAD_FAST              108 (nsup_ahi)
           3442 LOAD_CONST             124 ('.1f')
           3444 FORMAT_VALUE             4 (with format)
           3446 JUMP_FORWARD             1 (to 3450)
        >> 3448 LOAD_CONST             148 ('N/A')
        >> 3450 STORE_FAST             110 (nsup_str)

732        3452 LOAD_DEREF               0 (lang)
           3454 LOAD_CONST              25 ('he')
           3456 COMPARE_OP               2 (==)
           3458 EXTENDED_ARG             6
           3460 POP_JUMP_IF_FALSE     1742 (to 3484)

733        3462 LOAD_GLOBAL             49 (get_display)
           3464 LOAD_CONST             182 ('pAHI\nגב: ')
           3466 LOAD_FAST              109 (sup_str)
           3468 FORMAT_VALUE             0
           3470 LOAD_CONST             183 ('\nלא גב: ')
           3472 LOAD_FAST              110 (nsup_str)
           3474 FORMAT_VALUE             0
           3476 BUILD_STRING             4
           3478 CALL_FUNCTION            1
           3480 STORE_FAST             111 (bottom_str)
           3482 JUMP_FORWARD             8 (to 3500)

735     >> 3484 LOAD_CONST             184 ('pAHI\nSupine:\n')
           3486 LOAD_FAST              109 (sup_str)
           3488 FORMAT_VALUE             0
           3490 LOAD_CONST             185 ('\nNon-Supine:\n')
           3492 LOAD_FAST              110 (nsup_str)
           3494 FORMAT_VALUE             0
           3496 BUILD_STRING             4
           3498 STORE_FAST             111 (bottom_str)

736     >> 3500 LOAD_DEREF               0 (lang)
           3502 LOAD_CONST              25 ('he')
           3504 COMPARE_OP               2 (==)
           3506 EXTENDED_ARG             6
           3508 POP_JUMP_IF_FALSE     1757 (to 3514)
           3510 LOAD_CONST              90 (0.52)
           3512 JUMP_FORWARD             1 (to 3516)
        >> 3514 LOAD_CONST             186 (0.49)
        >> 3516 STORE_FAST             112 (text_y)

737        3518 LOAD_FAST               94 (ax5_pie)
           3520 LOAD_ATTR               19 (text)
           3522 LOAD_CONST              19 (0.5)
           3524 LOAD_FAST              112 (text_y)
           3526 LOAD_FAST              111 (bottom_str)
           3528 LOAD_FAST               94 (ax5_pie)
           3530 LOAD_ATTR               20 (transAxes)

738        3532 LOAD_CONST             187 (7)
           3534 LOAD_GLOBAL             21 (TEXT_H)
           3536 LOAD_CONST              22 ('center')
           3538 LOAD_CONST              22 ('center')
           3540 LOAD_CONST              21 ('bold')

737        3542 LOAD_CONST             108 (('transform', 'fontsize', 'color', 'ha', 'va', 'fontweight'))
           3544 CALL_FUNCTION_KW         9
           3546 POP_TOP

741     >> 3548 LOAD_FAST               22 (fig)
           3550 LOAD_METHOD             31 (add_subplot)
           3552 LOAD_FAST               42 (gs)
           3554 LOAD_CONST             119 (4)
           3556 LOAD_CONST               0 (None)
           3558 LOAD_CONST               0 (None)
           3560 BUILD_SLICE              2
           3562 BUILD_TUPLE              2
           3564 BINARY_SUBSCR
           3566 CALL_METHOD              1
           3568 STORE_FAST             113 (ax6)

742        3570 LOAD_GLOBAL             32 (_panel)
           3572 LOAD_FAST              113 (ax6)
           3574 CALL_FUNCTION            1
           3576 POP_TOP
           3578 LOAD_FAST              113 (ax6)
           3580 LOAD_METHOD             13 (axis)
           3582 LOAD_CONST              12 ('off')
           3584 CALL_METHOD              1
           3586 POP_TOP

743        3588 LOAD_GLOBAL             33 (_section_title)
           3590 LOAD_FAST              113 (ax6)
           3592 LOAD_CONST             188 ('Summary')
           3594 LOAD_CONST             187 (7)
           3596 LOAD_CONST              68 (0.95)
           3598 LOAD_DEREF               0 (lang)
           3600 LOAD_CONST              61 (('y_frac', 'lang'))
           3602 CALL_FUNCTION_KW         5
           3604 POP_TOP

745        3606 LOAD_GLOBAL             59 (_bullets)
           3608 LOAD_FAST               21 (st)
           3610 LOAD_FAST               20 (rdi_v)
           3612 LOAD_FAST                7 (spo2_stats)
           3614 LOAD_DEREF               0 (lang)
           3616 LOAD_CONST              66 (('lang',))
           3618 CALL_FUNCTION_KW         4
           3620 STORE_FAST             114 (blist)

746        3622 LOAD_FAST               13 (notes)
           3624 EXTENDED_ARG             7
           3626 POP_JUMP_IF_FALSE     1835 (to 3670)

747        3628 LOAD_DEREF               0 (lang)
           3630 LOAD_CONST              25 ('he')
           3632 COMPARE_OP               2 (==)
           3634 EXTENDED_ARG             7
           3636 POP_JUMP_IF_FALSE     1830 (to 3660)

748        3638 LOAD_FAST              114 (blist)
           3640 LOAD_METHOD             60 (extend)
           3642 LOAD_CONST             189 (<code object <listcomp> at 0x0000026C8AA32970, file "patient_report.py", line 748>)
           3644 LOAD_CONST             170 ('_generate_single_report.<locals>.<listcomp>')
           3646 MAKE_FUNCTION            0
           3648 LOAD_FAST               13 (notes)
           3650 GET_ITER
           3652 CALL_FUNCTION            1
           3654 CALL_METHOD              1
           3656 POP_TOP
           3658 JUMP_FORWARD             5 (to 3670)

750     >> 3660 LOAD_FAST              114 (blist)
           3662 LOAD_METHOD             60 (extend)
           3664 LOAD_FAST               13 (notes)
           3666 CALL_METHOD              1
           3668 POP_TOP

752     >> 3670 LOAD_CONST              52 (0.23)
           3672 STORE_FAST             115 (line_h)

753        3674 LOAD_GLOBAL             38 (enumerate)
           3676 LOAD_FAST              114 (blist)
           3678 LOAD_CONST               0 (None)
           3680 LOAD_CONST              49 (5)
           3682 BUILD_SLICE              2
           3684 BINARY_SUBSCR
           3686 CALL_FUNCTION            1
           3688 GET_ITER
        >> 3690 FOR_ITER                47 (to 3786)
           3692 UNPACK_SEQUENCE          2
           3694 STORE_FAST              50 (i)
           3696 STORE_FAST             116 (line)

754        3698 LOAD_CONST              65 (0.65)
           3700 LOAD_FAST               50 (i)
           3702 LOAD_FAST              115 (line_h)
           3704 BINARY_MULTIPLY
           3706 BINARY_SUBTRACT
           3708 STORE_FAST              76 (y)

755        3710 LOAD_FAST              113 (ax6)
           3712 LOAD_ATTR               24 (plot)
           3714 LOAD_GLOBAL             43 (_x)
           3716 LOAD_CONST             190 (0.012)
           3718 LOAD_DEREF               0 (lang)
           3720 CALL_FUNCTION            2
           3722 LOAD_FAST               76 (y)
           3724 LOAD_CONST             191 ('o')
           3726 LOAD_GLOBAL             25 (ACCENT)
           3728 LOAD_CONST             119 (4)

756        3730 LOAD_FAST              113 (ax6)
           3732 LOAD_ATTR               20 (transAxes)
           3734 LOAD_CONST             192 (False)

755        3736 LOAD_CONST             193 (('color', 'markersize', 'transform', 'clip_on'))
           3738 CALL_FUNCTION_KW         7
           3740 POP_TOP

757        3742 LOAD_FAST              113 (ax6)
           3744 LOAD_ATTR               19 (text)
           3746 LOAD_GLOBAL             43 (_x)
           3748 LOAD_CONST              84 (0.03)
           3750 LOAD_DEREF               0 (lang)
           3752 CALL_FUNCTION            2
           3754 LOAD_FAST               76 (y)
           3756 LOAD_FAST              116 (line)

758        3758 LOAD_FAST              113 (ax6)
           3760 LOAD_ATTR               20 (transAxes)
           3762 LOAD_CONST              45 (13)

759        3764 LOAD_GLOBAL             21 (TEXT_H)
           3766 LOAD_CONST              22 ('center')
           3768 LOAD_GLOBAL             50 (_ha)
           3770 LOAD_CONST              29 ('left')
           3772 LOAD_DEREF               0 (lang)
           3774 CALL_FUNCTION            2

757        3776 LOAD_CONST              46 (('transform', 'fontsize', 'color', 'va', 'ha'))
           3778 CALL_FUNCTION_KW         8
           3780 POP_TOP
           3782 EXTENDED_ARG             7
           3784 JUMP_ABSOLUTE         1845 (to 3690)

762     >> 3786 LOAD_FAST               22 (fig)
           3788 LOAD_METHOD             11 (add_axes)
           3790 BUILD_LIST               0
           3792 LOAD_CONST             194 ((0.04, 0.08, 0.92, 0.14))
           3794 LIST_EXTEND              1
           3796 CALL_METHOD              1
           3798 STORE_FAST             117 (ax_f)

763        3800 LOAD_FAST              117 (ax_f)
           3802 LOAD_METHOD             13 (axis)
           3804 LOAD_CONST              12 ('off')
           3806 CALL_METHOD              1
           3808 POP_TOP

764        3810 LOAD_FAST              117 (ax_f)
           3812 LOAD_ATTR               24 (plot)
           3814 LOAD_CONST               3 (0)
           3816 LOAD_CONST              34 (1)
           3818 BUILD_LIST               2
           3820 LOAD_CONST              71 (0.85)
           3822 LOAD_CONST              71 (0.85)
           3824 BUILD_LIST               2
           3826 LOAD_GLOBAL             36 (BORDER)
           3828 LOAD_CONST             195 (0.8)
           3830 LOAD_FAST              117 (ax_f)
           3832 LOAD_ATTR               20 (transAxes)
           3834 LOAD_CONST              37 (('color', 'lw', 'transform'))
           3836 CALL_FUNCTION_KW         5
           3838 POP_TOP

766        3840 LOAD_FAST               21 (st)
           3842 LOAD_METHOD             48 (get)
           3844 LOAD_CONST              74 ('TST')
           3846 CALL_METHOD              1
           3848 EXTENDED_ARG             7
           3850 POP_JUMP_IF_FALSE     1932 (to 3864)
           3852 LOAD_FAST               21 (st)
           3854 LOAD_CONST              74 ('TST')
           3856 BINARY_SUBSCR
           3858 LOAD_CONST             196 (60.0)
           3860 BINARY_TRUE_DIVIDE
           3862 JUMP_FORWARD             1 (to 3866)
        >> 3864 LOAD_CONST               3 (0)
        >> 3866 STORE_FAST             118 (tst_hrs)

767        3868 LOAD_FAST               20 (rdi_v)
           3870 LOAD_CONST               0 (None)
           3872 IS_OP                    1
           3874 EXTENDED_ARG             7
           3876 POP_JUMP_IF_FALSE     1941 (to 3882)
           3878 LOAD_FAST               20 (rdi_v)
           3880 JUMP_FORWARD             1 (to 3884)
        >> 3882 LOAD_CONST               3 (0)
        >> 3884 STORE_FAST             119 (rdi_val)

768        3886 LOAD_FAST               21 (st)
           3888 LOAD_METHOD             48 (get)
           3890 LOAD_CONST              74 ('TST')
           3892 CALL_METHOD              1
           3894 EXTENDED_ARG             7
           3896 POP_JUMP_IF_FALSE     1966 (to 3932)
           3898 LOAD_FAST               21 (st)
           3900 LOAD_CONST              74 ('TST')
           3902 BINARY_SUBSCR
           3904 LOAD_CONST               3 (0)
           3906 COMPARE_OP               4 (>)
           3908 EXTENDED_ARG             7
           3910 POP_JUMP_IF_FALSE     1966 (to 3932)
           3912 LOAD_FAST                7 (spo2_stats)
           3914 LOAD_CONST             122 ('t_under90')
           3916 BINARY_SUBSCR
           3918 LOAD_FAST               21 (st)
           3920 LOAD_CONST              74 ('TST')
           3922 BINARY_SUBSCR
           3924 BINARY_TRUE_DIVIDE
           3926 LOAD_CONST             197 (100.0)
           3928 BINARY_MULTIPLY
           3930 JUMP_FORWARD             1 (to 3934)
        >> 3932 LOAD_CONST               3 (0)
        >> 3934 STORE_FAST              73 (t90_val)

769        3936 LOAD_FAST                7 (spo2_stats)
           3938 LOAD_METHOD             48 (get)
           3940 LOAD_CONST             120 ('avg')
           3942 LOAD_CONST             198 (100)
           3944 CALL_METHOD              2
           3946 STORE_FAST             120 (avg_sat_val)

770        3948 LOAD_FAST                7 (spo2_stats)
           3950 LOAD_METHOD             48 (get)
           3952 LOAD_CONST             121 ('min')
           3954 LOAD_CONST             198 (100)
           3956 CALL_METHOD              2
           3958 STORE_FAST             121 (min_sat_val)

772        3960 LOAD_GLOBAL             61 (get_clinical_conclusion)
           3962 LOAD_FAST              118 (tst_hrs)
           3964 LOAD_FAST              119 (rdi_val)
           3966 LOAD_FAST               73 (t90_val)
           3968 LOAD_FAST              120 (avg_sat_val)
           3970 LOAD_FAST              121 (min_sat_val)
           3972 LOAD_DEREF               0 (lang)
           3974 CALL_FUNCTION            6
           3976 STORE_FAST             122 (conclusion)

774        3978 LOAD_CONST               3 (0)
           3980 LOAD_CONST               0 (None)
           3982 IMPORT_NAME             62 (textwrap)
           3984 STORE_FAST             123 (textwrap)

775        3986 BUILD_LIST               0
           3988 STORE_FAST             124 (wrapped_lines)

776        3990 LOAD_FAST              122 (conclusion)
           3992 LOAD_METHOD             23 (split)
           3994 LOAD_CONST             199 ('\n')
           3996 CALL_METHOD              1
           3998 GET_ITER
        >> 4000 FOR_ITER                13 (to 4028)
           4002 STORE_FAST             116 (line)

777        4004 LOAD_FAST              124 (wrapped_lines)
           4006 LOAD_METHOD             60 (extend)
           4008 LOAD_FAST              123 (textwrap)
           4010 LOAD_ATTR               63 (wrap)
           4012 LOAD_FAST              116 (line)
           4014 LOAD_CONST             198 (100)
           4016 LOAD_CONST             200 (('width',))
           4018 CALL_FUNCTION_KW         2
           4020 CALL_METHOD              1
           4022 POP_TOP
           4024 EXTENDED_ARG             7
           4026 JUMP_ABSOLUTE         2000 (to 4000)

779     >> 4028 LOAD_DEREF               0 (lang)
           4030 LOAD_CONST              25 ('he')
           4032 COMPARE_OP               2 (==)
           4034 EXTENDED_ARG             7
           4036 POP_JUMP_IF_FALSE     2030 (to 4060)

780        4038 LOAD_CONST             199 ('\n')
           4040 LOAD_METHOD             28 (join)
           4042 LOAD_CONST             201 (<code object <listcomp> at 0x0000026C8AA32A20, file "patient_report.py", line 780>)
           4044 LOAD_CONST             170 ('_generate_single_report.<locals>.<listcomp>')
           4046 MAKE_FUNCTION            0
           4048 LOAD_FAST              124 (wrapped_lines)
           4050 GET_ITER
           4052 CALL_FUNCTION            1
           4054 CALL_METHOD              1
           4056 STORE_FAST             122 (conclusion)
           4058 JUMP_FORWARD             5 (to 4070)

782     >> 4060 LOAD_CONST             199 ('\n')
           4062 LOAD_METHOD             28 (join)
           4064 LOAD_FAST              124 (wrapped_lines)
           4066 CALL_METHOD              1
           4068 STORE_FAST             122 (conclusion)

784     >> 4070 LOAD_FAST              117 (ax_f)
           4072 LOAD_ATTR               19 (text)
           4074 LOAD_CONST              19 (0.5)
           4076 LOAD_CONST             202 (0.63)
           4078 LOAD_FAST              122 (conclusion)
           4080 LOAD_CONST              22 ('center')
           4082 LOAD_CONST              22 ('center')
           4084 LOAD_CONST              45 (13)

785        4086 LOAD_GLOBAL             21 (TEXT_H)
           4088 LOAD_FAST              117 (ax_f)
           4090 LOAD_ATTR               20 (transAxes)
           4092 LOAD_CONST              21 ('bold')
           4094 LOAD_CONST             203 (1.6)

784        4096 LOAD_CONST             204 (('ha', 'va', 'fontsize', 'color', 'transform', 'fontweight', 'linespacing'))
           4098 CALL_FUNCTION_KW        10
           4100 POP_TOP

787        4102 LOAD_CONST             205 ("Disclaimer: This report was generated as part of a scientific research study during which the participant's overnight sleep recordings were collected. The information presented herein is limited in scope, does not provide comprehensive respiratory measurements, and should not be considered a substitute for a clinical sleep study. In any case of uncertainty or clinical concern, further evaluation by a clinical sleep laboratory is recommended.")
           4104 STORE_FAST             125 (disclaimer_en)

788        4106 LOAD_CONST             206 ('הבהרה: דוח זה בוצע כחלק ממחקר מדעי שבמהלכו נאספו רישומי שנת הלילה של הנבדק. מידע זה הינו חלקי בלבד, אינו מספק מדדי נשימה מלאים ואינו מהווה תחליף לבדיקת שינה קלינית. בכל מצב המעורר ספק יש לפנות למעבדת שינה קלינית לבירור נוסף')
           4108 STORE_FAST             126 (disclaimer_he)

790        4110 LOAD_DEREF               0 (lang)
           4112 LOAD_CONST              25 ('he')
           4114 COMPARE_OP               2 (==)
           4116 EXTENDED_ARG             8
           4118 POP_JUMP_IF_FALSE     2062 (to 4124)
           4120 LOAD_FAST              126 (disclaimer_he)
           4122 JUMP_FORWARD             1 (to 4126)
        >> 4124 LOAD_FAST              125 (disclaimer_en)
        >> 4126 STORE_FAST             127 (disc_text)

791        4128 BUILD_LIST               0
           4130 STORE_FAST             128 (wrapped_disc)

792        4132 LOAD_FAST              127 (disc_text)
           4134 LOAD_METHOD             23 (split)
           4136 LOAD_CONST             199 ('\n')
           4138 CALL_METHOD              1
           4140 GET_ITER
        >> 4142 FOR_ITER                13 (to 4170)
           4144 STORE_FAST             116 (line)

793        4146 LOAD_FAST              128 (wrapped_disc)
           4148 LOAD_METHOD             60 (extend)
           4150 LOAD_FAST              123 (textwrap)
           4152 LOAD_ATTR               63 (wrap)
           4154 LOAD_FAST              116 (line)
           4156 LOAD_CONST             207 (130)
           4158 LOAD_CONST             200 (('width',))
           4160 CALL_FUNCTION_KW         2
           4162 CALL_METHOD              1
           4164 POP_TOP
           4166 EXTENDED_ARG             8
           4168 JUMP_ABSOLUTE         2071 (to 4142)

794     >> 4170 LOAD_DEREF               0 (lang)
           4172 LOAD_CONST              25 ('he')
           4174 COMPARE_OP               2 (==)
           4176 EXTENDED_ARG             8
           4178 POP_JUMP_IF_FALSE     2101 (to 4202)

795        4180 LOAD_CONST             199 ('\n')
           4182 LOAD_METHOD             28 (join)
           4184 LOAD_CONST             208 (<code object <listcomp> at 0x0000026C8AA32AD0, file "patient_report.py", line 795>)
           4186 LOAD_CONST             170 ('_generate_single_report.<locals>.<listcomp>')
           4188 MAKE_FUNCTION            0
           4190 LOAD_FAST              128 (wrapped_disc)
           4192 GET_ITER
           4194 CALL_FUNCTION            1
           4196 CALL_METHOD              1
           4198 STORE_FAST             129 (disc_str)
           4200 JUMP_FORWARD             5 (to 4212)

797     >> 4202 LOAD_CONST             199 ('\n')
           4204 LOAD_METHOD             28 (join)
           4206 LOAD_FAST              128 (wrapped_disc)
           4208 CALL_METHOD              1
           4210 STORE_FAST             129 (disc_str)

799     >> 4212 LOAD_FAST              117 (ax_f)
           4214 LOAD_ATTR               19 (text)
           4216 LOAD_CONST              19 (0.5)
           4218 LOAD_CONST             209 (0.15)
           4220 LOAD_FAST              129 (disc_str)
           4222 LOAD_CONST              22 ('center')
           4224 LOAD_CONST              22 ('center')
           4226 LOAD_CONST              82 (7.5)

800        4228 LOAD_GLOBAL             29 (TEXT_M)
           4230 LOAD_FAST              117 (ax_f)
           4232 LOAD_ATTR               20 (transAxes)
           4234 LOAD_CONST             210 (1.4)

799        4236 LOAD_CONST             211 (('ha', 'va', 'fontsize', 'color', 'transform', 'linespacing'))
           4238 CALL_FUNCTION_KW         9
           4240 POP_TOP

803        4242 LOAD_DEREF               0 (lang)
           4244 LOAD_CONST              25 ('he')
           4246 COMPARE_OP               2 (==)
           4248 EXTENDED_ARG             8
           4250 POP_JUMP_IF_FALSE     2134 (to 4268)

804        4252 LOAD_FAST                3 (outdir)
           4254 LOAD_FAST                1 (subject_id)
           4256 FORMAT_VALUE             0
           4258 LOAD_CONST             212 ('_patient_report_he.png')
           4260 BUILD_STRING             2
           4262 BINARY_TRUE_DIVIDE
           4264 STORE_FAST             130 (out_path)
           4266 JUMP_FORWARD             7 (to 4282)

806     >> 4268 LOAD_FAST                3 (outdir)
           4270 LOAD_FAST                1 (subject_id)
           4272 FORMAT_VALUE             0
           4274 LOAD_CONST             213 ('_patient_report_en.png')
           4276 BUILD_STRING             2
           4278 BINARY_TRUE_DIVIDE
           4280 STORE_FAST             130 (out_path)

808     >> 4282 LOAD_FAST               22 (fig)
           4284 LOAD_ATTR               64 (savefig)
           4286 LOAD_FAST              130 (out_path)
           4288 LOAD_FAST               17 (dpi)
           4290 LOAD_CONST             214 ('tight')
           4292 LOAD_GLOBAL              3 (BG)
           4294 LOAD_CONST             215 (('dpi', 'bbox_inches', 'facecolor'))
           4296 CALL_FUNCTION_KW         4
           4298 POP_TOP

809        4300 LOAD_GLOBAL              1 (plt)
           4302 LOAD_METHOD             65 (close)
           4304 LOAD_FAST               22 (fig)
           4306 CALL_METHOD              1
           4308 POP_TOP

810        4310 LOAD_GLOBAL             15 (print)
           4312 LOAD_CONST             216 ('[PatientReport] Saved -> ')
           4314 LOAD_FAST              130 (out_path)
           4316 FORMAT_VALUE             0
           4318 BUILD_STRING             2
           4320 CALL_FUNCTION            1
           4322 POP_TOP

813        4324 SETUP_FINALLY           56 (to 4438)

814        4326 LOAD_CONST               3 (0)
           4328 LOAD_CONST               4 (('Image',))
           4330 IMPORT_NAME              6 (PIL)
           4332 IMPORT_FROM              7 (Image)
           4334 STORE_FAST              23 (Image)
           4336 POP_TOP

815        4338 LOAD_FAST              130 (out_path)
           4340 LOAD_METHOD             66 (with_suffix)
           4342 LOAD_CONST             217 ('.pdf')
           4344 CALL_METHOD              1
           4346 STORE_FAST             131 (pdf_path)

816        4348 LOAD_FAST               23 (Image)
           4350 LOAD_METHOD             10 (open)
           4352 LOAD_FAST              130 (out_path)
           4354 CALL_METHOD              1
           4356 SETUP_WITH              21 (to 4400)
           4358 STORE_FAST             132 (img)

817        4360 LOAD_FAST              132 (img)
           4362 LOAD_METHOD             67 (convert)
           4364 LOAD_CONST             218 ('RGB')
           4366 CALL_METHOD              1
           4368 STORE_FAST             133 (rgb_img)

818        4370 LOAD_FAST              133 (rgb_img)
           4372 LOAD_ATTR               68 (save)
           4374 LOAD_FAST              131 (pdf_path)
           4376 LOAD_CONST             219 ('PDF')
           4378 LOAD_CONST             197 (100.0)
           4380 LOAD_CONST             220 (('resolution',))
           4382 CALL_FUNCTION_KW         3
           4384 POP_TOP
           4386 POP_BLOCK

816        4388 LOAD_CONST               0 (None)
           4390 DUP_TOP
           4392 DUP_TOP
           4394 CALL_FUNCTION            3
           4396 POP_TOP
           4398 JUMP_FORWARD             9 (to 4418)
        >> 4400 WITH_EXCEPT_START
           4402 EXTENDED_ARG             8
           4404 POP_JUMP_IF_TRUE      2204 (to 4408)
           4406 RERAISE                  1
        >> 4408 POP_TOP
           4410 POP_TOP
           4412 POP_TOP
           4414 POP_EXCEPT
           4416 POP_TOP

819     >> 4418 LOAD_GLOBAL             15 (print)
           4420 LOAD_CONST             216 ('[PatientReport] Saved -> ')
           4422 LOAD_FAST              131 (pdf_path)
           4424 FORMAT_VALUE             0
           4426 BUILD_STRING             2
           4428 CALL_FUNCTION            1
           4430 POP_TOP

820        4432 LOAD_FAST              131 (pdf_path)
           4434 POP_BLOCK
           4436 RETURN_VALUE

821     >> 4438 DUP_TOP
           4440 LOAD_GLOBAL             14 (Exception)
           4442 EXTENDED_ARG             8
           4444 JUMP_IF_NOT_EXC_MATCH  2246 (to 4492)
           4446 POP_TOP
           4448 STORE_FAST              31 (e)
           4450 POP_TOP
           4452 SETUP_FINALLY           15 (to 4484)

822        4454 LOAD_GLOBAL             15 (print)
           4456 LOAD_CONST             221 ('[PatientReport] Failed to save PDF: ')
           4458 LOAD_FAST               31 (e)
           4460 FORMAT_VALUE             0
           4462 BUILD_STRING             2
           4464 CALL_FUNCTION            1
           4466 POP_TOP

823        4468 LOAD_FAST              130 (out_path)
           4470 POP_BLOCK
           4472 ROT_FOUR
           4474 POP_EXCEPT
           4476 LOAD_CONST               0 (None)
           4478 STORE_FAST              31 (e)
           4480 DELETE_FAST             31 (e)
           4482 RETURN_VALUE
        >> 4484 LOAD_CONST               0 (None)
           4486 STORE_FAST              31 (e)
           4488 DELETE_FAST             31 (e)
           4490 RERAISE                  1

821     >> 4492 RERAISE                  0

Disassembly of <code object _resource_path at 0x0000026C8AA32340, file "patient_report.py", line 432>:
433           0 SETUP_FINALLY            5 (to 12)
              2 LOAD_DEREF               1 (sys)
              4 LOAD_ATTR                0 (_MEIPASS)
              6 STORE_FAST               1 (base_path)
              8 POP_BLOCK
             10 JUMP_FORWARD            15 (to 42)

434     >>   12 DUP_TOP
             14 LOAD_GLOBAL              1 (Exception)
             16 JUMP_IF_NOT_EXC_MATCH    20 (to 40)
             18 POP_TOP
             20 POP_TOP
             22 POP_TOP
             24 LOAD_DEREF               0 (os)
             26 LOAD_ATTR                2 (path)
             28 LOAD_METHOD              3 (abspath)
             30 LOAD_CONST               1 ('.')
             32 CALL_METHOD              1
             34 STORE_FAST               1 (base_path)
             36 POP_EXCEPT
             38 JUMP_FORWARD             1 (to 42)
        >>   40 RERAISE                  0

435     >>   42 LOAD_DEREF               0 (os)
             44 LOAD_ATTR                2 (path)
             46 LOAD_METHOD              4 (join)
             48 LOAD_FAST                1 (base_path)
             50 LOAD_FAST                0 (relative_path)
             52 CALL_METHOD              2
             54 RETURN_VALUE

Disassembly of <code object _fmt_cv at 0x0000026C8AA32760, file "patient_report.py", line 659>:
660           0 LOAD_FAST                0 (val)
              2 LOAD_CONST               1 ('N/A')
              4 COMPARE_OP               2 (==)
              6 POP_JUMP_IF_TRUE         8 (to 16)
              8 LOAD_FAST                0 (val)
             10 LOAD_CONST               0 (None)
             12 IS_OP                    0
             14 POP_JUMP_IF_FALSE       10 (to 20)

661     >>   16 LOAD_CONST               1 ('N/A')
             18 RETURN_VALUE

662     >>   20 LOAD_FAST                0 (val)
             22 LOAD_CONST               2 ('.0f')
             24 FORMAT_VALUE             4 (with format)
             26 RETURN_VALUE

Disassembly of <code object <listcomp> at 0x0000026C8AA32810, file "patient_report.py", line 699>:
699           0 BUILD_LIST               0
              2 LOAD_FAST                0 (.0)
        >>    4 FOR_ITER                 6 (to 18)
              6 STORE_FAST               1 (k)
              8 LOAD_DEREF               0 (pos_stats)
             10 LOAD_FAST                1 (k)
             12 BINARY_SUBSCR
             14 LIST_APPEND              2
             16 JUMP_ABSOLUTE            2 (to 4)
        >>   18 RETURN_VALUE

Disassembly of <code object <listcomp> at 0x0000026C8AA328C0, file "patient_report.py", line 703>:
703           0 BUILD_LIST               0
              2 LOAD_FAST                0 (.0)
        >>    4 FOR_ITER                 7 (to 20)
              6 STORE_FAST               1 (l)
              8 LOAD_GLOBAL              0 (_t)
             10 LOAD_FAST                1 (l)
             12 LOAD_DEREF               0 (lang)
             14 CALL_FUNCTION            2
             16 LIST_APPEND              2
             18 JUMP_ABSOLUTE            2 (to 4)
        >>   20 RETURN_VALUE

Disassembly of <code object <listcomp> at 0x0000026C8AA32970, file "patient_report.py", line 748>:
748           0 BUILD_LIST               0
              2 LOAD_FAST                0 (.0)
        >>    4 FOR_ITER                 6 (to 18)
              6 STORE_FAST               1 (n)
              8 LOAD_GLOBAL              0 (get_display)
             10 LOAD_FAST                1 (n)
             12 CALL_FUNCTION            1
             14 LIST_APPEND              2
             16 JUMP_ABSOLUTE            2 (to 4)
        >>   18 RETURN_VALUE

Disassembly of <code object <listcomp> at 0x0000026C8AA32A20, file "patient_report.py", line 780>:
780           0 BUILD_LIST               0
              2 LOAD_FAST                0 (.0)
        >>    4 FOR_ITER                 6 (to 18)
              6 STORE_FAST               1 (line)
              8 LOAD_GLOBAL              0 (get_display)
             10 LOAD_FAST                1 (line)
             12 CALL_FUNCTION            1
             14 LIST_APPEND              2
             16 JUMP_ABSOLUTE            2 (to 4)
        >>   18 RETURN_VALUE

Disassembly of <code object <listcomp> at 0x0000026C8AA32AD0, file "patient_report.py", line 795>:
795           0 BUILD_LIST               0
              2 LOAD_FAST                0 (.0)
        >>    4 FOR_ITER                 6 (to 18)
              6 STORE_FAST               1 (line)
              8 LOAD_GLOBAL              0 (get_display)
             10 LOAD_FAST                1 (line)
             12 CALL_FUNCTION            1
             14 LIST_APPEND              2
             16 JUMP_ABSOLUTE            2 (to 4)
        >>   18 RETURN_VALUE

--- generate_patient_report ---
828           0 LOAD_GLOBAL              0 (_generate_single_report)
              2 LOAD_CONST               6 (())
              4 LOAD_CONST               1 ('subject_name')
              6 LOAD_FAST                0 (subject_name)
              8 BUILD_MAP                1
             10 LOAD_FAST                1 (kwargs)
             12 DICT_MERGE               1
             14 LOAD_CONST               2 ('lang')
             16 LOAD_CONST               3 ('en')
             18 BUILD_MAP                1
             20 DICT_MERGE               1
             22 CALL_FUNCTION_EX         1
             24 STORE_FAST               2 (out_en)

829          26 LOAD_GLOBAL              0 (_generate_single_report)
             28 LOAD_CONST               6 (())
             30 LOAD_CONST               1 ('subject_name')
             32 LOAD_FAST                0 (subject_name)
             34 BUILD_MAP                1
             36 LOAD_FAST                1 (kwargs)
             38 DICT_MERGE               1
             40 LOAD_CONST               2 ('lang')
             42 LOAD_CONST               4 ('he')
             44 BUILD_MAP                1
             46 DICT_MERGE               1
             48 CALL_FUNCTION_EX         1
             50 POP_TOP

830          52 LOAD_FAST                2 (out_en)
             54 RETURN_VALUE
